Workbook
Name SegmentaciónDeDatos_Proveedor: #N/A
Name SegmentaciónDeDatos_RUBRO: #N/A
Name SegmentaciónDeDatos_SUBRUBRO: #N/A
Name SegmentaciónDeDatos_Tipo_de_insumo: #N/A

Sheet Insumos y gastos
C4: Tabla de insumos | J4: Tabla de costo de tintas
C5: Organiza los costos de tus insumos, nombres de proveedores y cantidades ❤ | J5: Por modelo de impresora ❤
J6: Nombre impresora | L6: Nombre impresora | N6: Nombre impresora | P6: Nombre Impresora | R6: Nombre Impresora | T6: Nombre impresora
J7: Color | K7: Precio | L7: Color | M7: Precio | N7: Color | O7: Precio | P7: Color | Q7: Precio | R7: Color | S7: Precio | T7: Color | U7: Precio
J8: Magenta | L8: Magenta | N8: Magenta | P8: Magenta | R8: Magenta | T8: Magenta
J9: Cyan | L9: Cyan | N9: Cyan | P9: Cyan | R9: Cyan | T9: Cyan
J10: Amarillo | L10: Amarillo | N10: Amarillo | P10: Amarillo | R10: Amarillo | T10: Amarillo
J11: Negro | L11: Negro | N11: Negro | P11: Negro | R11: Negro | T11: Negro
J12: Total | K12: =SUM(K8:K11) -> 0 | L12: Total | M12: =SUM(M8:M11) -> 0 | N12: Total | O12: =SUM(O8:O11) -> 0 | P12: Total | Q12: =SUM(Q8:Q11) -> 0 | R12: Total | S12: =SUM(S8:S11) -> 0 | T12: Total | U12: =SUM(U8:U11) -> 0
C13: Tipo de insumo | D13: Proveedor | E13: Nombre insumo | F13: Cant. Bulto | G13: Pr. costo bulto | H13: Pr. Unidad | J13: Cantidad impresa | L13: Cantidad impresa | N13: Cantidad impresa | P13: Cantidad impresa | R13: Cantidad impresa | T13: Cantidad impresa
B14: =Tabla1[[#This Row],[Nombre insumo]] -> Boreal Obra 80gr | C14: PAPEL | D14: EYPAPEL! | E14: Boreal Obra 80gr | F14: 500 | G14: 6683 | H14: =Tabla1[[#This Row],[Pr. costo bulto]]/Tabla1[[#This Row],[Cant. Bulto]] -> 13.366 | J14: Valor por hoja | K14: =K12/K13 -> #DIV/0! | L14: Valor por hoja | M14: =M12/M13 -> #DIV/0! | N14: Valor por hoja | O14: =O12/O13 -> #DIV/0! | P14: Valor por hoja | Q14: =Q12/Q13 -> #DIV/0! | R14: Valor por hoja | S14: =S12/S13 -> #DIV/0! | T14: Valor por hoja | U14: =U12/U13 -> #DIV/0!
B15: =Tabla1[[#This Row],[Nombre insumo]] -> 0 | H15: =Tabla1[[#This Row],[Pr. costo bulto]]/Tabla1[[#This Row],[Cant. Bulto]] -> #DIV/0! | J15: Valor con desgaste | L15: Valor con desgaste | N15: Valor con desgaste | P15: Valor con desgaste | R15: Valor con desgaste | T15: Valor con desgaste
B16: =Tabla1[[#This Row],[Nombre insumo]] -> 0 | H16: =Tabla1[[#This Row],[Pr. costo bulto]]/Tabla1[[#This Row],[Cant. Bulto]] -> #DIV/0!
B17: =Tabla1[[#This Row],[Nombre insumo]] -> 0 | H17: =Tabla1[[#This Row],[Pr. costo bulto]]/Tabla1[[#This Row],[Cant. Bulto]] -> #DIV/0!
B18: =Tabla1[[#This Row],[Nombre insumo]] -> 0 | H18: =Tabla1[[#This Row],[Pr. costo bulto]]/Tabla1[[#This Row],[Cant. Bulto]] -> #DIV/0!
B19: =Tabla1[[#This Row],[Nombre insumo]] -> 0 | H19: =Tabla1[[#This Row],[Pr. costo bulto]]/Tabla1[[#This Row],[Cant. Bulto]] -> #DIV/0!
B20: =Tabla1[[#This Row],[Nombre insumo]] -> 0 | H20: =Tabla1[[#This Row],[Pr. costo bulto]]/Tabla1[[#This Row],[Cant. Bulto]] -> #DIV/0! | J20: Tabla de costos | P20: Mano de obra
B21: =Tabla1[[#This Row],[Nombre insumo]] -> 0 | H21: =Tabla1[[#This Row],[Pr. costo bulto]]/Tabla1[[#This Row],[Cant. Bulto]] -> #DIV/0!
B22: =Tabla1[[#This Row],[Nombre insumo]] -> 0 | H22: =Tabla1[[#This Row],[Pr. costo bulto]]/Tabla1[[#This Row],[Cant. Bulto]] -> #DIV/0! | J22: Los costos fijos mensuales organizados ❤ | P22: Valorá tu tiempo y tu trabajo ❤
B23: =Tabla1[[#This Row],[Nombre insumo]] -> 0 | H23: =Tabla1[[#This Row],[Pr. costo bulto]]/Tabla1[[#This Row],[Cant. Bulto]] -> #DIV/0!
B24: =Tabla1[[#This Row],[Nombre insumo]] -> 0 | H24: =Tabla1[[#This Row],[Pr. costo bulto]]/Tabla1[[#This Row],[Cant. Bulto]] -> #DIV/0! | J24: Tipo de costo | K24: Valor mensual | L24: Por día | M24: Por hora (*) | P24: Valor por hora
B25: =Tabla1[[#This Row],[Nombre insumo]] -> 0 | H25: =Tabla1[[#This Row],[Pr. costo bulto]]/Tabla1[[#This Row],[Cant. Bulto]] -> #DIV/0! | J25: - | L25: =K25/30 -> 0 | M25: =L25/10 -> 0 | P25: Valor por dia | Q25: =Q24*10 -> 0
B26: =Tabla1[[#This Row],[Nombre insumo]] -> 0 | H26: =Tabla1[[#This Row],[Pr. costo bulto]]/Tabla1[[#This Row],[Cant. Bulto]] -> #DIV/0! | J26: - | L26: =K26/30 -> 0 | M26: =L26/10 -> 0 | P26: Valor por semana | Q26: =Q25*5 -> 0
B27: =Tabla1[[#This Row],[Nombre insumo]] -> 0 | H27: =Tabla1[[#This Row],[Pr. costo bulto]]/Tabla1[[#This Row],[Cant. Bulto]] -> #DIV/0! | J27: - | L27: =K27/30 -> 0 | M27: =L27/10 -> 0 | P27: Valor por mes | Q27: =Q25*20 -> 0
B28: =Tabla1[[#This Row],[Nombre insumo]] -> 0 | H28: =Tabla1[[#This Row],[Pr. costo bulto]]/Tabla1[[#This Row],[Cant. Bulto]] -> #DIV/0! | J28: - | L28: =K28/30 -> 0 | M28: =L28/10 -> 0 | P28: (*) Calculado en base a 10 horas de trabajo 5 dias a la semana
B29: =Tabla1[[#This Row],[Nombre insumo]] -> 0 | H29: =Tabla1[[#This Row],[Pr. costo bulto]]/Tabla1[[#This Row],[Cant. Bulto]] -> #DIV/0! | J29: - | L29: =K29/30 -> 0 | M29: =L29/10 -> 0
B30: =Tabla1[[#This Row],[Nombre insumo]] -> 0 | H30: =Tabla1[[#This Row],[Pr. costo bulto]]/Tabla1[[#This Row],[Cant. Bulto]] -> #DIV/0! | J30: - | L30: =K30/30 -> 0 | M30: =L30/10 -> 0
B31: =Tabla1[[#This Row],[Nombre insumo]] -> 0 | H31: =Tabla1[[#This Row],[Pr. costo bulto]]/Tabla1[[#This Row],[Cant. Bulto]] -> #DIV/0! | J31: - | L31: =K31/30 -> 0 | M31: =L31/10 -> 0
B32: =Tabla1[[#This Row],[Nombre insumo]] -> 0 | H32: =Tabla1[[#This Row],[Pr. costo bulto]]/Tabla1[[#This Row],[Cant. Bulto]] -> #DIV/0! | J32: - | L32: =K32/30 -> 0 | M32: =L32/10 -> 0
B33: =Tabla1[[#This Row],[Nombre insumo]] -> 0 | H33: =Tabla1[[#This Row],[Pr. costo bulto]]/Tabla1[[#This Row],[Cant. Bulto]] -> #DIV/0! | J33: - | L33: =K33/30 -> 0 | M33: =L33/10 -> 0
B34: =Tabla1[[#This Row],[Nombre insumo]] -> 0 | H34: =Tabla1[[#This Row],[Pr. costo bulto]]/Tabla1[[#This Row],[Cant. Bulto]] -> #DIV/0! | J34: - | L34: =K34/30 -> 0 | M34: =L34/10 -> 0
B35: =Tabla1[[#This Row],[Nombre insumo]] -> 0 | H35: =Tabla1[[#This Row],[Pr. costo bulto]]/Tabla1[[#This Row],[Cant. Bulto]] -> #DIV/0! | J35: - | L35: =K35/30 -> 0 | M35: =L35/10 -> 0
B36: =Tabla1[[#This Row],[Nombre insumo]] -> 0 | H36: =Tabla1[[#This Row],[Pr. costo bulto]]/Tabla1[[#This Row],[Cant. Bulto]] -> #DIV/0! | J36: - | L36: =K36/30 -> 0 | M36: =L36/10 -> 0
B37: =Tabla1[[#This Row],[Nombre insumo]] -> 0 | H37: =Tabla1[[#This Row],[Pr. costo bulto]]/Tabla1[[#This Row],[Cant. Bulto]] -> #DIV/0! | J37: - | L37: =K37/30 -> 0 | M37: =L37/10 -> 0
B38: =Tabla1[[#This Row],[Nombre insumo]] -> 0 | H38: =Tabla1[[#This Row],[Pr. costo bulto]]/Tabla1[[#This Row],[Cant. Bulto]] -> #DIV/0! | J38: - | L38: =K38/30 -> 0 | M38: =L38/10 -> 0
B39: =Tabla1[[#This Row],[Nombre insumo]] -> 0 | H39: =Tabla1[[#This Row],[Pr. costo bulto]]/Tabla1[[#This Row],[Cant. Bulto]] -> #DIV/0! | J39: - | L39: =K39/30 -> 0 | M39: =L39/10 -> 0
B40: =Tabla1[[#This Row],[Nombre insumo]] -> 0 | H40: =Tabla1[[#This Row],[Pr. costo bulto]]/Tabla1[[#This Row],[Cant. Bulto]] -> #DIV/0! | J40: - | L40: =K40/30 -> 0 | M40: =L40/10 -> 0
... B49: =Tabla1[[#This Row],[Nombre insumo]] -> 0 | H49: =Tabla1[[#This Row],[Pr. costo bulto]]/Tabla1[[#This Row],[Cant. Bulto]] -> #DIV/0! | J49: - | L49: =K49/30 -> 0 | M49: =L49/10 -> 0
B50: =Tabla1[[#This Row],[Nombre insumo]] -> 0 | H50: =Tabla1[[#This Row],[Pr. costo bulto]]/Tabla1[[#This Row],[Cant. Bulto]] -> #DIV/0! | J50: Total | L50: =SUM(L25:L49) -> 0 | M50: =SUM(M25:M49) -> 0
B51: =Tabla1[[#This Row],[Nombre insumo]] -> 0 | H51: =Tabla1[[#This Row],[Pr. costo bulto]]/Tabla1[[#This Row],[Cant. Bulto]] -> #DIV/0! | J51: (*) Calculado en base a 10 horas de trabajo
B52: =Tabla1[[#This Row],[Nombre insumo]] -> 0 | H52: =Tabla1[[#This Row],[Pr. costo bulto]]/Tabla1[[#This Row],[Cant. Bulto]] -> #DIV/0!
B53: =Tabla1[[#This Row],[Nombre insumo]] -> 0 | H53: =Tabla1[[#This Row],[Pr. costo bulto]]/Tabla1[[#This Row],[Cant. Bulto]] -> #DIV/0!
B54: =Tabla1[[#This Row],[Nombre insumo]] -> 0 | H54: =Tabla1[[#This Row],[Pr. costo bulto]]/Tabla1[[#This Row],[Cant. Bulto]] -> #DIV/0!
B55: =Tabla1[[#This Row],[Nombre insumo]] -> 0 | H55: =Tabla1[[#This Row],[Pr. costo bulto]]/Tabla1[[#This Row],[Cant. Bulto]] -> #DIV/0!
B56: Rollo laminado mate metro | H56: =Tabla1[[#This Row],[Pr. costo bulto]]/Tabla1[[#This Row],[Cant. Bulto]] -> #DIV/0!
B57: =Tabla1[[#This Row],[Nombre insumo]] -> 0 | H57: =Tabla1[[#This Row],[Pr. costo bulto]]/Tabla1[[#This Row],[Cant. Bulto]] -> #DIV/0!
B58: =Tabla1[[#This Row],[Nombre insumo]] -> 0 | H58: =Tabla1[[#This Row],[Pr. costo bulto]]/Tabla1[[#This Row],[Cant. Bulto]] -> #DIV/0!
B59: =Tabla1[[#This Row],[Nombre insumo]] -> 0 | H59: =Tabla1[[#This Row],[Pr. costo bulto]]/Tabla1[[#This Row],[Cant. Bulto]] -> #DIV/0!
B60: =Tabla1[[#This Row],[Nombre insumo]] -> 0 | H60: =Tabla1[[#This Row],[Pr. costo bulto]]/Tabla1[[#This Row],[Cant. Bulto]] -> #DIV/0!
B61: =Tabla1[[#This Row],[Nombre insumo]] -> 0 | H61: =Tabla1[[#This Row],[Pr. costo bulto]]/Tabla1[[#This Row],[Cant. Bulto]] -> #DIV/0!
B62: =Tabla1[[#This Row],[Nombre insumo]] -> 0 | H62: =Tabla1[[#This Row],[Pr. costo bulto]]/Tabla1[[#This Row],[Cant. Bulto]] -> #DIV/0!
B63: =Tabla1[[#This Row],[Nombre insumo]] -> 0 | H63: =Tabla1[[#This Row],[Pr. costo bulto]]/Tabla1[[#This Row],[Cant. Bulto]] -> #DIV/0!
B64: =Tabla1[[#This Row],[Nombre insumo]] -> 0 | H64: =Tabla1[[#This Row],[Pr. costo bulto]]/Tabla1[[#This Row],[Cant. Bulto]] -> #DIV/0!
B65: =Tabla1[[#This Row],[Nombre insumo]] -> 0 | H65: =Tabla1[[#This Row],[Pr. costo bulto]]/Tabla1[[#This Row],[Cant. Bulto]] -> #DIV/0!
B66: =Tabla1[[#This Row],[Nombre insumo]] -> 0 | H66: =Tabla1[[#This Row],[Pr. costo bulto]]/Tabla1[[#This Row],[Cant. Bulto]] -> #DIV/0!
B67: =Tabla1[[#This Row],[Nombre insumo]] -> #VALUE!
B68: =Tabla1[[#This Row],[Nombre insumo]] -> #VALUE!
B69: =Tabla1[[#This Row],[Nombre insumo]] -> #VALUE!
B70: =Tabla1[[#This Row],[Nombre insumo]] -> #VALUE!
B71: =Tabla1[[#This Row],[Nombre insumo]] -> #VALUE!
B72: =Tabla1[[#This Row],[Nombre insumo]] -> #VALUE!
B73: =Tabla1[[#This Row],[Nombre insumo]] -> #VALUE!
B74: =Tabla1[[#This Row],[Nombre insumo]] -> #VALUE!
B75: =Tabla1[[#This Row],[Nombre insumo]] -> #VALUE!
B76: =Tabla1[[#This Row],[Nombre insumo]] -> #VALUE!
B77: =Tabla1[[#This Row],[Nombre insumo]] -> #VALUE!
B78: =Tabla1[[#This Row],[Nombre insumo]] -> #VALUE!
... B1390: =Tabla1[[#This Row],[Nombre insumo]] -> #VALUE!

Sheet Calculadora de costos
J2: Calculadora
J3: Calcula el valor de cualquier presupuesto o producto teniendo en cuenta todos los costos ❤
J5: Insumos | K5: Tipo de insumo | L5: Costo insumo | M5: Cantidad | N5: Total costo insumo | O5: Doble faz | P5: Impresora | Q5: Costo impresión | R5: Total insumo + impresión
A6: SI | I6: EPSON L4260 | K6: =IFERROR(VLOOKUP(J6,'Insumos y gastos'!$B$13:$C$83,2,0),"") -> 0 | L6: =IFERROR(VLOOKUP(J6,Tabla1[[#All],[Nombre insumo]:[Pr. Unidad]],4,0),0) -> 0 | N6: =Tabla2[[#This Row],[Cantidad]]*Tabla2[[#This Row],[Costo insumo]] -> 0 | Q6: =IF(AND(Tabla2[[#This Row],[Tipo de insumo]]="PAPEL",Tabla2[[#This Row],[Doble faz]]="SI",Tabla2[[#This Row],[Impresora]]='Insumos y gastos'!$J$6),M6*'Insumos y gastos'!$K$15*2,IF(AND(Tabla2[[#This Row],[Tipo de insumo]]="PAPEL",Tabla2[[#This Row],[Doble faz]]="SI",Tabla2[[#This Row],[Impresora]]='Insumos y gastos'!$L$6),M6*'Insumos y gastos'!$M$15*2,IF(AND(Tabla2[[#This Row],[Tipo de insumo]]="PAPEL",Tabla2[[#This Row],[Doble faz]]="SI",Tabla2[[#This Row],[Impresora]]='Insumos y gastos'!$N$6),M6*'Insumos y gastos'!$O$15*2,IF(AND(Tabla2[[#This Row],[Tipo de insumo]]="PAPEL",Tabla2[[#This Row],[Doble faz]]="SI",Tabla2[[#This Row],[Impresora]]='Insumos y gastos'!$P$6),M6*'Insumos y gastos'!$Q$15*2,IF(AND(Tabla2[[#This Row],[Tipo de insumo]]="PAPEL",Tabla2[[#This Row],[Doble faz]]="SI",Tabla2[[#This Row],[Impresora]]='Insumos y gastos'!$R$6),M6*'Insumos y gastos'!$S$15*2,IF(AND(Tabla2[[#This Row],[Tipo de insumo]]="PAPEL",Tabla2[[#This Row],[Doble faz]]="SI",Tabla2[[#This Row],[Impresora]]='Insumos y gastos'!$T$6),M6*'Insumos y gastos'!$U$15*2,IF(AND(Tabla2[[#This Row],[Tipo de insumo]]="PAPEL",Tabla2[[#This Row],[Doble faz]]="NO",Tabla2[[#This Row],[Impresora]]='Insumos y gastos'!$J$6),M6*'Insumos y gastos'!$K$15,IF(AND(Tabla2[[#This Row],[Tipo de insumo]]="PAPEL",Tabla2[[#This Row],[Doble faz]]="NO",Tabla2[[#This Row],[Impresora]]='Insumos y gastos'!$L$6),M6*'Insumos y gastos'!$M$15,IF(AND(Tabla2[[#This Row],[Tipo de insumo]]="PAPEL",Tabla2[[#This Row],[Doble faz]]="NO",Tabla2[[#This Row],[Impresora]]='Insumos y gastos'!$N$6),M6*'Insumos y gastos'!$O$15,IF(AND(Tabla2[[#This Row],[Tipo de insumo]]="PAPEL",Tabla2[[#This Row],[Doble faz]]="NO",Tabla2[[#This Row],[Impresora]]='Insumos y gastos'!$P$6),M6*'Insumos y gastos'!$Q$15,IF(AND(Tabla2[[#This Row],[Tipo de insumo]]="PAPEL",Tabla2[[#This Row],[Doble faz]]="NO",Tabla2[[#This Row],[Impresora]]='Insumos y gastos'!$R$6),M6*'Insumos y gastos'!$S$15,IF(AND(Tabla2[[#This Row],[Tipo de insumo]]="PAPEL",Tabla2[[#This Row],[Doble faz]]="NO",Tabla2[[#This Row],[Impresora]]='Insumos y gastos'!$T$6),M6*'Insumos y gastos'!$U$15,0)))))))))))) -> 0 | R6: =Tabla2[[#This Row],[Costo impresión]]+Tabla2[[#This Row],[Total costo insumo]] -> 0
A7: NO | I7: BROTHER T420W | K7: =IFERROR(VLOOKUP(J7,'Insumos y gastos'!$B$13:$C$83,2,0),"") -> 0 | L7: =IFERROR(VLOOKUP(J7,Tabla1[[#All],[Nombre insumo]:[Pr. Unidad]],4,0),0) -> 0 | N7: =Tabla2[[#This Row],[Cantidad]]*Tabla2[[#This Row],[Costo insumo]] -> 0 | Q7: =IF(AND(Tabla2[[#This Row],[Tipo de insumo]]="PAPEL",Tabla2[[#This Row],[Doble faz]]="SI",Tabla2[[#This Row],[Impresora]]='Insumos y gastos'!$J$6),M7*'Insumos y gastos'!$K$15*2,IF(AND(Tabla2[[#This Row],[Tipo de insumo]]="PAPEL",Tabla2[[#This Row],[Doble faz]]="SI",Tabla2[[#This Row],[Impresora]]='Insumos y gastos'!$L$6),M7*'Insumos y gastos'!$M$15*2,IF(AND(Tabla2[[#This Row],[Tipo de insumo]]="PAPEL",Tabla2[[#This Row],[Doble faz]]="SI",Tabla2[[#This Row],[Impresora]]='Insumos y gastos'!$N$6),M7*'Insumos y gastos'!$O$15*2,IF(AND(Tabla2[[#This Row],[Tipo de insumo]]="PAPEL",Tabla2[[#This Row],[Doble faz]]="SI",Tabla2[[#This Row],[Impresora]]='Insumos y gastos'!$P$6),M7*'Insumos y gastos'!$Q$15*2,IF(AND(Tabla2[[#This Row],[Tipo de insumo]]="PAPEL",Tabla2[[#This Row],[Doble faz]]="SI",Tabla2[[#This Row],[Impresora]]='Insumos y gastos'!$R$6),M7*'Insumos y gastos'!$S$15*2,IF(AND(Tabla2[[#This Row],[Tipo de insumo]]="PAPEL",Tabla2[[#This Row],[Doble faz]]="SI",Tabla2[[#This Row],[Impresora]]='Insumos y gastos'!$T$6),M7*'Insumos y gastos'!$U$15*2,IF(AND(Tabla2[[#This Row],[Tipo de insumo]]="PAPEL",Tabla2[[#This Row],[Doble faz]]="NO",Tabla2[[#This Row],[Impresora]]='Insumos y gastos'!$J$6),M7*'Insumos y gastos'!$K$15,IF(AND(Tabla2[[#This Row],[Tipo de insumo]]="PAPEL",Tabla2[[#This Row],[Doble faz]]="NO",Tabla2[[#This Row],[Impresora]]='Insumos y gastos'!$L$6),M7*'Insumos y gastos'!$M$15,IF(AND(Tabla2[[#This Row],[Tipo de insumo]]="PAPEL",Tabla2[[#This Row],[Doble faz]]="NO",Tabla2[[#This Row],[Impresora]]='Insumos y gastos'!$N$6),M7*'Insumos y gastos'!$O$15,IF(AND(Tabla2[[#This Row],[Tipo de insumo]]="PAPEL",Tabla2[[#This Row],[Doble faz]]="NO",Tabla2[[#This Row],[Impresora]]='Insumos y gastos'!$P$6),M7*'Insumos y gastos'!$Q$15,IF(AND(Tabla2[[#This Row],[Tipo de insumo]]="PAPEL",Tabla2[[#This Row],[Doble faz]]="NO",Tabla2[[#This Row],[Impresora]]='Insumos y gastos'!$R$6),M7*'Insumos y gastos'!$S$15,IF(AND(Tabla2[[#This Row],[Tipo de insumo]]="PAPEL",Tabla2[[#This Row],[Doble faz]]="NO",Tabla2[[#This Row],[Impresora]]='Insumos y gastos'!$T$6),M7*'Insumos y gastos'!$U$15,0)))))))))))) -> 0 | R7: =Tabla2[[#This Row],[Costo impresión]]+Tabla2[[#This Row],[Total costo insumo]] -> 0
I8: EPSON L1250 | K8: =IFERROR(VLOOKUP(J8,'Insumos y gastos'!$B$13:$C$83,2,0),"") -> 0 | L8: =IFERROR(VLOOKUP(J8,Tabla1[[#All],[Nombre insumo]:[Pr. Unidad]],4,0),0) -> 0 | N8: =Tabla2[[#This Row],[Cantidad]]*Tabla2[[#This Row],[Costo insumo]] -> 0 | Q8: =IF(AND(Tabla2[[#This Row],[Tipo de insumo]]="PAPEL",Tabla2[[#This Row],[Doble faz]]="SI",Tabla2[[#This Row],[Impresora]]='Insumos y gastos'!$J$6),M8*'Insumos y gastos'!$K$15*2,IF(AND(Tabla2[[#This Row],[Tipo de insumo]]="PAPEL",Tabla2[[#This Row],[Doble faz]]="SI",Tabla2[[#This Row],[Impresora]]='Insumos y gastos'!$L$6),M8*'Insumos y gastos'!$M$15*2,IF(AND(Tabla2[[#This Row],[Tipo de insumo]]="PAPEL",Tabla2[[#This Row],[Doble faz]]="SI",Tabla2[[#This Row],[Impresora]]='Insumos y gastos'!$N$6),M8*'Insumos y gastos'!$O$15*2,IF(AND(Tabla2[[#This Row],[Tipo de insumo]]="PAPEL",Tabla2[[#This Row],[Doble faz]]="SI",Tabla2[[#This Row],[Impresora]]='Insumos y gastos'!$P$6),M8*'Insumos y gastos'!$Q$15*2,IF(AND(Tabla2[[#This Row],[Tipo de insumo]]="PAPEL",Tabla2[[#This Row],[Doble faz]]="SI",Tabla2[[#This Row],[Impresora]]='Insumos y gastos'!$R$6),M8*'Insumos y gastos'!$S$15*2,IF(AND(Tabla2[[#This Row],[Tipo de insumo]]="PAPEL",Tabla2[[#This Row],[Doble faz]]="SI",Tabla2[[#This Row],[Impresora]]='Insumos y gastos'!$T$6),M8*'Insumos y gastos'!$U$15*2,IF(AND(Tabla2[[#This Row],[Tipo de insumo]]="PAPEL",Tabla2[[#This Row],[Doble faz]]="NO",Tabla2[[#This Row],[Impresora]]='Insumos y gastos'!$J$6),M8*'Insumos y gastos'!$K$15,IF(AND(Tabla2[[#This Row],[Tipo de insumo]]="PAPEL",Tabla2[[#This Row],[Doble faz]]="NO",Tabla2[[#This Row],[Impresora]]='Insumos y gastos'!$L$6),M8*'Insumos y gastos'!$M$15,IF(AND(Tabla2[[#This Row],[Tipo de insumo]]="PAPEL",Tabla2[[#This Row],[Doble faz]]="NO",Tabla2[[#This Row],[Impresora]]='Insumos y gastos'!$N$6),M8*'Insumos y gastos'!$O$15,IF(AND(Tabla2[[#This Row],[Tipo de insumo]]="PAPEL",Tabla2[[#This Row],[Doble faz]]="NO",Tabla2[[#This Row],[Impresora]]='Insumos y gastos'!$P$6),M8*'Insumos y gastos'!$Q$15,IF(AND(Tabla2[[#This Row],[Tipo de insumo]]="PAPEL",Tabla2[[#This Row],[Doble faz]]="NO",Tabla2[[#This Row],[Impresora]]='Insumos y gastos'!$R$6),M8*'Insumos y gastos'!$S$15,IF(AND(Tabla2[[#This Row],[Tipo de insumo]]="PAPEL",Tabla2[[#This Row],[Doble faz]]="NO",Tabla2[[#This Row],[Impresora]]='Insumos y gastos'!$T$6),M8*'Insumos y gastos'!$U$15,0)))))))))))) -> 0 | R8: =Tabla2[[#This Row],[Costo impresión]]+Tabla2[[#This Row],[Total costo insumo]] -> 0
I9: EPSON L1250 SUBLIMACION | K9: =IFERROR(VLOOKUP(J9,'Insumos y gastos'!$B$13:$C$83,2,0),"") -> 0 | L9: =IFERROR(VLOOKUP(J9,Tabla1[[#All],[Nombre insumo]:[Pr. Unidad]],4,0),0) -> 0 | N9: =Tabla2[[#This Row],[Cantidad]]*Tabla2[[#This Row],[Costo insumo]] -> 0 | Q9: =IF(AND(Tabla2[[#This Row],[Tipo de insumo]]="PAPEL",Tabla2[[#This Row],[Doble faz]]="SI",Tabla2[[#This Row],[Impresora]]='Insumos y gastos'!$J$6),M9*'Insumos y gastos'!$K$15*2,IF(AND(Tabla2[[#This Row],[Tipo de insumo]]="PAPEL",Tabla2[[#This Row],[Doble faz]]="SI",Tabla2[[#This Row],[Impresora]]='Insumos y gastos'!$L$6),M9*'Insumos y gastos'!$M$15*2,IF(AND(Tabla2[[#This Row],[Tipo de insumo]]="PAPEL",Tabla2[[#This Row],[Doble faz]]="SI",Tabla2[[#This Row],[Impresora]]='Insumos y gastos'!$N$6),M9*'Insumos y gastos'!$O$15*2,IF(AND(Tabla2[[#This Row],[Tipo de insumo]]="PAPEL",Tabla2[[#This Row],[Doble faz]]="SI",Tabla2[[#This Row],[Impresora]]='Insumos y gastos'!$P$6),M9*'Insumos y gastos'!$Q$15*2,IF(AND(Tabla2[[#This Row],[Tipo de insumo]]="PAPEL",Tabla2[[#This Row],[Doble faz]]="SI",Tabla2[[#This Row],[Impresora]]='Insumos y gastos'!$R$6),M9*'Insumos y gastos'!$S$15*2,IF(AND(Tabla2[[#This Row],[Tipo de insumo]]="PAPEL",Tabla2[[#This Row],[Doble faz]]="SI",Tabla2[[#This Row],[Impresora]]='Insumos y gastos'!$T$6),M9*'Insumos y gastos'!$U$15*2,IF(AND(Tabla2[[#This Row],[Tipo de insumo]]="PAPEL",Tabla2[[#This Row],[Doble faz]]="NO",Tabla2[[#This Row],[Impresora]]='Insumos y gastos'!$J$6),M9*'Insumos y gastos'!$K$15,IF(AND(Tabla2[[#This Row],[Tipo de insumo]]="PAPEL",Tabla2[[#This Row],[Doble faz]]="NO",Tabla2[[#This Row],[Impresora]]='Insumos y gastos'!$L$6),M9*'Insumos y gastos'!$M$15,IF(AND(Tabla2[[#This Row],[Tipo de insumo]]="PAPEL",Tabla2[[#This Row],[Doble faz]]="NO",Tabla2[[#This Row],[Impresora]]='Insumos y gastos'!$N$6),M9*'Insumos y gastos'!$O$15,IF(AND(Tabla2[[#This Row],[Tipo de insumo]]="PAPEL",Tabla2[[#This Row],[Doble faz]]="NO",Tabla2[[#This Row],[Impresora]]='Insumos y gastos'!$P$6),M9*'Insumos y gastos'!$Q$15,IF(AND(Tabla2[[#This Row],[Tipo de insumo]]="PAPEL",Tabla2[[#This Row],[Doble faz]]="NO",Tabla2[[#This Row],[Impresora]]='Insumos y gastos'!$R$6),M9*'Insumos y gastos'!$S$15,IF(AND(Tabla2[[#This Row],[Tipo de insumo]]="PAPEL",Tabla2[[#This Row],[Doble faz]]="NO",Tabla2[[#This Row],[Impresora]]='Insumos y gastos'!$T$6),M9*'Insumos y gastos'!$U$15,0)))))))))))) -> 0 | R9: =Tabla2[[#This Row],[Costo impresión]]+Tabla2[[#This Row],[Total costo insumo]] -> 0
I10: HP M1111W | K10: =IFERROR(VLOOKUP(J10,'Insumos y gastos'!$B$13:$C$83,2,0),"") -> 0 | L10: =IFERROR(VLOOKUP(J10,Tabla1[[#All],[Nombre insumo]:[Pr. Unidad]],4,0),0) -> 0 | N10: =Tabla2[[#This Row],[Cantidad]]*Tabla2[[#This Row],[Costo insumo]] -> 0 | Q10: =IF(AND(Tabla2[[#This Row],[Tipo de insumo]]="PAPEL",Tabla2[[#This Row],[Doble faz]]="SI",Tabla2[[#This Row],[Impresora]]='Insumos y gastos'!$J$6),M10*'Insumos y gastos'!$K$15*2,IF(AND(Tabla2[[#This Row],[Tipo de insumo]]="PAPEL",Tabla2[[#This Row],[Doble faz]]="SI",Tabla2[[#This Row],[Impresora]]='Insumos y gastos'!$L$6),M10*'Insumos y gastos'!$M$15*2,IF(AND(Tabla2[[#This Row],[Tipo de insumo]]="PAPEL",Tabla2[[#This Row],[Doble faz]]="SI",Tabla2[[#This Row],[Impresora]]='Insumos y gastos'!$N$6),M10*'Insumos y gastos'!$O$15*2,IF(AND(Tabla2[[#This Row],[Tipo de insumo]]="PAPEL",Tabla2[[#This Row],[Doble faz]]="SI",Tabla2[[#This Row],[Impresora]]='Insumos y gastos'!$P$6),M10*'Insumos y gastos'!$Q$15*2,IF(AND(Tabla2[[#This Row],[Tipo de insumo]]="PAPEL",Tabla2[[#This Row],[Doble faz]]="SI",Tabla2[[#This Row],[Impresora]]='Insumos y gastos'!$R$6),M10*'Insumos y gastos'!$S$15*2,IF(AND(Tabla2[[#This Row],[Tipo de insumo]]="PAPEL",Tabla2[[#This Row],[Doble faz]]="SI",Tabla2[[#This Row],[Impresora]]='Insumos y gastos'!$T$6),M10*'Insumos y gastos'!$U$15*2,IF(AND(Tabla2[[#This Row],[Tipo de insumo]]="PAPEL",Tabla2[[#This Row],[Doble faz]]="NO",Tabla2[[#This Row],[Impresora]]='Insumos y gastos'!$J$6),M10*'Insumos y gastos'!$K$15,IF(AND(Tabla2[[#This Row],[Tipo de insumo]]="PAPEL",Tabla2[[#This Row],[Doble faz]]="NO",Tabla2[[#This Row],[Impresora]]='Insumos y gastos'!$L$6),M10*'Insumos y gastos'!$M$15,IF(AND(Tabla2[[#This Row],[Tipo de insumo]]="PAPEL",Tabla2[[#This Row],[Doble faz]]="NO",Tabla2[[#This Row],[Impresora]]='Insumos y gastos'!$N$6),M10*'Insumos y gastos'!$O$15,IF(AND(Tabla2[[#This Row],[Tipo de insumo]]="PAPEL",Tabla2[[#This Row],[Doble faz]]="NO",Tabla2[[#This Row],[Impresora]]='Insumos y gastos'!$P$6),M10*'Insumos y gastos'!$Q$15,IF(AND(Tabla2[[#This Row],[Tipo de insumo]]="PAPEL",Tabla2[[#This Row],[Doble faz]]="NO",Tabla2[[#This Row],[Impresora]]='Insumos y gastos'!$R$6),M10*'Insumos y gastos'!$S$15,IF(AND(Tabla2[[#This Row],[Tipo de insumo]]="PAPEL",Tabla2[[#This Row],[Doble faz]]="NO",Tabla2[[#This Row],[Impresora]]='Insumos y gastos'!$T$6),M10*'Insumos y gastos'!$U$15,0)))))))))))) -> 0 | R10: =Tabla2[[#This Row],[Costo impresión]]+Tabla2[[#This Row],[Total costo insumo]] -> 0
K11: =IFERROR(VLOOKUP(J11,'Insumos y gastos'!$B$13:$C$83,2,0),"") -> 0 | L11: =IFERROR(VLOOKUP(J11,Tabla1[[#All],[Nombre insumo]:[Pr. Unidad]],4,0),0) -> 0 | N11: =Tabla2[[#This Row],[Cantidad]]*Tabla2[[#This Row],[Costo insumo]] -> 0 | Q11: =IF(AND(Tabla2[[#This Row],[Tipo de insumo]]="PAPEL",Tabla2[[#This Row],[Doble faz]]="SI",Tabla2[[#This Row],[Impresora]]='Insumos y gastos'!$J$6),M11*'Insumos y gastos'!$K$15*2,IF(AND(Tabla2[[#This Row],[Tipo de insumo]]="PAPEL",Tabla2[[#This Row],[Doble faz]]="SI",Tabla2[[#This Row],[Impresora]]='Insumos y gastos'!$L$6),M11*'Insumos y gastos'!$M$15*2,IF(AND(Tabla2[[#This Row],[Tipo de insumo]]="PAPEL",Tabla2[[#This Row],[Doble faz]]="SI",Tabla2[[#This Row],[Impresora]]='Insumos y gastos'!$N$6),M11*'Insumos y gastos'!$O$15*2,IF(AND(Tabla2[[#This Row],[Tipo de insumo]]="PAPEL",Tabla2[[#This Row],[Doble faz]]="SI",Tabla2[[#This Row],[Impresora]]='Insumos y gastos'!$P$6),M11*'Insumos y gastos'!$Q$15*2,IF(AND(Tabla2[[#This Row],[Tipo de insumo]]="PAPEL",Tabla2[[#This Row],[Doble faz]]="SI",Tabla2[[#This Row],[Impresora]]='Insumos y gastos'!$R$6),M11*'Insumos y gastos'!$S$15*2,IF(AND(Tabla2[[#This Row],[Tipo de insumo]]="PAPEL",Tabla2[[#This Row],[Doble faz]]="SI",Tabla2[[#This Row],[Impresora]]='Insumos y gastos'!$T$6),M11*'Insumos y gastos'!$U$15*2,IF(AND(Tabla2[[#This Row],[Tipo de insumo]]="PAPEL",Tabla2[[#This Row],[Doble faz]]="NO",Tabla2[[#This Row],[Impresora]]='Insumos y gastos'!$J$6),M11*'Insumos y gastos'!$K$15,IF(AND(Tabla2[[#This Row],[Tipo de insumo]]="PAPEL",Tabla2[[#This Row],[Doble faz]]="NO",Tabla2[[#This Row],[Impresora]]='Insumos y gastos'!$L$6),M11*'Insumos y gastos'!$M$15,IF(AND(Tabla2[[#This Row],[Tipo de insumo]]="PAPEL",Tabla2[[#This Row],[Doble faz]]="NO",Tabla2[[#This Row],[Impresora]]='Insumos y gastos'!$N$6),M11*'Insumos y gastos'!$O$15,IF(AND(Tabla2[[#This Row],[Tipo de insumo]]="PAPEL",Tabla2[[#This Row],[Doble faz]]="NO",Tabla2[[#This Row],[Impresora]]='Insumos y gastos'!$P$6),M11*'Insumos y gastos'!$Q$15,IF(AND(Tabla2[[#This Row],[Tipo de insumo]]="PAPEL",Tabla2[[#This Row],[Doble faz]]="NO",Tabla2[[#This Row],[Impresora]]='Insumos y gastos'!$R$6),M11*'Insumos y gastos'!$S$15,IF(AND(Tabla2[[#This Row],[Tipo de insumo]]="PAPEL",Tabla2[[#This Row],[Doble faz]]="NO",Tabla2[[#This Row],[Impresora]]='Insumos y gastos'!$T$6),M11*'Insumos y gastos'!$U$15,0)))))))))))) -> 0 | R11: =Tabla2[[#This Row],[Costo impresión]]+Tabla2[[#This Row],[Total costo insumo]] -> 0
K12: =IFERROR(VLOOKUP(J12,'Insumos y gastos'!$B$13:$C$83,2,0),"") -> 0 | L12: =IFERROR(VLOOKUP(J12,Tabla1[[#All],[Nombre insumo]:[Pr. Unidad]],4,0),0) -> 0 | N12: =Tabla2[[#This Row],[Cantidad]]*Tabla2[[#This Row],[Costo insumo]] -> 0 | Q12: =IF(AND(Tabla2[[#This Row],[Tipo de insumo]]="PAPEL",Tabla2[[#This Row],[Doble faz]]="SI",Tabla2[[#This Row],[Impresora]]='Insumos y gastos'!$J$6),M12*'Insumos y gastos'!$K$15*2,IF(AND(Tabla2[[#This Row],[Tipo de insumo]]="PAPEL",Tabla2[[#This Row],[Doble faz]]="SI",Tabla2[[#This Row],[Impresora]]='Insumos y gastos'!$L$6),M12*'Insumos y gastos'!$M$15*2,IF(AND(Tabla2[[#This Row],[Tipo de insumo]]="PAPEL",Tabla2[[#This Row],[Doble faz]]="SI",Tabla2[[#This Row],[Impresora]]='Insumos y gastos'!$N$6),M12*'Insumos y gastos'!$O$15*2,IF(AND(Tabla2[[#This Row],[Tipo de insumo]]="PAPEL",Tabla2[[#This Row],[Doble faz]]="SI",Tabla2[[#This Row],[Impresora]]='Insumos y gastos'!$P$6),M12*'Insumos y gastos'!$Q$15*2,IF(AND(Tabla2[[#This Row],[Tipo de insumo]]="PAPEL",Tabla2[[#This Row],[Doble faz]]="SI",Tabla2[[#This Row],[Impresora]]='Insumos y gastos'!$R$6),M12*'Insumos y gastos'!$S$15*2,IF(AND(Tabla2[[#This Row],[Tipo de insumo]]="PAPEL",Tabla2[[#This Row],[Doble faz]]="SI",Tabla2[[#This Row],[Impresora]]='Insumos y gastos'!$T$6),M12*'Insumos y gastos'!$U$15*2,IF(AND(Tabla2[[#This Row],[Tipo de insumo]]="PAPEL",Tabla2[[#This Row],[Doble faz]]="NO",Tabla2[[#This Row],[Impresora]]='Insumos y gastos'!$J$6),M12*'Insumos y gastos'!$K$15,IF(AND(Tabla2[[#This Row],[Tipo de insumo]]="PAPEL",Tabla2[[#This Row],[Doble faz]]="NO",Tabla2[[#This Row],[Impresora]]='Insumos y gastos'!$L$6),M12*'Insumos y gastos'!$M$15,IF(AND(Tabla2[[#This Row],[Tipo de insumo]]="PAPEL",Tabla2[[#This Row],[Doble faz]]="NO",Tabla2[[#This Row],[Impresora]]='Insumos y gastos'!$N$6),M12*'Insumos y gastos'!$O$15,IF(AND(Tabla2[[#This Row],[Tipo de insumo]]="PAPEL",Tabla2[[#This Row],[Doble faz]]="NO",Tabla2[[#This Row],[Impresora]]='Insumos y gastos'!$P$6),M12*'Insumos y gastos'!$Q$15,IF(AND(Tabla2[[#This Row],[Tipo de insumo]]="PAPEL",Tabla2[[#This Row],[Doble faz]]="NO",Tabla2[[#This Row],[Impresora]]='Insumos y gastos'!$R$6),M12*'Insumos y gastos'!$S$15,IF(AND(Tabla2[[#This Row],[Tipo de insumo]]="PAPEL",Tabla2[[#This Row],[Doble faz]]="NO",Tabla2[[#This Row],[Impresora]]='Insumos y gastos'!$T$6),M12*'Insumos y gastos'!$U$15,0)))))))))))) -> 0 | R12: =Tabla2[[#This Row],[Costo impresión]]+Tabla2[[#This Row],[Total costo insumo]] -> 0
K13: =IFERROR(VLOOKUP(J13,'Insumos y gastos'!$B$13:$C$83,2,0),"") -> 0 | L13: =IFERROR(VLOOKUP(J13,Tabla1[[#All],[Nombre insumo]:[Pr. Unidad]],4,0),0) -> 0 | N13: =Tabla2[[#This Row],[Cantidad]]*Tabla2[[#This Row],[Costo insumo]] -> 0 | Q13: =IF(AND(Tabla2[[#This Row],[Tipo de insumo]]="PAPEL",Tabla2[[#This Row],[Doble faz]]="SI",Tabla2[[#This Row],[Impresora]]='Insumos y gastos'!$J$6),M13*'Insumos y gastos'!$K$15*2,IF(AND(Tabla2[[#This Row],[Tipo de insumo]]="PAPEL",Tabla2[[#This Row],[Doble faz]]="SI",Tabla2[[#This Row],[Impresora]]='Insumos y gastos'!$L$6),M13*'Insumos y gastos'!$M$15*2,IF(AND(Tabla2[[#This Row],[Tipo de insumo]]="PAPEL",Tabla2[[#This Row],[Doble faz]]="SI",Tabla2[[#This Row],[Impresora]]='Insumos y gastos'!$N$6),M13*'Insumos y gastos'!$O$15*2,IF(AND(Tabla2[[#This Row],[Tipo de insumo]]="PAPEL",Tabla2[[#This Row],[Doble faz]]="SI",Tabla2[[#This Row],[Impresora]]='Insumos y gastos'!$P$6),M13*'Insumos y gastos'!$Q$15*2,IF(AND(Tabla2[[#This Row],[Tipo de insumo]]="PAPEL",Tabla2[[#This Row],[Doble faz]]="SI",Tabla2[[#This Row],[Impresora]]='Insumos y gastos'!$R$6),M13*'Insumos y gastos'!$S$15*2,IF(AND(Tabla2[[#This Row],[Tipo de insumo]]="PAPEL",Tabla2[[#This Row],[Doble faz]]="SI",Tabla2[[#This Row],[Impresora]]='Insumos y gastos'!$T$6),M13*'Insumos y gastos'!$U$15*2,IF(AND(Tabla2[[#This Row],[Tipo de insumo]]="PAPEL",Tabla2[[#This Row],[Doble faz]]="NO",Tabla2[[#This Row],[Impresora]]='Insumos y gastos'!$J$6),M13*'Insumos y gastos'!$K$15,IF(AND(Tabla2[[#This Row],[Tipo de insumo]]="PAPEL",Tabla2[[#This Row],[Doble faz]]="NO",Tabla2[[#This Row],[Impresora]]='Insumos y gastos'!$L$6),M13*'Insumos y gastos'!$M$15,IF(AND(Tabla2[[#This Row],[Tipo de insumo]]="PAPEL",Tabla2[[#This Row],[Doble faz]]="NO",Tabla2[[#This Row],[Impresora]]='Insumos y gastos'!$N$6),M13*'Insumos y gastos'!$O$15,IF(AND(Tabla2[[#This Row],[Tipo de insumo]]="PAPEL",Tabla2[[#This Row],[Doble faz]]="NO",Tabla2[[#This Row],[Impresora]]='Insumos y gastos'!$P$6),M13*'Insumos y gastos'!$Q$15,IF(AND(Tabla2[[#This Row],[Tipo de insumo]]="PAPEL",Tabla2[[#This Row],[Doble faz]]="NO",Tabla2[[#This Row],[Impresora]]='Insumos y gastos'!$R$6),M13*'Insumos y gastos'!$S$15,IF(AND(Tabla2[[#This Row],[Tipo de insumo]]="PAPEL",Tabla2[[#This Row],[Doble faz]]="NO",Tabla2[[#This Row],[Impresora]]='Insumos y gastos'!$T$6),M13*'Insumos y gastos'!$U$15,0)))))))))))) -> 0 | R13: =Tabla2[[#This Row],[Costo impresión]]+Tabla2[[#This Row],[Total costo insumo]] -> 0
K14: =IFERROR(VLOOKUP(J14,'Insumos y gastos'!$B$13:$C$83,2,0),"") -> 0 | L14: =IFERROR(VLOOKUP(J14,Tabla1[[#All],[Nombre insumo]:[Pr. Unidad]],4,0),0) -> 0 | N14: =Tabla2[[#This Row],[Cantidad]]*Tabla2[[#This Row],[Costo insumo]] -> 0 | Q14: =IF(AND(Tabla2[[#This Row],[Tipo de insumo]]="PAPEL",Tabla2[[#This Row],[Doble faz]]="SI",Tabla2[[#This Row],[Impresora]]='Insumos y gastos'!$J$6),M14*'Insumos y gastos'!$K$15*2,IF(AND(Tabla2[[#This Row],[Tipo de insumo]]="PAPEL",Tabla2[[#This Row],[Doble faz]]="SI",Tabla2[[#This Row],[Impresora]]='Insumos y gastos'!$L$6),M14*'Insumos y gastos'!$M$15*2,IF(AND(Tabla2[[#This Row],[Tipo de insumo]]="PAPEL",Tabla2[[#This Row],[Doble faz]]="SI",Tabla2[[#This Row],[Impresora]]='Insumos y gastos'!$N$6),M14*'Insumos y gastos'!$O$15*2,IF(AND(Tabla2[[#This Row],[Tipo de insumo]]="PAPEL",Tabla2[[#This Row],[Doble faz]]="SI",Tabla2[[#This Row],[Impresora]]='Insumos y gastos'!$P$6),M14*'Insumos y gastos'!$Q$15*2,IF(AND(Tabla2[[#This Row],[Tipo de insumo]]="PAPEL",Tabla2[[#This Row],[Doble faz]]="SI",Tabla2[[#This Row],[Impresora]]='Insumos y gastos'!$R$6),M14*'Insumos y gastos'!$S$15*2,IF(AND(Tabla2[[#This Row],[Tipo de insumo]]="PAPEL",Tabla2[[#This Row],[Doble faz]]="SI",Tabla2[[#This Row],[Impresora]]='Insumos y gastos'!$T$6),M14*'Insumos y gastos'!$U$15*2,IF(AND(Tabla2[[#This Row],[Tipo de insumo]]="PAPEL",Tabla2[[#This Row],[Doble faz]]="NO",Tabla2[[#This Row],[Impresora]]='Insumos y gastos'!$J$6),M14*'Insumos y gastos'!$K$15,IF(AND(Tabla2[[#This Row],[Tipo de insumo]]="PAPEL",Tabla2[[#This Row],[Doble faz]]="NO",Tabla2[[#This Row],[Impresora]]='Insumos y gastos'!$L$6),M14*'Insumos y gastos'!$M$15,IF(AND(Tabla2[[#This Row],[Tipo de insumo]]="PAPEL",Tabla2[[#This Row],[Doble faz]]="NO",Tabla2[[#This Row],[Impresora]]='Insumos y gastos'!$N$6),M14*'Insumos y gastos'!$O$15,IF(AND(Tabla2[[#This Row],[Tipo de insumo]]="PAPEL",Tabla2[[#This Row],[Doble faz]]="NO",Tabla2[[#This Row],[Impresora]]='Insumos y gastos'!$P$6),M14*'Insumos y gastos'!$Q$15,IF(AND(Tabla2[[#This Row],[Tipo de insumo]]="PAPEL",Tabla2[[#This Row],[Doble faz]]="NO",Tabla2[[#This Row],[Impresora]]='Insumos y gastos'!$R$6),M14*'Insumos y gastos'!$S$15,IF(AND(Tabla2[[#This Row],[Tipo de insumo]]="PAPEL",Tabla2[[#This Row],[Doble faz]]="NO",Tabla2[[#This Row],[Impresora]]='Insumos y gastos'!$T$6),M14*'Insumos y gastos'!$U$15,0)))))))))))) -> 0 | R14: =Tabla2[[#This Row],[Costo impresión]]+Tabla2[[#This Row],[Total costo insumo]] -> 0
K15: =IFERROR(VLOOKUP(J15,'Insumos y gastos'!$B$13:$C$83,2,0),"") -> 0 | L15: =IFERROR(VLOOKUP(J15,Tabla1[[#All],[Nombre insumo]:[Pr. Unidad]],4,0),0) -> 0 | N15: =Tabla2[[#This Row],[Cantidad]]*Tabla2[[#This Row],[Costo insumo]] -> 0 | Q15: =IF(AND(Tabla2[[#This Row],[Tipo de insumo]]="PAPEL",Tabla2[[#This Row],[Doble faz]]="SI",Tabla2[[#This Row],[Impresora]]='Insumos y gastos'!$J$6),M15*'Insumos y gastos'!$K$15*2,IF(AND(Tabla2[[#This Row],[Tipo de insumo]]="PAPEL",Tabla2[[#This Row],[Doble faz]]="SI",Tabla2[[#This Row],[Impresora]]='Insumos y gastos'!$L$6),M15*'Insumos y gastos'!$M$15*2,IF(AND(Tabla2[[#This Row],[Tipo de insumo]]="PAPEL",Tabla2[[#This Row],[Doble faz]]="SI",Tabla2[[#This Row],[Impresora]]='Insumos y gastos'!$N$6),M15*'Insumos y gastos'!$O$15*2,IF(AND(Tabla2[[#This Row],[Tipo de insumo]]="PAPEL",Tabla2[[#This Row],[Doble faz]]="SI",Tabla2[[#This Row],[Impresora]]='Insumos y gastos'!$P$6),M15*'Insumos y gastos'!$Q$15*2,IF(AND(Tabla2[[#This Row],[Tipo de insumo]]="PAPEL",Tabla2[[#This Row],[Doble faz]]="SI",Tabla2[[#This Row],[Impresora]]='Insumos y gastos'!$R$6),M15*'Insumos y gastos'!$S$15*2,IF(AND(Tabla2[[#This Row],[Tipo de insumo]]="PAPEL",Tabla2[[#This Row],[Doble faz]]="SI",Tabla2[[#This Row],[Impresora]]='Insumos y gastos'!$T$6),M15*'Insumos y gastos'!$U$15*2,IF(AND(Tabla2[[#This Row],[Tipo de insumo]]="PAPEL",Tabla2[[#This Row],[Doble faz]]="NO",Tabla2[[#This Row],[Impresora]]='Insumos y gastos'!$J$6),M15*'Insumos y gastos'!$K$15,IF(AND(Tabla2[[#This Row],[Tipo de insumo]]="PAPEL",Tabla2[[#This Row],[Doble faz]]="NO",Tabla2[[#This Row],[Impresora]]='Insumos y gastos'!$L$6),M15*'Insumos y gastos'!$M$15,IF(AND(Tabla2[[#This Row],[Tipo de insumo]]="PAPEL",Tabla2[[#This Row],[Doble faz]]="NO",Tabla2[[#This Row],[Impresora]]='Insumos y gastos'!$N$6),M15*'Insumos y gastos'!$O$15,IF(AND(Tabla2[[#This Row],[Tipo de insumo]]="PAPEL",Tabla2[[#This Row],[Doble faz]]="NO",Tabla2[[#This Row],[Impresora]]='Insumos y gastos'!$P$6),M15*'Insumos y gastos'!$Q$15,IF(AND(Tabla2[[#This Row],[Tipo de insumo]]="PAPEL",Tabla2[[#This Row],[Doble faz]]="NO",Tabla2[[#This Row],[Impresora]]='Insumos y gastos'!$R$6),M15*'Insumos y gastos'!$S$15,IF(AND(Tabla2[[#This Row],[Tipo de insumo]]="PAPEL",Tabla2[[#This Row],[Doble faz]]="NO",Tabla2[[#This Row],[Impresora]]='Insumos y gastos'!$T$6),M15*'Insumos y gastos'!$U$15,0)))))))))))) -> 0 | R15: =Tabla2[[#This Row],[Costo impresión]]+Tabla2[[#This Row],[Total costo insumo]] -> 0
K16: =IFERROR(VLOOKUP(J16,'Insumos y gastos'!$B$13:$C$83,2,0),"") -> 0 | L16: =IFERROR(VLOOKUP(J16,Tabla1[[#All],[Nombre insumo]:[Pr. Unidad]],4,0),0) -> 0 | N16: =Tabla2[[#This Row],[Cantidad]]*Tabla2[[#This Row],[Costo insumo]] -> 0 | Q16: =IF(AND(Tabla2[[#This Row],[Tipo de insumo]]="PAPEL",Tabla2[[#This Row],[Doble faz]]="SI",Tabla2[[#This Row],[Impresora]]='Insumos y gastos'!$J$6),M16*'Insumos y gastos'!$K$15*2,IF(AND(Tabla2[[#This Row],[Tipo de insumo]]="PAPEL",Tabla2[[#This Row],[Doble faz]]="SI",Tabla2[[#This Row],[Impresora]]='Insumos y gastos'!$L$6),M16*'Insumos y gastos'!$M$15*2,IF(AND(Tabla2[[#This Row],[Tipo de insumo]]="PAPEL",Tabla2[[#This Row],[Doble faz]]="SI",Tabla2[[#This Row],[Impresora]]='Insumos y gastos'!$N$6),M16*'Insumos y gastos'!$O$15*2,IF(AND(Tabla2[[#This Row],[Tipo de insumo]]="PAPEL",Tabla2[[#This Row],[Doble faz]]="SI",Tabla2[[#This Row],[Impresora]]='Insumos y gastos'!$P$6),M16*'Insumos y gastos'!$Q$15*2,IF(AND(Tabla2[[#This Row],[Tipo de insumo]]="PAPEL",Tabla2[[#This Row],[Doble faz]]="SI",Tabla2[[#This Row],[Impresora]]='Insumos y gastos'!$R$6),M16*'Insumos y gastos'!$S$15*2,IF(AND(Tabla2[[#This Row],[Tipo de insumo]]="PAPEL",Tabla2[[#This Row],[Doble faz]]="SI",Tabla2[[#This Row],[Impresora]]='Insumos y gastos'!$T$6),M16*'Insumos y gastos'!$U$15*2,IF(AND(Tabla2[[#This Row],[Tipo de insumo]]="PAPEL",Tabla2[[#This Row],[Doble faz]]="NO",Tabla2[[#This Row],[Impresora]]='Insumos y gastos'!$J$6),M16*'Insumos y gastos'!$K$15,IF(AND(Tabla2[[#This Row],[Tipo de insumo]]="PAPEL",Tabla2[[#This Row],[Doble faz]]="NO",Tabla2[[#This Row],[Impresora]]='Insumos y gastos'!$L$6),M16*'Insumos y gastos'!$M$15,IF(AND(Tabla2[[#This Row],[Tipo de insumo]]="PAPEL",Tabla2[[#This Row],[Doble faz]]="NO",Tabla2[[#This Row],[Impresora]]='Insumos y gastos'!$N$6),M16*'Insumos y gastos'!$O$15,IF(AND(Tabla2[[#This Row],[Tipo de insumo]]="PAPEL",Tabla2[[#This Row],[Doble faz]]="NO",Tabla2[[#This Row],[Impresora]]='Insumos y gastos'!$P$6),M16*'Insumos y gastos'!$Q$15,IF(AND(Tabla2[[#This Row],[Tipo de insumo]]="PAPEL",Tabla2[[#This Row],[Doble faz]]="NO",Tabla2[[#This Row],[Impresora]]='Insumos y gastos'!$R$6),M16*'Insumos y gastos'!$S$15,IF(AND(Tabla2[[#This Row],[Tipo de insumo]]="PAPEL",Tabla2[[#This Row],[Doble faz]]="NO",Tabla2[[#This Row],[Impresora]]='Insumos y gastos'!$T$6),M16*'Insumos y gastos'!$U$15,0)))))))))))) -> 0 | R16: =Tabla2[[#This Row],[Costo impresión]]+Tabla2[[#This Row],[Total costo insumo]] -> 0
K17: =IFERROR(VLOOKUP(J17,'Insumos y gastos'!$B$13:$C$83,2,0),"") -> 0 | L17: =IFERROR(VLOOKUP(J17,Tabla1[[#All],[Nombre insumo]:[Pr. Unidad]],4,0),0) -> 0 | N17: =Tabla2[[#This Row],[Cantidad]]*Tabla2[[#This Row],[Costo insumo]] -> 0 | Q17: =IF(AND(Tabla2[[#This Row],[Tipo de insumo]]="PAPEL",Tabla2[[#This Row],[Doble faz]]="SI",Tabla2[[#This Row],[Impresora]]='Insumos y gastos'!$J$6),M17*'Insumos y gastos'!$K$15*2,IF(AND(Tabla2[[#This Row],[Tipo de insumo]]="PAPEL",Tabla2[[#This Row],[Doble faz]]="SI",Tabla2[[#This Row],[Impresora]]='Insumos y gastos'!$L$6),M17*'Insumos y gastos'!$M$15*2,IF(AND(Tabla2[[#This Row],[Tipo de insumo]]="PAPEL",Tabla2[[#This Row],[Doble faz]]="SI",Tabla2[[#This Row],[Impresora]]='Insumos y gastos'!$N$6),M17*'Insumos y gastos'!$O$15*2,IF(AND(Tabla2[[#This Row],[Tipo de insumo]]="PAPEL",Tabla2[[#This Row],[Doble faz]]="SI",Tabla2[[#This Row],[Impresora]]='Insumos y gastos'!$P$6),M17*'Insumos y gastos'!$Q$15*2,IF(AND(Tabla2[[#This Row],[Tipo de insumo]]="PAPEL",Tabla2[[#This Row],[Doble faz]]="SI",Tabla2[[#This Row],[Impresora]]='Insumos y gastos'!$R$6),M17*'Insumos y gastos'!$S$15*2,IF(AND(Tabla2[[#This Row],[Tipo de insumo]]="PAPEL",Tabla2[[#This Row],[Doble faz]]="SI",Tabla2[[#This Row],[Impresora]]='Insumos y gastos'!$T$6),M17*'Insumos y gastos'!$U$15*2,IF(AND(Tabla2[[#This Row],[Tipo de insumo]]="PAPEL",Tabla2[[#This Row],[Doble faz]]="NO",Tabla2[[#This Row],[Impresora]]='Insumos y gastos'!$J$6),M17*'Insumos y gastos'!$K$15,IF(AND(Tabla2[[#This Row],[Tipo de insumo]]="PAPEL",Tabla2[[#This Row],[Doble faz]]="NO",Tabla2[[#This Row],[Impresora]]='Insumos y gastos'!$L$6),M17*'Insumos y gastos'!$M$15,IF(AND(Tabla2[[#This Row],[Tipo de insumo]]="PAPEL",Tabla2[[#This Row],[Doble faz]]="NO",Tabla2[[#This Row],[Impresora]]='Insumos y gastos'!$N$6),M17*'Insumos y gastos'!$O$15,IF(AND(Tabla2[[#This Row],[Tipo de insumo]]="PAPEL",Tabla2[[#This Row],[Doble faz]]="NO",Tabla2[[#This Row],[Impresora]]='Insumos y gastos'!$P$6),M17*'Insumos y gastos'!$Q$15,IF(AND(Tabla2[[#This Row],[Tipo de insumo]]="PAPEL",Tabla2[[#This Row],[Doble faz]]="NO",Tabla2[[#This Row],[Impresora]]='Insumos y gastos'!$R$6),M17*'Insumos y gastos'!$S$15,IF(AND(Tabla2[[#This Row],[Tipo de insumo]]="PAPEL",Tabla2[[#This Row],[Doble faz]]="NO",Tabla2[[#This Row],[Impresora]]='Insumos y gastos'!$T$6),M17*'Insumos y gastos'!$U$15,0)))))))))))) -> 0 | R17: =Tabla2[[#This Row],[Costo impresión]]+Tabla2[[#This Row],[Total costo insumo]] -> 0
K18: =IFERROR(VLOOKUP(J18,'Insumos y gastos'!$B$13:$C$83,2,0),"") -> 0 | L18: =IFERROR(VLOOKUP(J18,Tabla1[[#All],[Nombre insumo]:[Pr. Unidad]],4,0),0) -> 0 | N18: =Tabla2[[#This Row],[Cantidad]]*Tabla2[[#This Row],[Costo insumo]] -> 0 | Q18: =IF(AND(Tabla2[[#This Row],[Tipo de insumo]]="PAPEL",Tabla2[[#This Row],[Doble faz]]="SI",Tabla2[[#This Row],[Impresora]]='Insumos y gastos'!$J$6),M18*'Insumos y gastos'!$K$15*2,IF(AND(Tabla2[[#This Row],[Tipo de insumo]]="PAPEL",Tabla2[[#This Row],[Doble faz]]="SI",Tabla2[[#This Row],[Impresora]]='Insumos y gastos'!$L$6),M18*'Insumos y gastos'!$M$15*2,IF(AND(Tabla2[[#This Row],[Tipo de insumo]]="PAPEL",Tabla2[[#This Row],[Doble faz]]="SI",Tabla2[[#This Row],[Impresora]]='Insumos y gastos'!$N$6),M18*'Insumos y gastos'!$O$15*2,IF(AND(Tabla2[[#This Row],[Tipo de insumo]]="PAPEL",Tabla2[[#This Row],[Doble faz]]="SI",Tabla2[[#This Row],[Impresora]]='Insumos y gastos'!$P$6),M18*'Insumos y gastos'!$Q$15*2,IF(AND(Tabla2[[#This Row],[Tipo de insumo]]="PAPEL",Tabla2[[#This Row],[Doble faz]]="SI",Tabla2[[#This Row],[Impresora]]='Insumos y gastos'!$R$6),M18*'Insumos y gastos'!$S$15*2,IF(AND(Tabla2[[#This Row],[Tipo de insumo]]="PAPEL",Tabla2[[#This Row],[Doble faz]]="SI",Tabla2[[#This Row],[Impresora]]='Insumos y gastos'!$T$6),M18*'Insumos y gastos'!$U$15*2,IF(AND(Tabla2[[#This Row],[Tipo de insumo]]="PAPEL",Tabla2[[#This Row],[Doble faz]]="NO",Tabla2[[#This Row],[Impresora]]='Insumos y gastos'!$J$6),M18*'Insumos y gastos'!$K$15,IF(AND(Tabla2[[#This Row],[Tipo de insumo]]="PAPEL",Tabla2[[#This Row],[Doble faz]]="NO",Tabla2[[#This Row],[Impresora]]='Insumos y gastos'!$L$6),M18*'Insumos y gastos'!$M$15,IF(AND(Tabla2[[#This Row],[Tipo de insumo]]="PAPEL",Tabla2[[#This Row],[Doble faz]]="NO",Tabla2[[#This Row],[Impresora]]='Insumos y gastos'!$N$6),M18*'Insumos y gastos'!$O$15,IF(AND(Tabla2[[#This Row],[Tipo de insumo]]="PAPEL",Tabla2[[#This Row],[Doble faz]]="NO",Tabla2[[#This Row],[Impresora]]='Insumos y gastos'!$P$6),M18*'Insumos y gastos'!$Q$15,IF(AND(Tabla2[[#This Row],[Tipo de insumo]]="PAPEL",Tabla2[[#This Row],[Doble faz]]="NO",Tabla2[[#This Row],[Impresora]]='Insumos y gastos'!$R$6),M18*'Insumos y gastos'!$S$15,IF(AND(Tabla2[[#This Row],[Tipo de insumo]]="PAPEL",Tabla2[[#This Row],[Doble faz]]="NO",Tabla2[[#This Row],[Impresora]]='Insumos y gastos'!$T$6),M18*'Insumos y gastos'!$U$15,0)))))))))))) -> 0 | R18: =Tabla2[[#This Row],[Costo impresión]]+Tabla2[[#This Row],[Total costo insumo]] -> 0
K19: =IFERROR(VLOOKUP(J19,'Insumos y gastos'!$B$13:$C$83,2,0),"") -> 0 | L19: =IFERROR(VLOOKUP(J19,Tabla1[[#All],[Nombre insumo]:[Pr. Unidad]],4,0),0) -> 0 | N19: =Tabla2[[#This Row],[Cantidad]]*Tabla2[[#This Row],[Costo insumo]] -> 0 | Q19: =IF(AND(Tabla2[[#This Row],[Tipo de insumo]]="PAPEL",Tabla2[[#This Row],[Doble faz]]="SI",Tabla2[[#This Row],[Impresora]]='Insumos y gastos'!$J$6),M19*'Insumos y gastos'!$K$15*2,IF(AND(Tabla2[[#This Row],[Tipo de insumo]]="PAPEL",Tabla2[[#This Row],[Doble faz]]="SI",Tabla2[[#This Row],[Impresora]]='Insumos y gastos'!$L$6),M19*'Insumos y gastos'!$M$15*2,IF(AND(Tabla2[[#This Row],[Tipo de insumo]]="PAPEL",Tabla2[[#This Row],[Doble faz]]="SI",Tabla2[[#This Row],[Impresora]]='Insumos y gastos'!$N$6),M19*'Insumos y gastos'!$O$15*2,IF(AND(Tabla2[[#This Row],[Tipo de insumo]]="PAPEL",Tabla2[[#This Row],[Doble faz]]="SI",Tabla2[[#This Row],[Impresora]]='Insumos y gastos'!$P$6),M19*'Insumos y gastos'!$Q$15*2,IF(AND(Tabla2[[#This Row],[Tipo de insumo]]="PAPEL",Tabla2[[#This Row],[Doble faz]]="SI",Tabla2[[#This Row],[Impresora]]='Insumos y gastos'!$R$6),M19*'Insumos y gastos'!$S$15*2,IF(AND(Tabla2[[#This Row],[Tipo de insumo]]="PAPEL",Tabla2[[#This Row],[Doble faz]]="SI",Tabla2[[#This Row],[Impresora]]='Insumos y gastos'!$T$6),M19*'Insumos y gastos'!$U$15*2,IF(AND(Tabla2[[#This Row],[Tipo de insumo]]="PAPEL",Tabla2[[#This Row],[Doble faz]]="NO",Tabla2[[#This Row],[Impresora]]='Insumos y gastos'!$J$6),M19*'Insumos y gastos'!$K$15,IF(AND(Tabla2[[#This Row],[Tipo de insumo]]="PAPEL",Tabla2[[#This Row],[Doble faz]]="NO",Tabla2[[#This Row],[Impresora]]='Insumos y gastos'!$L$6),M19*'Insumos y gastos'!$M$15,IF(AND(Tabla2[[#This Row],[Tipo de insumo]]="PAPEL",Tabla2[[#This Row],[Doble faz]]="NO",Tabla2[[#This Row],[Impresora]]='Insumos y gastos'!$N$6),M19*'Insumos y gastos'!$O$15,IF(AND(Tabla2[[#This Row],[Tipo de insumo]]="PAPEL",Tabla2[[#This Row],[Doble faz]]="NO",Tabla2[[#This Row],[Impresora]]='Insumos y gastos'!$P$6),M19*'Insumos y gastos'!$Q$15,IF(AND(Tabla2[[#This Row],[Tipo de insumo]]="PAPEL",Tabla2[[#This Row],[Doble faz]]="NO",Tabla2[[#This Row],[Impresora]]='Insumos y gastos'!$R$6),M19*'Insumos y gastos'!$S$15,IF(AND(Tabla2[[#This Row],[Tipo de insumo]]="PAPEL",Tabla2[[#This Row],[Doble faz]]="NO",Tabla2[[#This Row],[Impresora]]='Insumos y gastos'!$T$6),M19*'Insumos y gastos'!$U$15,0)))))))))))) -> 0 | R19: =Tabla2[[#This Row],[Costo impresión]]+Tabla2[[#This Row],[Total costo insumo]] -> 0
K20: =IFERROR(VLOOKUP(J20,'Insumos y gastos'!$B$13:$C$83,2,0),"") -> 0 | L20: =IFERROR(VLOOKUP(J20,Tabla1[[#All],[Nombre insumo]:[Pr. Unidad]],4,0),0) -> 0 | N20: =Tabla2[[#This Row],[Cantidad]]*Tabla2[[#This Row],[Costo insumo]] -> 0 | Q20: =IF(AND(Tabla2[[#This Row],[Tipo de insumo]]="PAPEL",Tabla2[[#This Row],[Doble faz]]="SI",Tabla2[[#This Row],[Impresora]]='Insumos y gastos'!$J$6),M20*'Insumos y gastos'!$K$15*2,IF(AND(Tabla2[[#This Row],[Tipo de insumo]]="PAPEL",Tabla2[[#This Row],[Doble faz]]="SI",Tabla2[[#This Row],[Impresora]]='Insumos y gastos'!$L$6),M20*'Insumos y gastos'!$M$15*2,IF(AND(Tabla2[[#This Row],[Tipo de insumo]]="PAPEL",Tabla2[[#This Row],[Doble faz]]="SI",Tabla2[[#This Row],[Impresora]]='Insumos y gastos'!$N$6),M20*'Insumos y gastos'!$O$15*2,IF(AND(Tabla2[[#This Row],[Tipo de insumo]]="PAPEL",Tabla2[[#This Row],[Doble faz]]="SI",Tabla2[[#This Row],[Impresora]]='Insumos y gastos'!$P$6),M20*'Insumos y gastos'!$Q$15*2,IF(AND(Tabla2[[#This Row],[Tipo de insumo]]="PAPEL",Tabla2[[#This Row],[Doble faz]]="SI",Tabla2[[#This Row],[Impresora]]='Insumos y gastos'!$R$6),M20*'Insumos y gastos'!$S$15*2,IF(AND(Tabla2[[#This Row],[Tipo de insumo]]="PAPEL",Tabla2[[#This Row],[Doble faz]]="SI",Tabla2[[#This Row],[Impresora]]='Insumos y gastos'!$T$6),M20*'Insumos y gastos'!$U$15*2,IF(AND(Tabla2[[#This Row],[Tipo de insumo]]="PAPEL",Tabla2[[#This Row],[Doble faz]]="NO",Tabla2[[#This Row],[Impresora]]='Insumos y gastos'!$J$6),M20*'Insumos y gastos'!$K$15,IF(AND(Tabla2[[#This Row],[Tipo de insumo]]="PAPEL",Tabla2[[#This Row],[Doble faz]]="NO",Tabla2[[#This Row],[Impresora]]='Insumos y gastos'!$L$6),M20*'Insumos y gastos'!$M$15,IF(AND(Tabla2[[#This Row],[Tipo de insumo]]="PAPEL",Tabla2[[#This Row],[Doble faz]]="NO",Tabla2[[#This Row],[Impresora]]='Insumos y gastos'!$N$6),M20*'Insumos y gastos'!$O$15,IF(AND(Tabla2[[#This Row],[Tipo de insumo]]="PAPEL",Tabla2[[#This Row],[Doble faz]]="NO",Tabla2[[#This Row],[Impresora]]='Insumos y gastos'!$P$6),M20*'Insumos y gastos'!$Q$15,IF(AND(Tabla2[[#This Row],[Tipo de insumo]]="PAPEL",Tabla2[[#This Row],[Doble faz]]="NO",Tabla2[[#This Row],[Impresora]]='Insumos y gastos'!$R$6),M20*'Insumos y gastos'!$S$15,IF(AND(Tabla2[[#This Row],[Tipo de insumo]]="PAPEL",Tabla2[[#This Row],[Doble faz]]="NO",Tabla2[[#This Row],[Impresora]]='Insumos y gastos'!$T$6),M20*'Insumos y gastos'!$U$15,0)))))))))))) -> 0 | R20: =Tabla2[[#This Row],[Costo impresión]]+Tabla2[[#This Row],[Total costo insumo]] -> 0
K21: =IFERROR(VLOOKUP(J21,'Insumos y gastos'!$B$13:$C$83,2,0),"") -> 0 | L21: =IFERROR(VLOOKUP(J21,Tabla1[[#All],[Nombre insumo]:[Pr. Unidad]],4,0),0) -> 0 | N21: =Tabla2[[#This Row],[Cantidad]]*Tabla2[[#This Row],[Costo insumo]] -> 0 | Q21: =IF(AND(Tabla2[[#This Row],[Tipo de insumo]]="PAPEL",Tabla2[[#This Row],[Doble faz]]="SI",Tabla2[[#This Row],[Impresora]]='Insumos y gastos'!$J$6),M21*'Insumos y gastos'!$K$15*2,IF(AND(Tabla2[[#This Row],[Tipo de insumo]]="PAPEL",Tabla2[[#This Row],[Doble faz]]="SI",Tabla2[[#This Row],[Impresora]]='Insumos y gastos'!$L$6),M21*'Insumos y gastos'!$M$15*2,IF(AND(Tabla2[[#This Row],[Tipo de insumo]]="PAPEL",Tabla2[[#This Row],[Doble faz]]="SI",Tabla2[[#This Row],[Impresora]]='Insumos y gastos'!$N$6),M21*'Insumos y gastos'!$O$15*2,IF(AND(Tabla2[[#This Row],[Tipo de insumo]]="PAPEL",Tabla2[[#This Row],[Doble faz]]="SI",Tabla2[[#This Row],[Impresora]]='Insumos y gastos'!$P$6),M21*'Insumos y gastos'!$Q$15*2,IF(AND(Tabla2[[#This Row],[Tipo de insumo]]="PAPEL",Tabla2[[#This Row],[Doble faz]]="SI",Tabla2[[#This Row],[Impresora]]='Insumos y gastos'!$R$6),M21*'Insumos y gastos'!$S$15*2,IF(AND(Tabla2[[#This Row],[Tipo de insumo]]="PAPEL",Tabla2[[#This Row],[Doble faz]]="SI",Tabla2[[#This Row],[Impresora]]='Insumos y gastos'!$T$6),M21*'Insumos y gastos'!$U$15*2,IF(AND(Tabla2[[#This Row],[Tipo de insumo]]="PAPEL",Tabla2[[#This Row],[Doble faz]]="NO",Tabla2[[#This Row],[Impresora]]='Insumos y gastos'!$J$6),M21*'Insumos y gastos'!$K$15,IF(AND(Tabla2[[#This Row],[Tipo de insumo]]="PAPEL",Tabla2[[#This Row],[Doble faz]]="NO",Tabla2[[#This Row],[Impresora]]='Insumos y gastos'!$L$6),M21*'Insumos y gastos'!$M$15,IF(AND(Tabla2[[#This Row],[Tipo de insumo]]="PAPEL",Tabla2[[#This Row],[Doble faz]]="NO",Tabla2[[#This Row],[Impresora]]='Insumos y gastos'!$N$6),M21*'Insumos y gastos'!$O$15,IF(AND(Tabla2[[#This Row],[Tipo de insumo]]="PAPEL",Tabla2[[#This Row],[Doble faz]]="NO",Tabla2[[#This Row],[Impresora]]='Insumos y gastos'!$P$6),M21*'Insumos y gastos'!$Q$15,IF(AND(Tabla2[[#This Row],[Tipo de insumo]]="PAPEL",Tabla2[[#This Row],[Doble faz]]="NO",Tabla2[[#This Row],[Impresora]]='Insumos y gastos'!$R$6),M21*'Insumos y gastos'!$S$15,IF(AND(Tabla2[[#This Row],[Tipo de insumo]]="PAPEL",Tabla2[[#This Row],[Doble faz]]="NO",Tabla2[[#This Row],[Impresora]]='Insumos y gastos'!$T$6),M21*'Insumos y gastos'!$U$15,0)))))))))))) -> 0 | R21: =Tabla2[[#This Row],[Costo impresión]]+Tabla2[[#This Row],[Total costo insumo]] -> 0
K22: =IFERROR(VLOOKUP(J22,'Insumos y gastos'!$B$13:$C$83,2,0),"") -> 0 | L22: =IFERROR(VLOOKUP(J22,Tabla1[[#All],[Nombre insumo]:[Pr. Unidad]],4,0),0) -> 0 | N22: =Tabla2[[#This Row],[Cantidad]]*Tabla2[[#This Row],[Costo insumo]] -> 0 | Q22: =IF(AND(Tabla2[[#This Row],[Tipo de insumo]]="PAPEL",Tabla2[[#This Row],[Doble faz]]="SI",Tabla2[[#This Row],[Impresora]]='Insumos y gastos'!$J$6),M22*'Insumos y gastos'!$K$15*2,IF(AND(Tabla2[[#This Row],[Tipo de insumo]]="PAPEL",Tabla2[[#This Row],[Doble faz]]="SI",Tabla2[[#This Row],[Impresora]]='Insumos y gastos'!$L$6),M22*'Insumos y gastos'!$M$15*2,IF(AND(Tabla2[[#This Row],[Tipo de insumo]]="PAPEL",Tabla2[[#This Row],[Doble faz]]="SI",Tabla2[[#This Row],[Impresora]]='Insumos y gastos'!$N$6),M22*'Insumos y gastos'!$O$15*2,IF(AND(Tabla2[[#This Row],[Tipo de insumo]]="PAPEL",Tabla2[[#This Row],[Doble faz]]="SI",Tabla2[[#This Row],[Impresora]]='Insumos y gastos'!$P$6),M22*'Insumos y gastos'!$Q$15*2,IF(AND(Tabla2[[#This Row],[Tipo de insumo]]="PAPEL",Tabla2[[#This Row],[Doble faz]]="SI",Tabla2[[#This Row],[Impresora]]='Insumos y gastos'!$R$6),M22*'Insumos y gastos'!$S$15*2,IF(AND(Tabla2[[#This Row],[Tipo de insumo]]="PAPEL",Tabla2[[#This Row],[Doble faz]]="SI",Tabla2[[#This Row],[Impresora]]='Insumos y gastos'!$T$6),M22*'Insumos y gastos'!$U$15*2,IF(AND(Tabla2[[#This Row],[Tipo de insumo]]="PAPEL",Tabla2[[#This Row],[Doble faz]]="NO",Tabla2[[#This Row],[Impresora]]='Insumos y gastos'!$J$6),M22*'Insumos y gastos'!$K$15,IF(AND(Tabla2[[#This Row],[Tipo de insumo]]="PAPEL",Tabla2[[#This Row],[Doble faz]]="NO",Tabla2[[#This Row],[Impresora]]='Insumos y gastos'!$L$6),M22*'Insumos y gastos'!$M$15,IF(AND(Tabla2[[#This Row],[Tipo de insumo]]="PAPEL",Tabla2[[#This Row],[Doble faz]]="NO",Tabla2[[#This Row],[Impresora]]='Insumos y gastos'!$N$6),M22*'Insumos y gastos'!$O$15,IF(AND(Tabla2[[#This Row],[Tipo de insumo]]="PAPEL",Tabla2[[#This Row],[Doble faz]]="NO",Tabla2[[#This Row],[Impresora]]='Insumos y gastos'!$P$6),M22*'Insumos y gastos'!$Q$15,IF(AND(Tabla2[[#This Row],[Tipo de insumo]]="PAPEL",Tabla2[[#This Row],[Doble faz]]="NO",Tabla2[[#This Row],[Impresora]]='Insumos y gastos'!$R$6),M22*'Insumos y gastos'!$S$15,IF(AND(Tabla2[[#This Row],[Tipo de insumo]]="PAPEL",Tabla2[[#This Row],[Doble faz]]="NO",Tabla2[[#This Row],[Impresora]]='Insumos y gastos'!$T$6),M22*'Insumos y gastos'!$U$15,0)))))))))))) -> 0 | R22: =Tabla2[[#This Row],[Costo impresión]]+Tabla2[[#This Row],[Total costo insumo]] -> 0
K23: =IFERROR(VLOOKUP(J23,'Insumos y gastos'!$B$13:$C$83,2,0),"") -> 0 | L23: =IFERROR(VLOOKUP(J23,Tabla1[[#All],[Nombre insumo]:[Pr. Unidad]],4,0),0) -> 0 | N23: =Tabla2[[#This Row],[Cantidad]]*Tabla2[[#This Row],[Costo insumo]] -> 0 | Q23: =IF(AND(Tabla2[[#This Row],[Tipo de insumo]]="PAPEL",Tabla2[[#This Row],[Doble faz]]="SI",Tabla2[[#This Row],[Impresora]]='Insumos y gastos'!$J$6),M23*'Insumos y gastos'!$K$15*2,IF(AND(Tabla2[[#This Row],[Tipo de insumo]]="PAPEL",Tabla2[[#This Row],[Doble faz]]="SI",Tabla2[[#This Row],[Impresora]]='Insumos y gastos'!$L$6),M23*'Insumos y gastos'!$M$15*2,IF(AND(Tabla2[[#This Row],[Tipo de insumo]]="PAPEL",Tabla2[[#This Row],[Doble faz]]="SI",Tabla2[[#This Row],[Impresora]]='Insumos y gastos'!$N$6),M23*'Insumos y gastos'!$O$15*2,IF(AND(Tabla2[[#This Row],[Tipo de insumo]]="PAPEL",Tabla2[[#This Row],[Doble faz]]="SI",Tabla2[[#This Row],[Impresora]]='Insumos y gastos'!$P$6),M23*'Insumos y gastos'!$Q$15*2,IF(AND(Tabla2[[#This Row],[Tipo de insumo]]="PAPEL",Tabla2[[#This Row],[Doble faz]]="SI",Tabla2[[#This Row],[Impresora]]='Insumos y gastos'!$R$6),M23*'Insumos y gastos'!$S$15*2,IF(AND(Tabla2[[#This Row],[Tipo de insumo]]="PAPEL",Tabla2[[#This Row],[Doble faz]]="SI",Tabla2[[#This Row],[Impresora]]='Insumos y gastos'!$T$6),M23*'Insumos y gastos'!$U$15*2,IF(AND(Tabla2[[#This Row],[Tipo de insumo]]="PAPEL",Tabla2[[#This Row],[Doble faz]]="NO",Tabla2[[#This Row],[Impresora]]='Insumos y gastos'!$J$6),M23*'Insumos y gastos'!$K$15,IF(AND(Tabla2[[#This Row],[Tipo de insumo]]="PAPEL",Tabla2[[#This Row],[Doble faz]]="NO",Tabla2[[#This Row],[Impresora]]='Insumos y gastos'!$L$6),M23*'Insumos y gastos'!$M$15,IF(AND(Tabla2[[#This Row],[Tipo de insumo]]="PAPEL",Tabla2[[#This Row],[Doble faz]]="NO",Tabla2[[#This Row],[Impresora]]='Insumos y gastos'!$N$6),M23*'Insumos y gastos'!$O$15,IF(AND(Tabla2[[#This Row],[Tipo de insumo]]="PAPEL",Tabla2[[#This Row],[Doble faz]]="NO",Tabla2[[#This Row],[Impresora]]='Insumos y gastos'!$P$6),M23*'Insumos y gastos'!$Q$15,IF(AND(Tabla2[[#This Row],[Tipo de insumo]]="PAPEL",Tabla2[[#This Row],[Doble faz]]="NO",Tabla2[[#This Row],[Impresora]]='Insumos y gastos'!$R$6),M23*'Insumos y gastos'!$S$15,IF(AND(Tabla2[[#This Row],[Tipo de insumo]]="PAPEL",Tabla2[[#This Row],[Doble faz]]="NO",Tabla2[[#This Row],[Impresora]]='Insumos y gastos'!$T$6),M23*'Insumos y gastos'!$U$15,0)))))))))))) -> 0 | R23: =Tabla2[[#This Row],[Costo impresión]]+Tabla2[[#This Row],[Total costo insumo]] -> 0
J24: Total | N24: =SUBTOTAL(109,Tabla2[Total costo insumo]) -> 0 | Q24: =SUBTOTAL(109,Tabla2[Costo impresión]) -> 0 | R24: =SUBTOTAL(109,Tabla2[Total insumo + impresión]) -> 0
R25: (*)
J26: (*) El total no incluye gastos fijos, ni hora de mano de obra, solo costo de insumos.
P28: Calculadora de horas
J30: Costo sin servicios | K30: Cantidad de horas | L30: Costo sevicios | M30: Mano de obra | N30: Costo final | P30: Minutos | Q30: Porcentaje horario
J31: =Tabla2[[#Totals],[Total insumo + impresión]] -> 0 | L31: =K31*'Insumos y gastos'!$M$50 -> 0 | M31: =K31*'Insumos y gastos'!$Q$24 -> 0 | N31: =J31+L31+M31 -> 0 | Q31: =P31/60 -> 0
K36: Precio final | O36: Precio final
K38: ¿Cuanto porcentaje de ganancia tengo? ❤ | O38: ¿A cuanto debo venderlo? ❤
K40: Precio publicado | L40: Porcentaje de ganancia | M40: Ganancia en pesos | O40: Porcentaje de ganancia | P40: Precio sugerido | Q40: Ganancia en pesos
L41: =((K41*100)/N31)/100 -> #DIV/0! | M41: =K41-N31 -> 0 | P41: =(O41*N31)+N31 -> 0 | Q41: =P41-N31 -> 0

Sheet Productos
A1: PRODUCTO | E1: COSTOS DE PAPELES E IMPRESIÓN | AN1: COSTO INSUMOS | BH1: Costo final
A2: SKU | B2: Nombre producto | C2: RUBRO | D2: SUBRUBRO | E2: Papel 1 | F2: Costo papel 1 | G2: Cantidad 1 | H2: Doble faz 1 | I2: Impresora 1 | J2: Costo impresión 1 | K2: Subtotal impresión 1 | L2: Papel 2 | M2: Costo papel 2 | N2: Cantidad 2 | O2: Doble faz 2 | P2: Impresora 2 | Q2: Costo impresión 2 | R2: Subtotal impresión 2 | S2: Papel 3 | T2: Costo papel 3 | U2: Cantidad 3 | V2: Doble faz 3 | W2: Impresora 3 | X2: Costo impresión 3 | Y2: Subtotal impresión 3 | Z2: Papel 4 | AA2: Costo papel 4 | AB2: Cantidad 4 | AC2: Doble faz 4 | AD2: Impresora 4 | AE2: Costo impresión 4 | AF2: Subtotal impresión 4 | AG2: Papel 5 | AH2: Costo papel 5 | AI2: Cantidad 5 | AJ2: Doble faz 5 | AK2: Impresora 5 | AL2: Costo impresión 5 | AM2: Subtotal impresión 5 | AN2: Insumo 1 | AO2: Costo insumo 1 | AP2: Cantidad insumo 1 | AQ2: Subtotal insumos 1 | AR2: Insumo 2 | AS2: Costo insumo 2 | AT2: Cantidad insumo 2 | AU2: Subtotal insumos 2 | AV2: Insumo 3 | AW2: Costo insumo 3 | AX2: Cantidad insumo 3 | AY2: Subtotal insumos 3 | AZ2: Insumo 4 | BA2: Costo insumo 4 | BB2: Cantidad insumo 4 | BC2: Subtotal insumos 4 | BD2: Insumo 5 | BE2: Costo insumo 5 | BF2: Cantidad insumo 5 | BG2: Subtotal insumos 5 | BH2: Costo sin servicios | BI2: Cantidad de horas | BJ2: Costo servicios | BK2: Costo mano de obra | BL2: Costo total
A3: 10001 | F3: =IFERROR(VLOOKUP(E3,Tabla1[[#All],[Nombre insumo]:[Pr. Unidad]],4,0),0) -> 0 | J3: =G3*F3 -> 0 | K3: =IF(AND(H3="SI",I3='Insumos y gastos'!$J$6),J3+('Insumos y gastos'!$K$15*G3*2),IF(AND(H3="NO",I3='Insumos y gastos'!$J$6),Productos!J3+('Insumos y gastos'!$K$15*Productos!G3),IF(AND(H3="SI",I3='Insumos y gastos'!$L$6),J3+('Insumos y gastos'!$M$15*G3*2),IF(AND(H3="NO",I3='Insumos y gastos'!$L$6),Productos!J3+('Insumos y gastos'!$M$15*Productos!G3),IF(AND(H3="SI",I3='Insumos y gastos'!$N$6),J3+('Insumos y gastos'!$O$15*G3*2),IF(AND(H3="NO",I3='Insumos y gastos'!$N$6),Productos!J3+('Insumos y gastos'!$O$15*Productos!G3),IF(AND(H3="SI",I3='Insumos y gastos'!$P$6),J3+('Insumos y gastos'!$Q$15*G3*2),IF(AND(H3="NO",I3='Insumos y gastos'!$P$6),Productos!J3+('Insumos y gastos'!$Q$15*Productos!G3),IF(AND(H3="SI",I3='Insumos y gastos'!$R$6),J3+('Insumos y gastos'!$S$15*G3*2),IF(AND(H3="NO",I3='Insumos y gastos'!$R$6),Productos!J3+('Insumos y gastos'!$S$15*Productos!G3),IF(AND(H3="SI",I3='Insumos y gastos'!$T$6),J3+('Insumos y gastos'!$U$15*G3*2),IF(AND(H3="NO",I3='Insumos y gastos'!$T$6),Productos!J3+('Insumos y gastos'!$U$15*Productos!G3),0)))))))))))) -> 0 | M3: =IFERROR(VLOOKUP(L3,Tabla1[[#All],[Nombre insumo]:[Pr. Unidad]],4,0),0) -> 0 | Q3: =N3*M3 -> 0 | R3: =IF(AND(O3="SI",P3='Insumos y gastos'!$J$6),Q3+('Insumos y gastos'!$K$15*N3*2),IF(AND(O3="NO",P3='Insumos y gastos'!$J$6),Productos!Q3+('Insumos y gastos'!$K$15*Productos!N3),IF(AND(O3="SI",P3='Insumos y gastos'!$L$6),Q3+('Insumos y gastos'!$M$15*N3*2),IF(AND(O3="NO",P3='Insumos y gastos'!$L$6),Productos!Q3+('Insumos y gastos'!$M$15*Productos!N3),IF(AND(O3="SI",P3='Insumos y gastos'!$N$6),Q3+('Insumos y gastos'!$O$15*N3*2),IF(AND(O3="NO",P3='Insumos y gastos'!$N$6),Productos!Q3+('Insumos y gastos'!$O$15*Productos!N3),IF(AND(O3="SI",P3='Insumos y gastos'!$P$6),Q3+('Insumos y gastos'!$Q$15*N3*2),IF(AND(O3="NO",P3='Insumos y gastos'!$P$6),Productos!Q3+('Insumos y gastos'!$Q$15*Productos!N3),IF(AND(O3="SI",P3='Insumos y gastos'!$R$6),Q3+('Insumos y gastos'!$S$15*N3*2),IF(AND(O3="NO",P3='Insumos y gastos'!$R$6),Productos!Q3+('Insumos y gastos'!$S$15*Productos!N3),IF(AND(O3="SI",P3='Insumos y gastos'!$T$6),Q3+('Insumos y gastos'!$U$15*N3*2),IF(AND(O3="NO",P3='Insumos y gastos'!$T$6),Productos!Q3+('Insumos y gastos'!$U$15*Productos!N3),0)))))))))))) -> 0 | T3: =IFERROR(VLOOKUP(S3,Tabla1[[#All],[Nombre insumo]:[Pr. Unidad]],4,0),0) -> 0 | X3: =U3*T3 -> 0 | Y3: =IF(AND(V3="SI",W3='Insumos y gastos'!$J$6),X3+('Insumos y gastos'!$K$15*U3*2),IF(AND(V3="NO",W3='Insumos y gastos'!$J$6),Productos!X3+('Insumos y gastos'!$K$15*Productos!U3),IF(AND(V3="SI",W3='Insumos y gastos'!$L$6),X3+('Insumos y gastos'!$M$15*U3*2),IF(AND(V3="NO",W3='Insumos y gastos'!$L$6),Productos!X3+('Insumos y gastos'!$M$15*Productos!U3),IF(AND(V3="SI",W3='Insumos y gastos'!$N$6),X3+('Insumos y gastos'!$O$15*U3*2),IF(AND(V3="NO",W3='Insumos y gastos'!$N$6),Productos!X3+('Insumos y gastos'!$O$15*Productos!U3),IF(AND(V3="SI",W3='Insumos y gastos'!$P$6),X3+('Insumos y gastos'!$Q$15*U3*2),IF(AND(V3="NO",W3='Insumos y gastos'!$P$6),Productos!X3+('Insumos y gastos'!$Q$15*Productos!U3),IF(AND(V3="SI",W3='Insumos y gastos'!$R$6),X3+('Insumos y gastos'!$S$15*U3*2),IF(AND(V3="NO",W3='Insumos y gastos'!$R$6),Productos!X3+('Insumos y gastos'!$S$15*Productos!U3),IF(AND(V3="SI",W3='Insumos y gastos'!$T$6),X3+('Insumos y gastos'!$U$15*U3*2),IF(AND(V3="NO",W3='Insumos y gastos'!$T$6),Productos!X3+('Insumos y gastos'!$U$15*Productos!U3),0)))))))))))) -> 0 | AA3: =IFERROR(VLOOKUP(Z3,Tabla1[[#All],[Nombre insumo]:[Pr. Unidad]],4,0),0) -> 0 | AE3: =AB3*AA3 -> 0 | AF3: =IF(AND(AC3="SI",AD3='Insumos y gastos'!$J$6),AE3+('Insumos y gastos'!$K$15*AB3*2),IF(AND(AC3="NO",AD3='Insumos y gastos'!$J$6),Productos!AE3+('Insumos y gastos'!$K$15*Productos!AB3),IF(AND(AC3="SI",AD3='Insumos y gastos'!$L$6),AE3+('Insumos y gastos'!$M$15*AB3*2),IF(AND(AC3="NO",AD3='Insumos y gastos'!$L$6),Productos!AE3+('Insumos y gastos'!$M$15*Productos!AB3),IF(AND(AC3="SI",AD3='Insumos y gastos'!$N$6),AE3+('Insumos y gastos'!$O$15*AB3*2),IF(AND(AC3="NO",AD3='Insumos y gastos'!$N$6),Productos!AE3+('Insumos y gastos'!$O$15*Productos!AB3),IF(AND(AC3="SI",AD3='Insumos y gastos'!$P$6),AE3+('Insumos y gastos'!$Q$15*AB3*2),IF(AND(AC3="NO",AD3='Insumos y gastos'!$P$6),Productos!AE3+('Insumos y gastos'!$Q$15*Productos!AB3),IF(AND(AC3="SI",AD3='Insumos y gastos'!$R$6),AE3+('Insumos y gastos'!$S$15*AB3*2),IF(AND(AC3="NO",AD3='Insumos y gastos'!$R$6),Productos!AE3+('Insumos y gastos'!$S$15*Productos!AB3),IF(AND(AC3="SI",AD3='Insumos y gastos'!$T$6),AE3+('Insumos y gastos'!$U$15*AB3*2),IF(AND(AC3="NO",AD3='Insumos y gastos'!$T$6),Productos!AE3+('Insumos y gastos'!$U$15*Productos!AB3),0)))))))))))) -> 0 | AH3: =IFERROR(VLOOKUP(AG3,Tabla1[[#All],[Nombre insumo]:[Pr. Unidad]],4,0),0) -> 0 | AL3: =AI3*AH3 -> 0 | AM3: =IF(AND(AJ3="SI",AK3='Insumos y gastos'!$J$6),AL3+('Insumos y gastos'!$K$15*AI3*2),IF(AND(AJ3="NO",AK3='Insumos y gastos'!$J$6),Productos!AL3+('Insumos y gastos'!$K$15*Productos!AI3),IF(AND(AJ3="SI",AK3='Insumos y gastos'!$L$6),AL3+('Insumos y gastos'!$M$15*AI3*2),IF(AND(AJ3="NO",AK3='Insumos y gastos'!$L$6),Productos!AL3+('Insumos y gastos'!$M$15*Productos!AI3),IF(AND(AJ3="SI",AK3='Insumos y gastos'!$N$6),AL3+('Insumos y gastos'!$O$15*AI3*2),IF(AND(AJ3="NO",AK3='Insumos y gastos'!$N$6),Productos!AL3+('Insumos y gastos'!$O$15*Productos!AI3),IF(AND(AJ3="SI",AK3='Insumos y gastos'!$P$6),AL3+('Insumos y gastos'!$Q$15*AI3*2),IF(AND(AJ3="NO",AK3='Insumos y gastos'!$P$6),Productos!AL3+('Insumos y gastos'!$Q$15*Productos!AI3),IF(AND(AJ3="SI",AK3='Insumos y gastos'!$R$6),AL3+('Insumos y gastos'!$S$15*AI3*2),IF(AND(AJ3="NO",AK3='Insumos y gastos'!$R$6),Productos!AL3+('Insumos y gastos'!$S$15*Productos!AI3),IF(AND(AJ3="SI",AK3='Insumos y gastos'!$T$6),AL3+('Insumos y gastos'!$U$15*AI3*2),IF(AND(AJ3="NO",AK3='Insumos y gastos'!$T$6),Productos!AL3+('Insumos y gastos'!$U$15*Productos!AI3),0)))))))))))) -> 0 | AO3: =IFERROR(VLOOKUP(AN3,Tabla1[[#All],[Nombre insumo]:[Pr. Unidad]],4,0),0) -> 0 | AQ3: =IF(Tabla3[[#This Row],[Costo insumo 1]]>0,Tabla3[[#This Row],[Cantidad insumo 1]]*Tabla3[[#This Row],[Costo insumo 1]],0) -> 0 | AS3: =IFERROR(VLOOKUP(AR3,Tabla1[[#All],[Nombre insumo]:[Pr. Unidad]],4,0),0) -> 0 | AU3: =IF(Tabla3[[#This Row],[Costo insumo 2]]>0,Tabla3[[#This Row],[Cantidad insumo 2]]*Tabla3[[#This Row],[Costo insumo 2]],0) -> 0 | AW3: =IFERROR(VLOOKUP(AV3,Tabla1[[#All],[Nombre insumo]:[Pr. Unidad]],4,0),0) -> 0 | AY3: =IF(Tabla3[[#This Row],[Costo insumo 3]]>0,Tabla3[[#This Row],[Cantidad insumo 3]]*Tabla3[[#This Row],[Costo insumo 3]],0) -> 0 | BA3: =IFERROR(VLOOKUP(AZ3,Tabla1[[#All],[Nombre insumo]:[Pr. Unidad]],4,0),0) -> 0 | BC3: =IF(Tabla3[[#This Row],[Costo insumo 4]]>0,Tabla3[[#This Row],[Cantidad insumo 4]]*Tabla3[[#This Row],[Costo insumo 4]],0) -> 0 | BE3: =IFERROR(VLOOKUP(BD3,Tabla1[[#All],[Nombre insumo]:[Pr. Unidad]],4,0),0) -> 0 | BG3: =IF(Tabla3[[#This Row],[Costo insumo 5]]>0,Tabla3[[#This Row],[Cantidad insumo 5]]*Tabla3[[#This Row],[Costo insumo 5]],0) -> 0 | BH3: =Tabla3[[#This Row],[Subtotal impresión 1]]+Tabla3[[#This Row],[Subtotal impresión 2]]+Tabla3[[#This Row],[Subtotal impresión 3]]+Tabla3[[#This Row],[Subtotal impresión 4]]+Tabla3[[#This Row],[Subtotal impresión 5]]+Tabla3[[#This Row],[Subtotal insumos 1]]+Tabla3[[#This Row],[Subtotal insumos 2]]+Tabla3[[#This Row],[Subtotal insumos 3]]+Tabla3[[#This Row],[Subtotal insumos 4]]+Tabla3[[#This Row],[Subtotal insumos 5]] -> 0 | BJ3: =BI3*'Insumos y gastos'!$M$50 -> 0 | BK3: =BI3*'Insumos y gastos'!$Q$24 -> 0 | BL3: =Tabla3[[#This Row],[Costo sin servicios]]+Tabla3[[#This Row],[Costo servicios]]+Tabla3[[#This Row],[Costo mano de obra]] -> 0
A4: 10002 | F4: =IFERROR(VLOOKUP(E4,Tabla1[[#All],[Nombre insumo]:[Pr. Unidad]],4,0),0) -> 0 | J4: =G4*F4 -> 0 | K4: =IF(AND(H4="SI",I4='Insumos y gastos'!$J$6),J4+('Insumos y gastos'!$K$15*G4*2),IF(AND(H4="NO",I4='Insumos y gastos'!$J$6),Productos!J4+('Insumos y gastos'!$K$15*Productos!G4),IF(AND(H4="SI",I4='Insumos y gastos'!$L$6),J4+('Insumos y gastos'!$M$15*G4*2),IF(AND(H4="NO",I4='Insumos y gastos'!$L$6),Productos!J4+('Insumos y gastos'!$M$15*Productos!G4),IF(AND(H4="SI",I4='Insumos y gastos'!$N$6),J4+('Insumos y gastos'!$O$15*G4*2),IF(AND(H4="NO",I4='Insumos y gastos'!$N$6),Productos!J4+('Insumos y gastos'!$O$15*Productos!G4),IF(AND(H4="SI",I4='Insumos y gastos'!$P$6),J4+('Insumos y gastos'!$Q$15*G4*2),IF(AND(H4="NO",I4='Insumos y gastos'!$P$6),Productos!J4+('Insumos y gastos'!$Q$15*Productos!G4),IF(AND(H4="SI",I4='Insumos y gastos'!$R$6),J4+('Insumos y gastos'!$S$15*G4*2),IF(AND(H4="NO",I4='Insumos y gastos'!$R$6),Productos!J4+('Insumos y gastos'!$S$15*Productos!G4),IF(AND(H4="SI",I4='Insumos y gastos'!$T$6),J4+('Insumos y gastos'!$U$15*G4*2),IF(AND(H4="NO",I4='Insumos y gastos'!$T$6),Productos!J4+('Insumos y gastos'!$U$15*Productos!G4),0)))))))))))) -> 0 | M4: =IFERROR(VLOOKUP(L4,Tabla1[[#All],[Nombre insumo]:[Pr. Unidad]],4,0),0) -> 0 | Q4: =N4*M4 -> 0 | R4: =IF(AND(O4="SI",P4='Insumos y gastos'!$J$6),Q4+('Insumos y gastos'!$K$15*N4*2),IF(AND(O4="NO",P4='Insumos y gastos'!$J$6),Productos!Q4+('Insumos y gastos'!$K$15*Productos!N4),IF(AND(O4="SI",P4='Insumos y gastos'!$L$6),Q4+('Insumos y gastos'!$M$15*N4*2),IF(AND(O4="NO",P4='Insumos y gastos'!$L$6),Productos!Q4+('Insumos y gastos'!$M$15*Productos!N4),IF(AND(O4="SI",P4='Insumos y gastos'!$N$6),Q4+('Insumos y gastos'!$O$15*N4*2),IF(AND(O4="NO",P4='Insumos y gastos'!$N$6),Productos!Q4+('Insumos y gastos'!$O$15*Productos!N4),IF(AND(O4="SI",P4='Insumos y gastos'!$P$6),Q4+('Insumos y gastos'!$Q$15*N4*2),IF(AND(O4="NO",P4='Insumos y gastos'!$P$6),Productos!Q4+('Insumos y gastos'!$Q$15*Productos!N4),IF(AND(O4="SI",P4='Insumos y gastos'!$R$6),Q4+('Insumos y gastos'!$S$15*N4*2),IF(AND(O4="NO",P4='Insumos y gastos'!$R$6),Productos!Q4+('Insumos y gastos'!$S$15*Productos!N4),IF(AND(O4="SI",P4='Insumos y gastos'!$T$6),Q4+('Insumos y gastos'!$U$15*N4*2),IF(AND(O4="NO",P4='Insumos y gastos'!$T$6),Productos!Q4+('Insumos y gastos'!$U$15*Productos!N4),0)))))))))))) -> 0 | T4: =IFERROR(VLOOKUP(S4,Tabla1[[#All],[Nombre insumo]:[Pr. Unidad]],4,0),0) -> 0 | X4: =U4*T4 -> 0 | Y4: =IF(AND(V4="SI",W4='Insumos y gastos'!$J$6),X4+('Insumos y gastos'!$K$15*U4*2),IF(AND(V4="NO",W4='Insumos y gastos'!$J$6),Productos!X4+('Insumos y gastos'!$K$15*Productos!U4),IF(AND(V4="SI",W4='Insumos y gastos'!$L$6),X4+('Insumos y gastos'!$M$15*U4*2),IF(AND(V4="NO",W4='Insumos y gastos'!$L$6),Productos!X4+('Insumos y gastos'!$M$15*Productos!U4),IF(AND(V4="SI",W4='Insumos y gastos'!$N$6),X4+('Insumos y gastos'!$O$15*U4*2),IF(AND(V4="NO",W4='Insumos y gastos'!$N$6),Productos!X4+('Insumos y gastos'!$O$15*Productos!U4),IF(AND(V4="SI",W4='Insumos y gastos'!$P$6),X4+('Insumos y gastos'!$Q$15*U4*2),IF(AND(V4="NO",W4='Insumos y gastos'!$P$6),Productos!X4+('Insumos y gastos'!$Q$15*Productos!U4),IF(AND(V4="SI",W4='Insumos y gastos'!$R$6),X4+('Insumos y gastos'!$S$15*U4*2),IF(AND(V4="NO",W4='Insumos y gastos'!$R$6),Productos!X4+('Insumos y gastos'!$S$15*Productos!U4),IF(AND(V4="SI",W4='Insumos y gastos'!$T$6),X4+('Insumos y gastos'!$U$15*U4*2),IF(AND(V4="NO",W4='Insumos y gastos'!$T$6),Productos!X4+('Insumos y gastos'!$U$15*Productos!U4),0)))))))))))) -> 0 | AA4: =IFERROR(VLOOKUP(Z4,Tabla1[[#All],[Nombre insumo]:[Pr. Unidad]],4,0),0) -> 0 | AE4: =AB4*AA4 -> 0 | AF4: =IF(AND(AC4="SI",AD4='Insumos y gastos'!$J$6),AE4+('Insumos y gastos'!$K$15*AB4*2),IF(AND(AC4="NO",AD4='Insumos y gastos'!$J$6),Productos!AE4+('Insumos y gastos'!$K$15*Productos!AB4),IF(AND(AC4="SI",AD4='Insumos y gastos'!$L$6),AE4+('Insumos y gastos'!$M$15*AB4*2),IF(AND(AC4="NO",AD4='Insumos y gastos'!$L$6),Productos!AE4+('Insumos y gastos'!$M$15*Productos!AB4),IF(AND(AC4="SI",AD4='Insumos y gastos'!$N$6),AE4+('Insumos y gastos'!$O$15*AB4*2),IF(AND(AC4="NO",AD4='Insumos y gastos'!$N$6),Productos!AE4+('Insumos y gastos'!$O$15*Productos!AB4),IF(AND(AC4="SI",AD4='Insumos y gastos'!$P$6),AE4+('Insumos y gastos'!$Q$15*AB4*2),IF(AND(AC4="NO",AD4='Insumos y gastos'!$P$6),Productos!AE4+('Insumos y gastos'!$Q$15*Productos!AB4),IF(AND(AC4="SI",AD4='Insumos y gastos'!$R$6),AE4+('Insumos y gastos'!$S$15*AB4*2),IF(AND(AC4="NO",AD4='Insumos y gastos'!$R$6),Productos!AE4+('Insumos y gastos'!$S$15*Productos!AB4),IF(AND(AC4="SI",AD4='Insumos y gastos'!$T$6),AE4+('Insumos y gastos'!$U$15*AB4*2),IF(AND(AC4="NO",AD4='Insumos y gastos'!$T$6),Productos!AE4+('Insumos y gastos'!$U$15*Productos!AB4),0)))))))))))) -> 0 | AH4: =IFERROR(VLOOKUP(AG4,Tabla1[[#All],[Nombre insumo]:[Pr. Unidad]],4,0),0) -> 0 | AL4: =AI4*AH4 -> 0 | AM4: =IF(AND(AJ4="SI",AK4='Insumos y gastos'!$J$6),AL4+('Insumos y gastos'!$K$15*AI4*2),IF(AND(AJ4="NO",AK4='Insumos y gastos'!$J$6),Productos!AL4+('Insumos y gastos'!$K$15*Productos!AI4),IF(AND(AJ4="SI",AK4='Insumos y gastos'!$L$6),AL4+('Insumos y gastos'!$M$15*AI4*2),IF(AND(AJ4="NO",AK4='Insumos y gastos'!$L$6),Productos!AL4+('Insumos y gastos'!$M$15*Productos!AI4),IF(AND(AJ4="SI",AK4='Insumos y gastos'!$N$6),AL4+('Insumos y gastos'!$O$15*AI4*2),IF(AND(AJ4="NO",AK4='Insumos y gastos'!$N$6),Productos!AL4+('Insumos y gastos'!$O$15*Productos!AI4),IF(AND(AJ4="SI",AK4='Insumos y gastos'!$P$6),AL4+('Insumos y gastos'!$Q$15*AI4*2),IF(AND(AJ4="NO",AK4='Insumos y gastos'!$P$6),Productos!AL4+('Insumos y gastos'!$Q$15*Productos!AI4),IF(AND(AJ4="SI",AK4='Insumos y gastos'!$R$6),AL4+('Insumos y gastos'!$S$15*AI4*2),IF(AND(AJ4="NO",AK4='Insumos y gastos'!$R$6),Productos!AL4+('Insumos y gastos'!$S$15*Productos!AI4),IF(AND(AJ4="SI",AK4='Insumos y gastos'!$T$6),AL4+('Insumos y gastos'!$U$15*AI4*2),IF(AND(AJ4="NO",AK4='Insumos y gastos'!$T$6),Productos!AL4+('Insumos y gastos'!$U$15*Productos!AI4),0)))))))))))) -> 0 | AO4: =IFERROR(VLOOKUP(AN4,Tabla1[[#All],[Nombre insumo]:[Pr. Unidad]],4,0),0) -> 0 | AQ4: =IF(Tabla3[[#This Row],[Costo insumo 1]]>0,Tabla3[[#This Row],[Cantidad insumo 1]]*Tabla3[[#This Row],[Costo insumo 1]],0) -> 0 | AS4: =IFERROR(VLOOKUP(AR4,Tabla1[[#All],[Nombre insumo]:[Pr. Unidad]],4,0),0) -> 0 | AU4: =IF(Tabla3[[#This Row],[Costo insumo 2]]>0,Tabla3[[#This Row],[Cantidad insumo 2]]*Tabla3[[#This Row],[Costo insumo 2]],0) -> 0 | AW4: =IFERROR(VLOOKUP(AV4,Tabla1[[#All],[Nombre insumo]:[Pr. Unidad]],4,0),0) -> 0 | AY4: =IF(Tabla3[[#This Row],[Costo insumo 3]]>0,Tabla3[[#This Row],[Cantidad insumo 3]]*Tabla3[[#This Row],[Costo insumo 3]],0) -> 0 | BA4: =IFERROR(VLOOKUP(AZ4,Tabla1[[#All],[Nombre insumo]:[Pr. Unidad]],4,0),0) -> 0 | BC4: =IF(Tabla3[[#This Row],[Costo insumo 4]]>0,Tabla3[[#This Row],[Cantidad insumo 4]]*Tabla3[[#This Row],[Costo insumo 4]],0) -> 0 | BE4: =IFERROR(VLOOKUP(BD4,Tabla1[[#All],[Nombre insumo]:[Pr. Unidad]],4,0),0) -> 0 | BG4: =IF(Tabla3[[#This Row],[Costo insumo 5]]>0,Tabla3[[#This Row],[Cantidad insumo 5]]*Tabla3[[#This Row],[Costo insumo 5]],0) -> 0 | BH4: =Tabla3[[#This Row],[Subtotal impresión 1]]+Tabla3[[#This Row],[Subtotal impresión 2]]+Tabla3[[#This Row],[Subtotal impresión 3]]+Tabla3[[#This Row],[Subtotal impresión 4]]+Tabla3[[#This Row],[Subtotal impresión 5]]+Tabla3[[#This Row],[Subtotal insumos 1]]+Tabla3[[#This Row],[Subtotal insumos 2]]+Tabla3[[#This Row],[Subtotal insumos 3]]+Tabla3[[#This Row],[Subtotal insumos 4]]+Tabla3[[#This Row],[Subtotal insumos 5]] -> 0 | BJ4: =BI4*'Insumos y gastos'!$M$50 -> 0 | BK4: =BI4*'Insumos y gastos'!$Q$24 -> 0 | BL4: =Tabla3[[#This Row],[Costo sin servicios]]+Tabla3[[#This Row],[Costo servicios]]+Tabla3[[#This Row],[Costo mano de obra]] -> 0
A5: 10003 | F5: =IFERROR(VLOOKUP(E5,Tabla1[[#All],[Nombre insumo]:[Pr. Unidad]],4,0),0) -> 0 | J5: =G5*F5 -> 0 | K5: =IF(AND(H5="SI",I5='Insumos y gastos'!$J$6),J5+('Insumos y gastos'!$K$15*G5*2),IF(AND(H5="NO",I5='Insumos y gastos'!$J$6),Productos!J5+('Insumos y gastos'!$K$15*Productos!G5),IF(AND(H5="SI",I5='Insumos y gastos'!$L$6),J5+('Insumos y gastos'!$M$15*G5*2),IF(AND(H5="NO",I5='Insumos y gastos'!$L$6),Productos!J5+('Insumos y gastos'!$M$15*Productos!G5),IF(AND(H5="SI",I5='Insumos y gastos'!$N$6),J5+('Insumos y gastos'!$O$15*G5*2),IF(AND(H5="NO",I5='Insumos y gastos'!$N$6),Productos!J5+('Insumos y gastos'!$O$15*Productos!G5),IF(AND(H5="SI",I5='Insumos y gastos'!$P$6),J5+('Insumos y gastos'!$Q$15*G5*2),IF(AND(H5="NO",I5='Insumos y gastos'!$P$6),Productos!J5+('Insumos y gastos'!$Q$15*Productos!G5),IF(AND(H5="SI",I5='Insumos y gastos'!$R$6),J5+('Insumos y gastos'!$S$15*G5*2),IF(AND(H5="NO",I5='Insumos y gastos'!$R$6),Productos!J5+('Insumos y gastos'!$S$15*Productos!G5),IF(AND(H5="SI",I5='Insumos y gastos'!$T$6),J5+('Insumos y gastos'!$U$15*G5*2),IF(AND(H5="NO",I5='Insumos y gastos'!$T$6),Productos!J5+('Insumos y gastos'!$U$15*Productos!G5),0)))))))))))) -> 0 | M5: =IFERROR(VLOOKUP(L5,Tabla1[[#All],[Nombre insumo]:[Pr. Unidad]],4,0),0) -> 0 | Q5: =N5*M5 -> 0 | R5: =IF(AND(O5="SI",P5='Insumos y gastos'!$J$6),Q5+('Insumos y gastos'!$K$15*N5*2),IF(AND(O5="NO",P5='Insumos y gastos'!$J$6),Productos!Q5+('Insumos y gastos'!$K$15*Productos!N5),IF(AND(O5="SI",P5='Insumos y gastos'!$L$6),Q5+('Insumos y gastos'!$M$15*N5*2),IF(AND(O5="NO",P5='Insumos y gastos'!$L$6),Productos!Q5+('Insumos y gastos'!$M$15*Productos!N5),IF(AND(O5="SI",P5='Insumos y gastos'!$N$6),Q5+('Insumos y gastos'!$O$15*N5*2),IF(AND(O5="NO",P5='Insumos y gastos'!$N$6),Productos!Q5+('Insumos y gastos'!$O$15*Productos!N5),IF(AND(O5="SI",P5='Insumos y gastos'!$P$6),Q5+('Insumos y gastos'!$Q$15*N5*2),IF(AND(O5="NO",P5='Insumos y gastos'!$P$6),Productos!Q5+('Insumos y gastos'!$Q$15*Productos!N5),IF(AND(O5="SI",P5='Insumos y gastos'!$R$6),Q5+('Insumos y gastos'!$S$15*N5*2),IF(AND(O5="NO",P5='Insumos y gastos'!$R$6),Productos!Q5+('Insumos y gastos'!$S$15*Productos!N5),IF(AND(O5="SI",P5='Insumos y gastos'!$T$6),Q5+('Insumos y gastos'!$U$15*N5*2),IF(AND(O5="NO",P5='Insumos y gastos'!$T$6),Productos!Q5+('Insumos y gastos'!$U$15*Productos!N5),0)))))))))))) -> 0 | T5: =IFERROR(VLOOKUP(S5,Tabla1[[#All],[Nombre insumo]:[Pr. Unidad]],4,0),0) -> 0 | X5: =U5*T5 -> 0 | Y5: =IF(AND(V5="SI",W5='Insumos y gastos'!$J$6),X5+('Insumos y gastos'!$K$15*U5*2),IF(AND(V5="NO",W5='Insumos y gastos'!$J$6),Productos!X5+('Insumos y gastos'!$K$15*Productos!U5),IF(AND(V5="SI",W5='Insumos y gastos'!$L$6),X5+('Insumos y gastos'!$M$15*U5*2),IF(AND(V5="NO",W5='Insumos y gastos'!$L$6),Productos!X5+('Insumos y gastos'!$M$15*Productos!U5),IF(AND(V5="SI",W5='Insumos y gastos'!$N$6),X5+('Insumos y gastos'!$O$15*U5*2),IF(AND(V5="NO",W5='Insumos y gastos'!$N$6),Productos!X5+('Insumos y gastos'!$O$15*Productos!U5),IF(AND(V5="SI",W5='Insumos y gastos'!$P$6),X5+('Insumos y gastos'!$Q$15*U5*2),IF(AND(V5="NO",W5='Insumos y gastos'!$P$6),Productos!X5+('Insumos y gastos'!$Q$15*Productos!U5),IF(AND(V5="SI",W5='Insumos y gastos'!$R$6),X5+('Insumos y gastos'!$S$15*U5*2),IF(AND(V5="NO",W5='Insumos y gastos'!$R$6),Productos!X5+('Insumos y gastos'!$S$15*Productos!U5),IF(AND(V5="SI",W5='Insumos y gastos'!$T$6),X5+('Insumos y gastos'!$U$15*U5*2),IF(AND(V5="NO",W5='Insumos y gastos'!$T$6),Productos!X5+('Insumos y gastos'!$U$15*Productos!U5),0)))))))))))) -> 0 | AA5: =IFERROR(VLOOKUP(Z5,Tabla1[[#All],[Nombre insumo]:[Pr. Unidad]],4,0),0) -> 0 | AE5: =AB5*AA5 -> 0 | AF5: =IF(AND(AC5="SI",AD5='Insumos y gastos'!$J$6),AE5+('Insumos y gastos'!$K$15*AB5*2),IF(AND(AC5="NO",AD5='Insumos y gastos'!$J$6),Productos!AE5+('Insumos y gastos'!$K$15*Productos!AB5),IF(AND(AC5="SI",AD5='Insumos y gastos'!$L$6),AE5+('Insumos y gastos'!$M$15*AB5*2),IF(AND(AC5="NO",AD5='Insumos y gastos'!$L$6),Productos!AE5+('Insumos y gastos'!$M$15*Productos!AB5),IF(AND(AC5="SI",AD5='Insumos y gastos'!$N$6),AE5+('Insumos y gastos'!$O$15*AB5*2),IF(AND(AC5="NO",AD5='Insumos y gastos'!$N$6),Productos!AE5+('Insumos y gastos'!$O$15*Productos!AB5),IF(AND(AC5="SI",AD5='Insumos y gastos'!$P$6),AE5+('Insumos y gastos'!$Q$15*AB5*2),IF(AND(AC5="NO",AD5='Insumos y gastos'!$P$6),Productos!AE5+('Insumos y gastos'!$Q$15*Productos!AB5),IF(AND(AC5="SI",AD5='Insumos y gastos'!$R$6),AE5+('Insumos y gastos'!$S$15*AB5*2),IF(AND(AC5="NO",AD5='Insumos y gastos'!$R$6),Productos!AE5+('Insumos y gastos'!$S$15*Productos!AB5),IF(AND(AC5="SI",AD5='Insumos y gastos'!$T$6),AE5+('Insumos y gastos'!$U$15*AB5*2),IF(AND(AC5="NO",AD5='Insumos y gastos'!$T$6),Productos!AE5+('Insumos y gastos'!$U$15*Productos!AB5),0)))))))))))) -> 0 | AH5: =IFERROR(VLOOKUP(AG5,Tabla1[[#All],[Nombre insumo]:[Pr. Unidad]],4,0),0) -> 0 | AL5: =AI5*AH5 -> 0 | AM5: =IF(AND(AJ5="SI",AK5='Insumos y gastos'!$J$6),AL5+('Insumos y gastos'!$K$15*AI5*2),IF(AND(AJ5="NO",AK5='Insumos y gastos'!$J$6),Productos!AL5+('Insumos y gastos'!$K$15*Productos!AI5),IF(AND(AJ5="SI",AK5='Insumos y gastos'!$L$6),AL5+('Insumos y gastos'!$M$15*AI5*2),IF(AND(AJ5="NO",AK5='Insumos y gastos'!$L$6),Productos!AL5+('Insumos y gastos'!$M$15*Productos!AI5),IF(AND(AJ5="SI",AK5='Insumos y gastos'!$N$6),AL5+('Insumos y gastos'!$O$15*AI5*2),IF(AND(AJ5="NO",AK5='Insumos y gastos'!$N$6),Productos!AL5+('Insumos y gastos'!$O$15*Productos!AI5),IF(AND(AJ5="SI",AK5='Insumos y gastos'!$P$6),AL5+('Insumos y gastos'!$Q$15*AI5*2),IF(AND(AJ5="NO",AK5='Insumos y gastos'!$P$6),Productos!AL5+('Insumos y gastos'!$Q$15*Productos!AI5),IF(AND(AJ5="SI",AK5='Insumos y gastos'!$R$6),AL5+('Insumos y gastos'!$S$15*AI5*2),IF(AND(AJ5="NO",AK5='Insumos y gastos'!$R$6),Productos!AL5+('Insumos y gastos'!$S$15*Productos!AI5),IF(AND(AJ5="SI",AK5='Insumos y gastos'!$T$6),AL5+('Insumos y gastos'!$U$15*AI5*2),IF(AND(AJ5="NO",AK5='Insumos y gastos'!$T$6),Productos!AL5+('Insumos y gastos'!$U$15*Productos!AI5),0)))))))))))) -> 0 | AO5: =IFERROR(VLOOKUP(AN5,Tabla1[[#All],[Nombre insumo]:[Pr. Unidad]],4,0),0) -> 0 | AQ5: =IF(Tabla3[[#This Row],[Costo insumo 1]]>0,Tabla3[[#This Row],[Cantidad insumo 1]]*Tabla3[[#This Row],[Costo insumo 1]],0) -> 0 | AS5: =IFERROR(VLOOKUP(AR5,Tabla1[[#All],[Nombre insumo]:[Pr. Unidad]],4,0),0) -> 0 | AU5: =IF(Tabla3[[#This Row],[Costo insumo 2]]>0,Tabla3[[#This Row],[Cantidad insumo 2]]*Tabla3[[#This Row],[Costo insumo 2]],0) -> 0 | AW5: =IFERROR(VLOOKUP(AV5,Tabla1[[#All],[Nombre insumo]:[Pr. Unidad]],4,0),0) -> 0 | AY5: =IF(Tabla3[[#This Row],[Costo insumo 3]]>0,Tabla3[[#This Row],[Cantidad insumo 3]]*Tabla3[[#This Row],[Costo insumo 3]],0) -> 0 | BA5: =IFERROR(VLOOKUP(AZ5,Tabla1[[#All],[Nombre insumo]:[Pr. Unidad]],4,0),0) -> 0 | BC5: =IF(Tabla3[[#This Row],[Costo insumo 4]]>0,Tabla3[[#This Row],[Cantidad insumo 4]]*Tabla3[[#This Row],[Costo insumo 4]],0) -> 0 | BE5: =IFERROR(VLOOKUP(BD5,Tabla1[[#All],[Nombre insumo]:[Pr. Unidad]],4,0),0) -> 0 | BG5: =IF(Tabla3[[#This Row],[Costo insumo 5]]>0,Tabla3[[#This Row],[Cantidad insumo 5]]*Tabla3[[#This Row],[Costo insumo 5]],0) -> 0 | BH5: =Tabla3[[#This Row],[Subtotal impresión 1]]+Tabla3[[#This Row],[Subtotal impresión 2]]+Tabla3[[#This Row],[Subtotal impresión 3]]+Tabla3[[#This Row],[Subtotal impresión 4]]+Tabla3[[#This Row],[Subtotal impresión 5]]+Tabla3[[#This Row],[Subtotal insumos 1]]+Tabla3[[#This Row],[Subtotal insumos 2]]+Tabla3[[#This Row],[Subtotal insumos 3]]+Tabla3[[#This Row],[Subtotal insumos 4]]+Tabla3[[#This Row],[Subtotal insumos 5]] -> 0 | BJ5: =BI5*'Insumos y gastos'!$M$50 -> 0 | BK5: =BI5*'Insumos y gastos'!$Q$24 -> 0 | BL5: =Tabla3[[#This Row],[Costo sin servicios]]+Tabla3[[#This Row],[Costo servicios]]+Tabla3[[#This Row],[Costo mano de obra]] -> 0
A6: 10004 | F6: =IFERROR(VLOOKUP(E6,Tabla1[[#All],[Nombre insumo]:[Pr. Unidad]],4,0),0) -> 0 | J6: =G6*F6 -> 0 | K6: =IF(AND(H6="SI",I6='Insumos y gastos'!$J$6),J6+('Insumos y gastos'!$K$15*G6*2),IF(AND(H6="NO",I6='Insumos y gastos'!$J$6),Productos!J6+('Insumos y gastos'!$K$15*Productos!G6),IF(AND(H6="SI",I6='Insumos y gastos'!$L$6),J6+('Insumos y gastos'!$M$15*G6*2),IF(AND(H6="NO",I6='Insumos y gastos'!$L$6),Productos!J6+('Insumos y gastos'!$M$15*Productos!G6),IF(AND(H6="SI",I6='Insumos y gastos'!$N$6),J6+('Insumos y gastos'!$O$15*G6*2),IF(AND(H6="NO",I6='Insumos y gastos'!$N$6),Productos!J6+('Insumos y gastos'!$O$15*Productos!G6),IF(AND(H6="SI",I6='Insumos y gastos'!$P$6),J6+('Insumos y gastos'!$Q$15*G6*2),IF(AND(H6="NO",I6='Insumos y gastos'!$P$6),Productos!J6+('Insumos y gastos'!$Q$15*Productos!G6),IF(AND(H6="SI",I6='Insumos y gastos'!$R$6),J6+('Insumos y gastos'!$S$15*G6*2),IF(AND(H6="NO",I6='Insumos y gastos'!$R$6),Productos!J6+('Insumos y gastos'!$S$15*Productos!G6),IF(AND(H6="SI",I6='Insumos y gastos'!$T$6),J6+('Insumos y gastos'!$U$15*G6*2),IF(AND(H6="NO",I6='Insumos y gastos'!$T$6),Productos!J6+('Insumos y gastos'!$U$15*Productos!G6),0)))))))))))) -> 0 | M6: =IFERROR(VLOOKUP(L6,Tabla1[[#All],[Nombre insumo]:[Pr. Unidad]],4,0),0) -> 0 | Q6: =N6*M6 -> 0 | R6: =IF(AND(O6="SI",P6='Insumos y gastos'!$J$6),Q6+('Insumos y gastos'!$K$15*N6*2),IF(AND(O6="NO",P6='Insumos y gastos'!$J$6),Productos!Q6+('Insumos y gastos'!$K$15*Productos!N6),IF(AND(O6="SI",P6='Insumos y gastos'!$L$6),Q6+('Insumos y gastos'!$M$15*N6*2),IF(AND(O6="NO",P6='Insumos y gastos'!$L$6),Productos!Q6+('Insumos y gastos'!$M$15*Productos!N6),IF(AND(O6="SI",P6='Insumos y gastos'!$N$6),Q6+('Insumos y gastos'!$O$15*N6*2),IF(AND(O6="NO",P6='Insumos y gastos'!$N$6),Productos!Q6+('Insumos y gastos'!$O$15*Productos!N6),IF(AND(O6="SI",P6='Insumos y gastos'!$P$6),Q6+('Insumos y gastos'!$Q$15*N6*2),IF(AND(O6="NO",P6='Insumos y gastos'!$P$6),Productos!Q6+('Insumos y gastos'!$Q$15*Productos!N6),IF(AND(O6="SI",P6='Insumos y gastos'!$R$6),Q6+('Insumos y gastos'!$S$15*N6*2),IF(AND(O6="NO",P6='Insumos y gastos'!$R$6),Productos!Q6+('Insumos y gastos'!$S$15*Productos!N6),IF(AND(O6="SI",P6='Insumos y gastos'!$T$6),Q6+('Insumos y gastos'!$U$15*N6*2),IF(AND(O6="NO",P6='Insumos y gastos'!$T$6),Productos!Q6+('Insumos y gastos'!$U$15*Productos!N6),0)))))))))))) -> 0 | T6: =IFERROR(VLOOKUP(S6,Tabla1[[#All],[Nombre insumo]:[Pr. Unidad]],4,0),0) -> 0 | X6: =U6*T6 -> 0 | Y6: =IF(AND(V6="SI",W6='Insumos y gastos'!$J$6),X6+('Insumos y gastos'!$K$15*U6*2),IF(AND(V6="NO",W6='Insumos y gastos'!$J$6),Productos!X6+('Insumos y gastos'!$K$15*Productos!U6),IF(AND(V6="SI",W6='Insumos y gastos'!$L$6),X6+('Insumos y gastos'!$M$15*U6*2),IF(AND(V6="NO",W6='Insumos y gastos'!$L$6),Productos!X6+('Insumos y gastos'!$M$15*Productos!U6),IF(AND(V6="SI",W6='Insumos y gastos'!$N$6),X6+('Insumos y gastos'!$O$15*U6*2),IF(AND(V6="NO",W6='Insumos y gastos'!$N$6),Productos!X6+('Insumos y gastos'!$O$15*Productos!U6),IF(AND(V6="SI",W6='Insumos y gastos'!$P$6),X6+('Insumos y gastos'!$Q$15*U6*2),IF(AND(V6="NO",W6='Insumos y gastos'!$P$6),Productos!X6+('Insumos y gastos'!$Q$15*Productos!U6),IF(AND(V6="SI",W6='Insumos y gastos'!$R$6),X6+('Insumos y gastos'!$S$15*U6*2),IF(AND(V6="NO",W6='Insumos y gastos'!$R$6),Productos!X6+('Insumos y gastos'!$S$15*Productos!U6),IF(AND(V6="SI",W6='Insumos y gastos'!$T$6),X6+('Insumos y gastos'!$U$15*U6*2),IF(AND(V6="NO",W6='Insumos y gastos'!$T$6),Productos!X6+('Insumos y gastos'!$U$15*Productos!U6),0)))))))))))) -> 0 | AA6: =IFERROR(VLOOKUP(Z6,Tabla1[[#All],[Nombre insumo]:[Pr. Unidad]],4,0),0) -> 0 | AE6: =AB6*AA6 -> 0 | AF6: =IF(AND(AC6="SI",AD6='Insumos y gastos'!$J$6),AE6+('Insumos y gastos'!$K$15*AB6*2),IF(AND(AC6="NO",AD6='Insumos y gastos'!$J$6),Productos!AE6+('Insumos y gastos'!$K$15*Productos!AB6),IF(AND(AC6="SI",AD6='Insumos y gastos'!$L$6),AE6+('Insumos y gastos'!$M$15*AB6*2),IF(AND(AC6="NO",AD6='Insumos y gastos'!$L$6),Productos!AE6+('Insumos y gastos'!$M$15*Productos!AB6),IF(AND(AC6="SI",AD6='Insumos y gastos'!$N$6),AE6+('Insumos y gastos'!$O$15*AB6*2),IF(AND(AC6="NO",AD6='Insumos y gastos'!$N$6),Productos!AE6+('Insumos y gastos'!$O$15*Productos!AB6),IF(AND(AC6="SI",AD6='Insumos y gastos'!$P$6),AE6+('Insumos y gastos'!$Q$15*AB6*2),IF(AND(AC6="NO",AD6='Insumos y gastos'!$P$6),Productos!AE6+('Insumos y gastos'!$Q$15*Productos!AB6),IF(AND(AC6="SI",AD6='Insumos y gastos'!$R$6),AE6+('Insumos y gastos'!$S$15*AB6*2),IF(AND(AC6="NO",AD6='Insumos y gastos'!$R$6),Productos!AE6+('Insumos y gastos'!$S$15*Productos!AB6),IF(AND(AC6="SI",AD6='Insumos y gastos'!$T$6),AE6+('Insumos y gastos'!$U$15*AB6*2),IF(AND(AC6="NO",AD6='Insumos y gastos'!$T$6),Productos!AE6+('Insumos y gastos'!$U$15*Productos!AB6),0)))))))))))) -> 0 | AH6: =IFERROR(VLOOKUP(AG6,Tabla1[[#All],[Nombre insumo]:[Pr. Unidad]],4,0),0) -> 0 | AL6: =AI6*AH6 -> 0 | AM6: =IF(AND(AJ6="SI",AK6='Insumos y gastos'!$J$6),AL6+('Insumos y gastos'!$K$15*AI6*2),IF(AND(AJ6="NO",AK6='Insumos y gastos'!$J$6),Productos!AL6+('Insumos y gastos'!$K$15*Productos!AI6),IF(AND(AJ6="SI",AK6='Insumos y gastos'!$L$6),AL6+('Insumos y gastos'!$M$15*AI6*2),IF(AND(AJ6="NO",AK6='Insumos y gastos'!$L$6),Productos!AL6+('Insumos y gastos'!$M$15*Productos!AI6),IF(AND(AJ6="SI",AK6='Insumos y gastos'!$N$6),AL6+('Insumos y gastos'!$O$15*AI6*2),IF(AND(AJ6="NO",AK6='Insumos y gastos'!$N$6),Productos!AL6+('Insumos y gastos'!$O$15*Productos!AI6),IF(AND(AJ6="SI",AK6='Insumos y gastos'!$P$6),AL6+('Insumos y gastos'!$Q$15*AI6*2),IF(AND(AJ6="NO",AK6='Insumos y gastos'!$P$6),Productos!AL6+('Insumos y gastos'!$Q$15*Productos!AI6),IF(AND(AJ6="SI",AK6='Insumos y gastos'!$R$6),AL6+('Insumos y gastos'!$S$15*AI6*2),IF(AND(AJ6="NO",AK6='Insumos y gastos'!$R$6),Productos!AL6+('Insumos y gastos'!$S$15*Productos!AI6),IF(AND(AJ6="SI",AK6='Insumos y gastos'!$T$6),AL6+('Insumos y gastos'!$U$15*AI6*2),IF(AND(AJ6="NO",AK6='Insumos y gastos'!$T$6),Productos!AL6+('Insumos y gastos'!$U$15*Productos!AI6),0)))))))))))) -> 0 | AO6: =IFERROR(VLOOKUP(AN6,Tabla1[[#All],[Nombre insumo]:[Pr. Unidad]],4,0),0) -> 0 | AQ6: =IF(Tabla3[[#This Row],[Costo insumo 1]]>0,Tabla3[[#This Row],[Cantidad insumo 1]]*Tabla3[[#This Row],[Costo insumo 1]],0) -> 0 | AS6: =IFERROR(VLOOKUP(AR6,Tabla1[[#All],[Nombre insumo]:[Pr. Unidad]],4,0),0) -> 0 | AU6: =IF(Tabla3[[#This Row],[Costo insumo 2]]>0,Tabla3[[#This Row],[Cantidad insumo 2]]*Tabla3[[#This Row],[Costo insumo 2]],0) -> 0 | AW6: =IFERROR(VLOOKUP(AV6,Tabla1[[#All],[Nombre insumo]:[Pr. Unidad]],4,0),0) -> 0 | AY6: =IF(Tabla3[[#This Row],[Costo insumo 3]]>0,Tabla3[[#This Row],[Cantidad insumo 3]]*Tabla3[[#This Row],[Costo insumo 3]],0) -> 0 | BA6: =IFERROR(VLOOKUP(AZ6,Tabla1[[#All],[Nombre insumo]:[Pr. Unidad]],4,0),0) -> 0 | BC6: =IF(Tabla3[[#This Row],[Costo insumo 4]]>0,Tabla3[[#This Row],[Cantidad insumo 4]]*Tabla3[[#This Row],[Costo insumo 4]],0) -> 0 | BE6: =IFERROR(VLOOKUP(BD6,Tabla1[[#All],[Nombre insumo]:[Pr. Unidad]],4,0),0) -> 0 | BG6: =IF(Tabla3[[#This Row],[Costo insumo 5]]>0,Tabla3[[#This Row],[Cantidad insumo 5]]*Tabla3[[#This Row],[Costo insumo 5]],0) -> 0 | BH6: =Tabla3[[#This Row],[Subtotal impresión 1]]+Tabla3[[#This Row],[Subtotal impresión 2]]+Tabla3[[#This Row],[Subtotal impresión 3]]+Tabla3[[#This Row],[Subtotal impresión 4]]+Tabla3[[#This Row],[Subtotal impresión 5]]+Tabla3[[#This Row],[Subtotal insumos 1]]+Tabla3[[#This Row],[Subtotal insumos 2]]+Tabla3[[#This Row],[Subtotal insumos 3]]+Tabla3[[#This Row],[Subtotal insumos 4]]+Tabla3[[#This Row],[Subtotal insumos 5]] -> 0 | BJ6: =BI6*'Insumos y gastos'!$M$50 -> 0 | BK6: =BI6*'Insumos y gastos'!$Q$24 -> 0 | BL6: =Tabla3[[#This Row],[Costo sin servicios]]+Tabla3[[#This Row],[Costo servicios]]+Tabla3[[#This Row],[Costo mano de obra]] -> 0
A7: 10005 | F7: =IFERROR(VLOOKUP(E7,Tabla1[[#All],[Nombre insumo]:[Pr. Unidad]],4,0),0) -> 0 | J7: =G7*F7 -> 0 | K7: =IF(AND(H7="SI",I7='Insumos y gastos'!$J$6),J7+('Insumos y gastos'!$K$15*G7*2),IF(AND(H7="NO",I7='Insumos y gastos'!$J$6),Productos!J7+('Insumos y gastos'!$K$15*Productos!G7),IF(AND(H7="SI",I7='Insumos y gastos'!$L$6),J7+('Insumos y gastos'!$M$15*G7*2),IF(AND(H7="NO",I7='Insumos y gastos'!$L$6),Productos!J7+('Insumos y gastos'!$M$15*Productos!G7),IF(AND(H7="SI",I7='Insumos y gastos'!$N$6),J7+('Insumos y gastos'!$O$15*G7*2),IF(AND(H7="NO",I7='Insumos y gastos'!$N$6),Productos!J7+('Insumos y gastos'!$O$15*Productos!G7),IF(AND(H7="SI",I7='Insumos y gastos'!$P$6),J7+('Insumos y gastos'!$Q$15*G7*2),IF(AND(H7="NO",I7='Insumos y gastos'!$P$6),Productos!J7+('Insumos y gastos'!$Q$15*Productos!G7),IF(AND(H7="SI",I7='Insumos y gastos'!$R$6),J7+('Insumos y gastos'!$S$15*G7*2),IF(AND(H7="NO",I7='Insumos y gastos'!$R$6),Productos!J7+('Insumos y gastos'!$S$15*Productos!G7),IF(AND(H7="SI",I7='Insumos y gastos'!$T$6),J7+('Insumos y gastos'!$U$15*G7*2),IF(AND(H7="NO",I7='Insumos y gastos'!$T$6),Productos!J7+('Insumos y gastos'!$U$15*Productos!G7),0)))))))))))) -> 0 | M7: =IFERROR(VLOOKUP(L7,Tabla1[[#All],[Nombre insumo]:[Pr. Unidad]],4,0),0) -> 0 | Q7: =N7*M7 -> 0 | R7: =IF(AND(O7="SI",P7='Insumos y gastos'!$J$6),Q7+('Insumos y gastos'!$K$15*N7*2),IF(AND(O7="NO",P7='Insumos y gastos'!$J$6),Productos!Q7+('Insumos y gastos'!$K$15*Productos!N7),IF(AND(O7="SI",P7='Insumos y gastos'!$L$6),Q7+('Insumos y gastos'!$M$15*N7*2),IF(AND(O7="NO",P7='Insumos y gastos'!$L$6),Productos!Q7+('Insumos y gastos'!$M$15*Productos!N7),IF(AND(O7="SI",P7='Insumos y gastos'!$N$6),Q7+('Insumos y gastos'!$O$15*N7*2),IF(AND(O7="NO",P7='Insumos y gastos'!$N$6),Productos!Q7+('Insumos y gastos'!$O$15*Productos!N7),IF(AND(O7="SI",P7='Insumos y gastos'!$P$6),Q7+('Insumos y gastos'!$Q$15*N7*2),IF(AND(O7="NO",P7='Insumos y gastos'!$P$6),Productos!Q7+('Insumos y gastos'!$Q$15*Productos!N7),IF(AND(O7="SI",P7='Insumos y gastos'!$R$6),Q7+('Insumos y gastos'!$S$15*N7*2),IF(AND(O7="NO",P7='Insumos y gastos'!$R$6),Productos!Q7+('Insumos y gastos'!$S$15*Productos!N7),IF(AND(O7="SI",P7='Insumos y gastos'!$T$6),Q7+('Insumos y gastos'!$U$15*N7*2),IF(AND(O7="NO",P7='Insumos y gastos'!$T$6),Productos!Q7+('Insumos y gastos'!$U$15*Productos!N7),0)))))))))))) -> 0 | T7: =IFERROR(VLOOKUP(S7,Tabla1[[#All],[Nombre insumo]:[Pr. Unidad]],4,0),0) -> 0 | X7: =U7*T7 -> 0 | Y7: =IF(AND(V7="SI",W7='Insumos y gastos'!$J$6),X7+('Insumos y gastos'!$K$15*U7*2),IF(AND(V7="NO",W7='Insumos y gastos'!$J$6),Productos!X7+('Insumos y gastos'!$K$15*Productos!U7),IF(AND(V7="SI",W7='Insumos y gastos'!$L$6),X7+('Insumos y gastos'!$M$15*U7*2),IF(AND(V7="NO",W7='Insumos y gastos'!$L$6),Productos!X7+('Insumos y gastos'!$M$15*Productos!U7),IF(AND(V7="SI",W7='Insumos y gastos'!$N$6),X7+('Insumos y gastos'!$O$15*U7*2),IF(AND(V7="NO",W7='Insumos y gastos'!$N$6),Productos!X7+('Insumos y gastos'!$O$15*Productos!U7),IF(AND(V7="SI",W7='Insumos y gastos'!$P$6),X7+('Insumos y gastos'!$Q$15*U7*2),IF(AND(V7="NO",W7='Insumos y gastos'!$P$6),Productos!X7+('Insumos y gastos'!$Q$15*Productos!U7),IF(AND(V7="SI",W7='Insumos y gastos'!$R$6),X7+('Insumos y gastos'!$S$15*U7*2),IF(AND(V7="NO",W7='Insumos y gastos'!$R$6),Productos!X7+('Insumos y gastos'!$S$15*Productos!U7),IF(AND(V7="SI",W7='Insumos y gastos'!$T$6),X7+('Insumos y gastos'!$U$15*U7*2),IF(AND(V7="NO",W7='Insumos y gastos'!$T$6),Productos!X7+('Insumos y gastos'!$U$15*Productos!U7),0)))))))))))) -> 0 | AA7: =IFERROR(VLOOKUP(Z7,Tabla1[[#All],[Nombre insumo]:[Pr. Unidad]],4,0),0) -> 0 | AE7: =AB7*AA7 -> 0 | AF7: =IF(AND(AC7="SI",AD7='Insumos y gastos'!$J$6),AE7+('Insumos y gastos'!$K$15*AB7*2),IF(AND(AC7="NO",AD7='Insumos y gastos'!$J$6),Productos!AE7+('Insumos y gastos'!$K$15*Productos!AB7),IF(AND(AC7="SI",AD7='Insumos y gastos'!$L$6),AE7+('Insumos y gastos'!$M$15*AB7*2),IF(AND(AC7="NO",AD7='Insumos y gastos'!$L$6),Productos!AE7+('Insumos y gastos'!$M$15*Productos!AB7),IF(AND(AC7="SI",AD7='Insumos y gastos'!$N$6),AE7+('Insumos y gastos'!$O$15*AB7*2),IF(AND(AC7="NO",AD7='Insumos y gastos'!$N$6),Productos!AE7+('Insumos y gastos'!$O$15*Productos!AB7),IF(AND(AC7="SI",AD7='Insumos y gastos'!$P$6),AE7+('Insumos y gastos'!$Q$15*AB7*2),IF(AND(AC7="NO",AD7='Insumos y gastos'!$P$6),Productos!AE7+('Insumos y gastos'!$Q$15*Productos!AB7),IF(AND(AC7="SI",AD7='Insumos y gastos'!$R$6),AE7+('Insumos y gastos'!$S$15*AB7*2),IF(AND(AC7="NO",AD7='Insumos y gastos'!$R$6),Productos!AE7+('Insumos y gastos'!$S$15*Productos!AB7),IF(AND(AC7="SI",AD7='Insumos y gastos'!$T$6),AE7+('Insumos y gastos'!$U$15*AB7*2),IF(AND(AC7="NO",AD7='Insumos y gastos'!$T$6),Productos!AE7+('Insumos y gastos'!$U$15*Productos!AB7),0)))))))))))) -> 0 | AH7: =IFERROR(VLOOKUP(AG7,Tabla1[[#All],[Nombre insumo]:[Pr. Unidad]],4,0),0) -> 0 | AL7: =AI7*AH7 -> 0 | AM7: =IF(AND(AJ7="SI",AK7='Insumos y gastos'!$J$6),AL7+('Insumos y gastos'!$K$15*AI7*2),IF(AND(AJ7="NO",AK7='Insumos y gastos'!$J$6),Productos!AL7+('Insumos y gastos'!$K$15*Productos!AI7),IF(AND(AJ7="SI",AK7='Insumos y gastos'!$L$6),AL7+('Insumos y gastos'!$M$15*AI7*2),IF(AND(AJ7="NO",AK7='Insumos y gastos'!$L$6),Productos!AL7+('Insumos y gastos'!$M$15*Productos!AI7),IF(AND(AJ7="SI",AK7='Insumos y gastos'!$N$6),AL7+('Insumos y gastos'!$O$15*AI7*2),IF(AND(AJ7="NO",AK7='Insumos y gastos'!$N$6),Productos!AL7+('Insumos y gastos'!$O$15*Productos!AI7),IF(AND(AJ7="SI",AK7='Insumos y gastos'!$P$6),AL7+('Insumos y gastos'!$Q$15*AI7*2),IF(AND(AJ7="NO",AK7='Insumos y gastos'!$P$6),Productos!AL7+('Insumos y gastos'!$Q$15*Productos!AI7),IF(AND(AJ7="SI",AK7='Insumos y gastos'!$R$6),AL7+('Insumos y gastos'!$S$15*AI7*2),IF(AND(AJ7="NO",AK7='Insumos y gastos'!$R$6),Productos!AL7+('Insumos y gastos'!$S$15*Productos!AI7),IF(AND(AJ7="SI",AK7='Insumos y gastos'!$T$6),AL7+('Insumos y gastos'!$U$15*AI7*2),IF(AND(AJ7="NO",AK7='Insumos y gastos'!$T$6),Productos!AL7+('Insumos y gastos'!$U$15*Productos!AI7),0)))))))))))) -> 0 | AO7: =IFERROR(VLOOKUP(AN7,Tabla1[[#All],[Nombre insumo]:[Pr. Unidad]],4,0),0) -> 0 | AQ7: =IF(Tabla3[[#This Row],[Costo insumo 1]]>0,Tabla3[[#This Row],[Cantidad insumo 1]]*Tabla3[[#This Row],[Costo insumo 1]],0) -> 0 | AS7: =IFERROR(VLOOKUP(AR7,Tabla1[[#All],[Nombre insumo]:[Pr. Unidad]],4,0),0) -> 0 | AU7: =IF(Tabla3[[#This Row],[Costo insumo 2]]>0,Tabla3[[#This Row],[Cantidad insumo 2]]*Tabla3[[#This Row],[Costo insumo 2]],0) -> 0 | AW7: =IFERROR(VLOOKUP(AV7,Tabla1[[#All],[Nombre insumo]:[Pr. Unidad]],4,0),0) -> 0 | AY7: =IF(Tabla3[[#This Row],[Costo insumo 3]]>0,Tabla3[[#This Row],[Cantidad insumo 3]]*Tabla3[[#This Row],[Costo insumo 3]],0) -> 0 | BA7: =IFERROR(VLOOKUP(AZ7,Tabla1[[#All],[Nombre insumo]:[Pr. Unidad]],4,0),0) -> 0 | BC7: =IF(Tabla3[[#This Row],[Costo insumo 4]]>0,Tabla3[[#This Row],[Cantidad insumo 4]]*Tabla3[[#This Row],[Costo insumo 4]],0) -> 0 | BE7: =IFERROR(VLOOKUP(BD7,Tabla1[[#All],[Nombre insumo]:[Pr. Unidad]],4,0),0) -> 0 | BG7: =IF(Tabla3[[#This Row],[Costo insumo 5]]>0,Tabla3[[#This Row],[Cantidad insumo 5]]*Tabla3[[#This Row],[Costo insumo 5]],0) -> 0 | BH7: =Tabla3[[#This Row],[Subtotal impresión 1]]+Tabla3[[#This Row],[Subtotal impresión 2]]+Tabla3[[#This Row],[Subtotal impresión 3]]+Tabla3[[#This Row],[Subtotal impresión 4]]+Tabla3[[#This Row],[Subtotal impresión 5]]+Tabla3[[#This Row],[Subtotal insumos 1]]+Tabla3[[#This Row],[Subtotal insumos 2]]+Tabla3[[#This Row],[Subtotal insumos 3]]+Tabla3[[#This Row],[Subtotal insumos 4]]+Tabla3[[#This Row],[Subtotal insumos 5]] -> 0 | BJ7: =BI7*'Insumos y gastos'!$M$50 -> 0 | BK7: =BI7*'Insumos y gastos'!$Q$24 -> 0 | BL7: =Tabla3[[#This Row],[Costo sin servicios]]+Tabla3[[#This Row],[Costo servicios]]+Tabla3[[#This Row],[Costo mano de obra]] -> 0
A8: 10006 | F8: =IFERROR(VLOOKUP(E8,Tabla1[[#All],[Nombre insumo]:[Pr. Unidad]],4,0),0) -> 0 | J8: =G8*F8 -> 0 | K8: =IF(AND(H8="SI",I8='Insumos y gastos'!$J$6),J8+('Insumos y gastos'!$K$15*G8*2),IF(AND(H8="NO",I8='Insumos y gastos'!$J$6),Productos!J8+('Insumos y gastos'!$K$15*Productos!G8),IF(AND(H8="SI",I8='Insumos y gastos'!$L$6),J8+('Insumos y gastos'!$M$15*G8*2),IF(AND(H8="NO",I8='Insumos y gastos'!$L$6),Productos!J8+('Insumos y gastos'!$M$15*Productos!G8),IF(AND(H8="SI",I8='Insumos y gastos'!$N$6),J8+('Insumos y gastos'!$O$15*G8*2),IF(AND(H8="NO",I8='Insumos y gastos'!$N$6),Productos!J8+('Insumos y gastos'!$O$15*Productos!G8),IF(AND(H8="SI",I8='Insumos y gastos'!$P$6),J8+('Insumos y gastos'!$Q$15*G8*2),IF(AND(H8="NO",I8='Insumos y gastos'!$P$6),Productos!J8+('Insumos y gastos'!$Q$15*Productos!G8),IF(AND(H8="SI",I8='Insumos y gastos'!$R$6),J8+('Insumos y gastos'!$S$15*G8*2),IF(AND(H8="NO",I8='Insumos y gastos'!$R$6),Productos!J8+('Insumos y gastos'!$S$15*Productos!G8),IF(AND(H8="SI",I8='Insumos y gastos'!$T$6),J8+('Insumos y gastos'!$U$15*G8*2),IF(AND(H8="NO",I8='Insumos y gastos'!$T$6),Productos!J8+('Insumos y gastos'!$U$15*Productos!G8),0)))))))))))) -> 0 | M8: =IFERROR(VLOOKUP(L8,Tabla1[[#All],[Nombre insumo]:[Pr. Unidad]],4,0),0) -> 0 | Q8: =N8*M8 -> 0 | R8: =IF(AND(O8="SI",P8='Insumos y gastos'!$J$6),Q8+('Insumos y gastos'!$K$15*N8*2),IF(AND(O8="NO",P8='Insumos y gastos'!$J$6),Productos!Q8+('Insumos y gastos'!$K$15*Productos!N8),IF(AND(O8="SI",P8='Insumos y gastos'!$L$6),Q8+('Insumos y gastos'!$M$15*N8*2),IF(AND(O8="NO",P8='Insumos y gastos'!$L$6),Productos!Q8+('Insumos y gastos'!$M$15*Productos!N8),IF(AND(O8="SI",P8='Insumos y gastos'!$N$6),Q8+('Insumos y gastos'!$O$15*N8*2),IF(AND(O8="NO",P8='Insumos y gastos'!$N$6),Productos!Q8+('Insumos y gastos'!$O$15*Productos!N8),IF(AND(O8="SI",P8='Insumos y gastos'!$P$6),Q8+('Insumos y gastos'!$Q$15*N8*2),IF(AND(O8="NO",P8='Insumos y gastos'!$P$6),Productos!Q8+('Insumos y gastos'!$Q$15*Productos!N8),IF(AND(O8="SI",P8='Insumos y gastos'!$R$6),Q8+('Insumos y gastos'!$S$15*N8*2),IF(AND(O8="NO",P8='Insumos y gastos'!$R$6),Productos!Q8+('Insumos y gastos'!$S$15*Productos!N8),IF(AND(O8="SI",P8='Insumos y gastos'!$T$6),Q8+('Insumos y gastos'!$U$15*N8*2),IF(AND(O8="NO",P8='Insumos y gastos'!$T$6),Productos!Q8+('Insumos y gastos'!$U$15*Productos!N8),0)))))))))))) -> 0 | T8: =IFERROR(VLOOKUP(S8,Tabla1[[#All],[Nombre insumo]:[Pr. Unidad]],4,0),0) -> 0 | X8: =U8*T8 -> 0 | Y8: =IF(AND(V8="SI",W8='Insumos y gastos'!$J$6),X8+('Insumos y gastos'!$K$15*U8*2),IF(AND(V8="NO",W8='Insumos y gastos'!$J$6),Productos!X8+('Insumos y gastos'!$K$15*Productos!U8),IF(AND(V8="SI",W8='Insumos y gastos'!$L$6),X8+('Insumos y gastos'!$M$15*U8*2),IF(AND(V8="NO",W8='Insumos y gastos'!$L$6),Productos!X8+('Insumos y gastos'!$M$15*Productos!U8),IF(AND(V8="SI",W8='Insumos y gastos'!$N$6),X8+('Insumos y gastos'!$O$15*U8*2),IF(AND(V8="NO",W8='Insumos y gastos'!$N$6),Productos!X8+('Insumos y gastos'!$O$15*Productos!U8),IF(AND(V8="SI",W8='Insumos y gastos'!$P$6),X8+('Insumos y gastos'!$Q$15*U8*2),IF(AND(V8="NO",W8='Insumos y gastos'!$P$6),Productos!X8+('Insumos y gastos'!$Q$15*Productos!U8),IF(AND(V8="SI",W8='Insumos y gastos'!$R$6),X8+('Insumos y gastos'!$S$15*U8*2),IF(AND(V8="NO",W8='Insumos y gastos'!$R$6),Productos!X8+('Insumos y gastos'!$S$15*Productos!U8),IF(AND(V8="SI",W8='Insumos y gastos'!$T$6),X8+('Insumos y gastos'!$U$15*U8*2),IF(AND(V8="NO",W8='Insumos y gastos'!$T$6),Productos!X8+('Insumos y gastos'!$U$15*Productos!U8),0)))))))))))) -> 0 | AA8: =IFERROR(VLOOKUP(Z8,Tabla1[[#All],[Nombre insumo]:[Pr. Unidad]],4,0),0) -> 0 | AE8: =AB8*AA8 -> 0 | AF8: =IF(AND(AC8="SI",AD8='Insumos y gastos'!$J$6),AE8+('Insumos y gastos'!$K$15*AB8*2),IF(AND(AC8="NO",AD8='Insumos y gastos'!$J$6),Productos!AE8+('Insumos y gastos'!$K$15*Productos!AB8),IF(AND(AC8="SI",AD8='Insumos y gastos'!$L$6),AE8+('Insumos y gastos'!$M$15*AB8*2),IF(AND(AC8="NO",AD8='Insumos y gastos'!$L$6),Productos!AE8+('Insumos y gastos'!$M$15*Productos!AB8),IF(AND(AC8="SI",AD8='Insumos y gastos'!$N$6),AE8+('Insumos y gastos'!$O$15*AB8*2),IF(AND(AC8="NO",AD8='Insumos y gastos'!$N$6),Productos!AE8+('Insumos y gastos'!$O$15*Productos!AB8),IF(AND(AC8="SI",AD8='Insumos y gastos'!$P$6),AE8+('Insumos y gastos'!$Q$15*AB8*2),IF(AND(AC8="NO",AD8='Insumos y gastos'!$P$6),Productos!AE8+('Insumos y gastos'!$Q$15*Productos!AB8),IF(AND(AC8="SI",AD8='Insumos y gastos'!$R$6),AE8+('Insumos y gastos'!$S$15*AB8*2),IF(AND(AC8="NO",AD8='Insumos y gastos'!$R$6),Productos!AE8+('Insumos y gastos'!$S$15*Productos!AB8),IF(AND(AC8="SI",AD8='Insumos y gastos'!$T$6),AE8+('Insumos y gastos'!$U$15*AB8*2),IF(AND(AC8="NO",AD8='Insumos y gastos'!$T$6),Productos!AE8+('Insumos y gastos'!$U$15*Productos!AB8),0)))))))))))) -> 0 | AH8: =IFERROR(VLOOKUP(AG8,Tabla1[[#All],[Nombre insumo]:[Pr. Unidad]],4,0),0) -> 0 | AL8: =AI8*AH8 -> 0 | AM8: =IF(AND(AJ8="SI",AK8='Insumos y gastos'!$J$6),AL8+('Insumos y gastos'!$K$15*AI8*2),IF(AND(AJ8="NO",AK8='Insumos y gastos'!$J$6),Productos!AL8+('Insumos y gastos'!$K$15*Productos!AI8),IF(AND(AJ8="SI",AK8='Insumos y gastos'!$L$6),AL8+('Insumos y gastos'!$M$15*AI8*2),IF(AND(AJ8="NO",AK8='Insumos y gastos'!$L$6),Productos!AL8+('Insumos y gastos'!$M$15*Productos!AI8),IF(AND(AJ8="SI",AK8='Insumos y gastos'!$N$6),AL8+('Insumos y gastos'!$O$15*AI8*2),IF(AND(AJ8="NO",AK8='Insumos y gastos'!$N$6),Productos!AL8+('Insumos y gastos'!$O$15*Productos!AI8),IF(AND(AJ8="SI",AK8='Insumos y gastos'!$P$6),AL8+('Insumos y gastos'!$Q$15*AI8*2),IF(AND(AJ8="NO",AK8='Insumos y gastos'!$P$6),Productos!AL8+('Insumos y gastos'!$Q$15*Productos!AI8),IF(AND(AJ8="SI",AK8='Insumos y gastos'!$R$6),AL8+('Insumos y gastos'!$S$15*AI8*2),IF(AND(AJ8="NO",AK8='Insumos y gastos'!$R$6),Productos!AL8+('Insumos y gastos'!$S$15*Productos!AI8),IF(AND(AJ8="SI",AK8='Insumos y gastos'!$T$6),AL8+('Insumos y gastos'!$U$15*AI8*2),IF(AND(AJ8="NO",AK8='Insumos y gastos'!$T$6),Productos!AL8+('Insumos y gastos'!$U$15*Productos!AI8),0)))))))))))) -> 0 | AO8: =IFERROR(VLOOKUP(AN8,Tabla1[[#All],[Nombre insumo]:[Pr. Unidad]],4,0),0) -> 0 | AQ8: =IF(Tabla3[[#This Row],[Costo insumo 1]]>0,Tabla3[[#This Row],[Cantidad insumo 1]]*Tabla3[[#This Row],[Costo insumo 1]],0) -> 0 | AS8: =IFERROR(VLOOKUP(AR8,Tabla1[[#All],[Nombre insumo]:[Pr. Unidad]],4,0),0) -> 0 | AU8: =IF(Tabla3[[#This Row],[Costo insumo 2]]>0,Tabla3[[#This Row],[Cantidad insumo 2]]*Tabla3[[#This Row],[Costo insumo 2]],0) -> 0 | AW8: =IFERROR(VLOOKUP(AV8,Tabla1[[#All],[Nombre insumo]:[Pr. Unidad]],4,0),0) -> 0 | AY8: =IF(Tabla3[[#This Row],[Costo insumo 3]]>0,Tabla3[[#This Row],[Cantidad insumo 3]]*Tabla3[[#This Row],[Costo insumo 3]],0) -> 0 | BA8: =IFERROR(VLOOKUP(AZ8,Tabla1[[#All],[Nombre insumo]:[Pr. Unidad]],4,0),0) -> 0 | BC8: =IF(Tabla3[[#This Row],[Costo insumo 4]]>0,Tabla3[[#This Row],[Cantidad insumo 4]]*Tabla3[[#This Row],[Costo insumo 4]],0) -> 0 | BE8: =IFERROR(VLOOKUP(BD8,Tabla1[[#All],[Nombre insumo]:[Pr. Unidad]],4,0),0) -> 0 | BG8: =IF(Tabla3[[#This Row],[Costo insumo 5]]>0,Tabla3[[#This Row],[Cantidad insumo 5]]*Tabla3[[#This Row],[Costo insumo 5]],0) -> 0 | BH8: =Tabla3[[#This Row],[Subtotal impresión 1]]+Tabla3[[#This Row],[Subtotal impresión 2]]+Tabla3[[#This Row],[Subtotal impresión 3]]+Tabla3[[#This Row],[Subtotal impresión 4]]+Tabla3[[#This Row],[Subtotal impresión 5]]+Tabla3[[#This Row],[Subtotal insumos 1]]+Tabla3[[#This Row],[Subtotal insumos 2]]+Tabla3[[#This Row],[Subtotal insumos 3]]+Tabla3[[#This Row],[Subtotal insumos 4]]+Tabla3[[#This Row],[Subtotal insumos 5]] -> 0 | BJ8: =BI8*'Insumos y gastos'!$M$50 -> 0 | BK8: =BI8*'Insumos y gastos'!$Q$24 -> 0 | BL8: =Tabla3[[#This Row],[Costo sin servicios]]+Tabla3[[#This Row],[Costo servicios]]+Tabla3[[#This Row],[Costo mano de obra]] -> 0
A9: 10007 | F9: =IFERROR(VLOOKUP(E9,Tabla1[[#All],[Nombre insumo]:[Pr. Unidad]],4,0),0) -> 0 | J9: =G9*F9 -> 0 | K9: =IF(AND(H9="SI",I9='Insumos y gastos'!$J$6),J9+('Insumos y gastos'!$K$15*G9*2),IF(AND(H9="NO",I9='Insumos y gastos'!$J$6),Productos!J9+('Insumos y gastos'!$K$15*Productos!G9),IF(AND(H9="SI",I9='Insumos y gastos'!$L$6),J9+('Insumos y gastos'!$M$15*G9*2),IF(AND(H9="NO",I9='Insumos y gastos'!$L$6),Productos!J9+('Insumos y gastos'!$M$15*Productos!G9),IF(AND(H9="SI",I9='Insumos y gastos'!$N$6),J9+('Insumos y gastos'!$O$15*G9*2),IF(AND(H9="NO",I9='Insumos y gastos'!$N$6),Productos!J9+('Insumos y gastos'!$O$15*Productos!G9),IF(AND(H9="SI",I9='Insumos y gastos'!$P$6),J9+('Insumos y gastos'!$Q$15*G9*2),IF(AND(H9="NO",I9='Insumos y gastos'!$P$6),Productos!J9+('Insumos y gastos'!$Q$15*Productos!G9),IF(AND(H9="SI",I9='Insumos y gastos'!$R$6),J9+('Insumos y gastos'!$S$15*G9*2),IF(AND(H9="NO",I9='Insumos y gastos'!$R$6),Productos!J9+('Insumos y gastos'!$S$15*Productos!G9),IF(AND(H9="SI",I9='Insumos y gastos'!$T$6),J9+('Insumos y gastos'!$U$15*G9*2),IF(AND(H9="NO",I9='Insumos y gastos'!$T$6),Productos!J9+('Insumos y gastos'!$U$15*Productos!G9),0)))))))))))) -> 0 | M9: =IFERROR(VLOOKUP(L9,Tabla1[[#All],[Nombre insumo]:[Pr. Unidad]],4,0),0) -> 0 | Q9: =N9*M9 -> 0 | R9: =IF(AND(O9="SI",P9='Insumos y gastos'!$J$6),Q9+('Insumos y gastos'!$K$15*N9*2),IF(AND(O9="NO",P9='Insumos y gastos'!$J$6),Productos!Q9+('Insumos y gastos'!$K$15*Productos!N9),IF(AND(O9="SI",P9='Insumos y gastos'!$L$6),Q9+('Insumos y gastos'!$M$15*N9*2),IF(AND(O9="NO",P9='Insumos y gastos'!$L$6),Productos!Q9+('Insumos y gastos'!$M$15*Productos!N9),IF(AND(O9="SI",P9='Insumos y gastos'!$N$6),Q9+('Insumos y gastos'!$O$15*N9*2),IF(AND(O9="NO",P9='Insumos y gastos'!$N$6),Productos!Q9+('Insumos y gastos'!$O$15*Productos!N9),IF(AND(O9="SI",P9='Insumos y gastos'!$P$6),Q9+('Insumos y gastos'!$Q$15*N9*2),IF(AND(O9="NO",P9='Insumos y gastos'!$P$6),Productos!Q9+('Insumos y gastos'!$Q$15*Productos!N9),IF(AND(O9="SI",P9='Insumos y gastos'!$R$6),Q9+('Insumos y gastos'!$S$15*N9*2),IF(AND(O9="NO",P9='Insumos y gastos'!$R$6),Productos!Q9+('Insumos y gastos'!$S$15*Productos!N9),IF(AND(O9="SI",P9='Insumos y gastos'!$T$6),Q9+('Insumos y gastos'!$U$15*N9*2),IF(AND(O9="NO",P9='Insumos y gastos'!$T$6),Productos!Q9+('Insumos y gastos'!$U$15*Productos!N9),0)))))))))))) -> 0 | T9: =IFERROR(VLOOKUP(S9,Tabla1[[#All],[Nombre insumo]:[Pr. Unidad]],4,0),0) -> 0 | X9: =U9*T9 -> 0 | Y9: =IF(AND(V9="SI",W9='Insumos y gastos'!$J$6),X9+('Insumos y gastos'!$K$15*U9*2),IF(AND(V9="NO",W9='Insumos y gastos'!$J$6),Productos!X9+('Insumos y gastos'!$K$15*Productos!U9),IF(AND(V9="SI",W9='Insumos y gastos'!$L$6),X9+('Insumos y gastos'!$M$15*U9*2),IF(AND(V9="NO",W9='Insumos y gastos'!$L$6),Productos!X9+('Insumos y gastos'!$M$15*Productos!U9),IF(AND(V9="SI",W9='Insumos y gastos'!$N$6),X9+('Insumos y gastos'!$O$15*U9*2),IF(AND(V9="NO",W9='Insumos y gastos'!$N$6),Productos!X9+('Insumos y gastos'!$O$15*Productos!U9),IF(AND(V9="SI",W9='Insumos y gastos'!$P$6),X9+('Insumos y gastos'!$Q$15*U9*2),IF(AND(V9="NO",W9='Insumos y gastos'!$P$6),Productos!X9+('Insumos y gastos'!$Q$15*Productos!U9),IF(AND(V9="SI",W9='Insumos y gastos'!$R$6),X9+('Insumos y gastos'!$S$15*U9*2),IF(AND(V9="NO",W9='Insumos y gastos'!$R$6),Productos!X9+('Insumos y gastos'!$S$15*Productos!U9),IF(AND(V9="SI",W9='Insumos y gastos'!$T$6),X9+('Insumos y gastos'!$U$15*U9*2),IF(AND(V9="NO",W9='Insumos y gastos'!$T$6),Productos!X9+('Insumos y gastos'!$U$15*Productos!U9),0)))))))))))) -> 0 | AA9: =IFERROR(VLOOKUP(Z9,Tabla1[[#All],[Nombre insumo]:[Pr. Unidad]],4,0),0) -> 0 | AE9: =AB9*AA9 -> 0 | AF9: =IF(AND(AC9="SI",AD9='Insumos y gastos'!$J$6),AE9+('Insumos y gastos'!$K$15*AB9*2),IF(AND(AC9="NO",AD9='Insumos y gastos'!$J$6),Productos!AE9+('Insumos y gastos'!$K$15*Productos!AB9),IF(AND(AC9="SI",AD9='Insumos y gastos'!$L$6),AE9+('Insumos y gastos'!$M$15*AB9*2),IF(AND(AC9="NO",AD9='Insumos y gastos'!$L$6),Productos!AE9+('Insumos y gastos'!$M$15*Productos!AB9),IF(AND(AC9="SI",AD9='Insumos y gastos'!$N$6),AE9+('Insumos y gastos'!$O$15*AB9*2),IF(AND(AC9="NO",AD9='Insumos y gastos'!$N$6),Productos!AE9+('Insumos y gastos'!$O$15*Productos!AB9),IF(AND(AC9="SI",AD9='Insumos y gastos'!$P$6),AE9+('Insumos y gastos'!$Q$15*AB9*2),IF(AND(AC9="NO",AD9='Insumos y gastos'!$P$6),Productos!AE9+('Insumos y gastos'!$Q$15*Productos!AB9),IF(AND(AC9="SI",AD9='Insumos y gastos'!$R$6),AE9+('Insumos y gastos'!$S$15*AB9*2),IF(AND(AC9="NO",AD9='Insumos y gastos'!$R$6),Productos!AE9+('Insumos y gastos'!$S$15*Productos!AB9),IF(AND(AC9="SI",AD9='Insumos y gastos'!$T$6),AE9+('Insumos y gastos'!$U$15*AB9*2),IF(AND(AC9="NO",AD9='Insumos y gastos'!$T$6),Productos!AE9+('Insumos y gastos'!$U$15*Productos!AB9),0)))))))))))) -> 0 | AH9: =IFERROR(VLOOKUP(AG9,Tabla1[[#All],[Nombre insumo]:[Pr. Unidad]],4,0),0) -> 0 | AL9: =AI9*AH9 -> 0 | AM9: =IF(AND(AJ9="SI",AK9='Insumos y gastos'!$J$6),AL9+('Insumos y gastos'!$K$15*AI9*2),IF(AND(AJ9="NO",AK9='Insumos y gastos'!$J$6),Productos!AL9+('Insumos y gastos'!$K$15*Productos!AI9),IF(AND(AJ9="SI",AK9='Insumos y gastos'!$L$6),AL9+('Insumos y gastos'!$M$15*AI9*2),IF(AND(AJ9="NO",AK9='Insumos y gastos'!$L$6),Productos!AL9+('Insumos y gastos'!$M$15*Productos!AI9),IF(AND(AJ9="SI",AK9='Insumos y gastos'!$N$6),AL9+('Insumos y gastos'!$O$15*AI9*2),IF(AND(AJ9="NO",AK9='Insumos y gastos'!$N$6),Productos!AL9+('Insumos y gastos'!$O$15*Productos!AI9),IF(AND(AJ9="SI",AK9='Insumos y gastos'!$P$6),AL9+('Insumos y gastos'!$Q$15*AI9*2),IF(AND(AJ9="NO",AK9='Insumos y gastos'!$P$6),Productos!AL9+('Insumos y gastos'!$Q$15*Productos!AI9),IF(AND(AJ9="SI",AK9='Insumos y gastos'!$R$6),AL9+('Insumos y gastos'!$S$15*AI9*2),IF(AND(AJ9="NO",AK9='Insumos y gastos'!$R$6),Productos!AL9+('Insumos y gastos'!$S$15*Productos!AI9),IF(AND(AJ9="SI",AK9='Insumos y gastos'!$T$6),AL9+('Insumos y gastos'!$U$15*AI9*2),IF(AND(AJ9="NO",AK9='Insumos y gastos'!$T$6),Productos!AL9+('Insumos y gastos'!$U$15*Productos!AI9),0)))))))))))) -> 0 | AO9: =IFERROR(VLOOKUP(AN9,Tabla1[[#All],[Nombre insumo]:[Pr. Unidad]],4,0),0) -> 0 | AQ9: =IF(Tabla3[[#This Row],[Costo insumo 1]]>0,Tabla3[[#This Row],[Cantidad insumo 1]]*Tabla3[[#This Row],[Costo insumo 1]],0) -> 0 | AS9: =IFERROR(VLOOKUP(AR9,Tabla1[[#All],[Nombre insumo]:[Pr. Unidad]],4,0),0) -> 0 | AU9: =IF(Tabla3[[#This Row],[Costo insumo 2]]>0,Tabla3[[#This Row],[Cantidad insumo 2]]*Tabla3[[#This Row],[Costo insumo 2]],0) -> 0 | AW9: =IFERROR(VLOOKUP(AV9,Tabla1[[#All],[Nombre insumo]:[Pr. Unidad]],4,0),0) -> 0 | AY9: =IF(Tabla3[[#This Row],[Costo insumo 3]]>0,Tabla3[[#This Row],[Cantidad insumo 3]]*Tabla3[[#This Row],[Costo insumo 3]],0) -> 0 | BA9: =IFERROR(VLOOKUP(AZ9,Tabla1[[#All],[Nombre insumo]:[Pr. Unidad]],4,0),0) -> 0 | BC9: =IF(Tabla3[[#This Row],[Costo insumo 4]]>0,Tabla3[[#This Row],[Cantidad insumo 4]]*Tabla3[[#This Row],[Costo insumo 4]],0) -> 0 | BE9: =IFERROR(VLOOKUP(BD9,Tabla1[[#All],[Nombre insumo]:[Pr. Unidad]],4,0),0) -> 0 | BG9: =IF(Tabla3[[#This Row],[Costo insumo 5]]>0,Tabla3[[#This Row],[Cantidad insumo 5]]*Tabla3[[#This Row],[Costo insumo 5]],0) -> 0 | BH9: =Tabla3[[#This Row],[Subtotal impresión 1]]+Tabla3[[#This Row],[Subtotal impresión 2]]+Tabla3[[#This Row],[Subtotal impresión 3]]+Tabla3[[#This Row],[Subtotal impresión 4]]+Tabla3[[#This Row],[Subtotal impresión 5]]+Tabla3[[#This Row],[Subtotal insumos 1]]+Tabla3[[#This Row],[Subtotal insumos 2]]+Tabla3[[#This Row],[Subtotal insumos 3]]+Tabla3[[#This Row],[Subtotal insumos 4]]+Tabla3[[#This Row],[Subtotal insumos 5]] -> 0 | BJ9: =BI9*'Insumos y gastos'!$M$50 -> 0 | BK9: =BI9*'Insumos y gastos'!$Q$24 -> 0 | BL9: =Tabla3[[#This Row],[Costo sin servicios]]+Tabla3[[#This Row],[Costo servicios]]+Tabla3[[#This Row],[Costo mano de obra]] -> 0
A10: 10008 | F10: =IFERROR(VLOOKUP(E10,Tabla1[[#All],[Nombre insumo]:[Pr. Unidad]],4,0),0) -> 0 | J10: =G10*F10 -> 0 | K10: =IF(AND(H10="SI",I10='Insumos y gastos'!$J$6),J10+('Insumos y gastos'!$K$15*G10*2),IF(AND(H10="NO",I10='Insumos y gastos'!$J$6),Productos!J10+('Insumos y gastos'!$K$15*Productos!G10),IF(AND(H10="SI",I10='Insumos y gastos'!$L$6),J10+('Insumos y gastos'!$M$15*G10*2),IF(AND(H10="NO",I10='Insumos y gastos'!$L$6),Productos!J10+('Insumos y gastos'!$M$15*Productos!G10),IF(AND(H10="SI",I10='Insumos y gastos'!$N$6),J10+('Insumos y gastos'!$O$15*G10*2),IF(AND(H10="NO",I10='Insumos y gastos'!$N$6),Productos!J10+('Insumos y gastos'!$O$15*Productos!G10),IF(AND(H10="SI",I10='Insumos y gastos'!$P$6),J10+('Insumos y gastos'!$Q$15*G10*2),IF(AND(H10="NO",I10='Insumos y gastos'!$P$6),Productos!J10+('Insumos y gastos'!$Q$15*Productos!G10),IF(AND(H10="SI",I10='Insumos y gastos'!$R$6),J10+('Insumos y gastos'!$S$15*G10*2),IF(AND(H10="NO",I10='Insumos y gastos'!$R$6),Productos!J10+('Insumos y gastos'!$S$15*Productos!G10),IF(AND(H10="SI",I10='Insumos y gastos'!$T$6),J10+('Insumos y gastos'!$U$15*G10*2),IF(AND(H10="NO",I10='Insumos y gastos'!$T$6),Productos!J10+('Insumos y gastos'!$U$15*Productos!G10),0)))))))))))) -> 0 | M10: =IFERROR(VLOOKUP(L10,Tabla1[[#All],[Nombre insumo]:[Pr. Unidad]],4,0),0) -> 0 | Q10: =N10*M10 -> 0 | R10: =IF(AND(O10="SI",P10='Insumos y gastos'!$J$6),Q10+('Insumos y gastos'!$K$15*N10*2),IF(AND(O10="NO",P10='Insumos y gastos'!$J$6),Productos!Q10+('Insumos y gastos'!$K$15*Productos!N10),IF(AND(O10="SI",P10='Insumos y gastos'!$L$6),Q10+('Insumos y gastos'!$M$15*N10*2),IF(AND(O10="NO",P10='Insumos y gastos'!$L$6),Productos!Q10+('Insumos y gastos'!$M$15*Productos!N10),IF(AND(O10="SI",P10='Insumos y gastos'!$N$6),Q10+('Insumos y gastos'!$O$15*N10*2),IF(AND(O10="NO",P10='Insumos y gastos'!$N$6),Productos!Q10+('Insumos y gastos'!$O$15*Productos!N10),IF(AND(O10="SI",P10='Insumos y gastos'!$P$6),Q10+('Insumos y gastos'!$Q$15*N10*2),IF(AND(O10="NO",P10='Insumos y gastos'!$P$6),Productos!Q10+('Insumos y gastos'!$Q$15*Productos!N10),IF(AND(O10="SI",P10='Insumos y gastos'!$R$6),Q10+('Insumos y gastos'!$S$15*N10*2),IF(AND(O10="NO",P10='Insumos y gastos'!$R$6),Productos!Q10+('Insumos y gastos'!$S$15*Productos!N10),IF(AND(O10="SI",P10='Insumos y gastos'!$T$6),Q10+('Insumos y gastos'!$U$15*N10*2),IF(AND(O10="NO",P10='Insumos y gastos'!$T$6),Productos!Q10+('Insumos y gastos'!$U$15*Productos!N10),0)))))))))))) -> 0 | T10: =IFERROR(VLOOKUP(S10,Tabla1[[#All],[Nombre insumo]:[Pr. Unidad]],4,0),0) -> 0 | X10: =U10*T10 -> 0 | Y10: =IF(AND(V10="SI",W10='Insumos y gastos'!$J$6),X10+('Insumos y gastos'!$K$15*U10*2),IF(AND(V10="NO",W10='Insumos y gastos'!$J$6),Productos!X10+('Insumos y gastos'!$K$15*Productos!U10),IF(AND(V10="SI",W10='Insumos y gastos'!$L$6),X10+('Insumos y gastos'!$M$15*U10*2),IF(AND(V10="NO",W10='Insumos y gastos'!$L$6),Productos!X10+('Insumos y gastos'!$M$15*Productos!U10),IF(AND(V10="SI",W10='Insumos y gastos'!$N$6),X10+('Insumos y gastos'!$O$15*U10*2),IF(AND(V10="NO",W10='Insumos y gastos'!$N$6),Productos!X10+('Insumos y gastos'!$O$15*Productos!U10),IF(AND(V10="SI",W10='Insumos y gastos'!$P$6),X10+('Insumos y gastos'!$Q$15*U10*2),IF(AND(V10="NO",W10='Insumos y gastos'!$P$6),Productos!X10+('Insumos y gastos'!$Q$15*Productos!U10),IF(AND(V10="SI",W10='Insumos y gastos'!$R$6),X10+('Insumos y gastos'!$S$15*U10*2),IF(AND(V10="NO",W10='Insumos y gastos'!$R$6),Productos!X10+('Insumos y gastos'!$S$15*Productos!U10),IF(AND(V10="SI",W10='Insumos y gastos'!$T$6),X10+('Insumos y gastos'!$U$15*U10*2),IF(AND(V10="NO",W10='Insumos y gastos'!$T$6),Productos!X10+('Insumos y gastos'!$U$15*Productos!U10),0)))))))))))) -> 0 | AA10: =IFERROR(VLOOKUP(Z10,Tabla1[[#All],[Nombre insumo]:[Pr. Unidad]],4,0),0) -> 0 | AE10: =AB10*AA10 -> 0 | AF10: =IF(AND(AC10="SI",AD10='Insumos y gastos'!$J$6),AE10+('Insumos y gastos'!$K$15*AB10*2),IF(AND(AC10="NO",AD10='Insumos y gastos'!$J$6),Productos!AE10+('Insumos y gastos'!$K$15*Productos!AB10),IF(AND(AC10="SI",AD10='Insumos y gastos'!$L$6),AE10+('Insumos y gastos'!$M$15*AB10*2),IF(AND(AC10="NO",AD10='Insumos y gastos'!$L$6),Productos!AE10+('Insumos y gastos'!$M$15*Productos!AB10),IF(AND(AC10="SI",AD10='Insumos y gastos'!$N$6),AE10+('Insumos y gastos'!$O$15*AB10*2),IF(AND(AC10="NO",AD10='Insumos y gastos'!$N$6),Productos!AE10+('Insumos y gastos'!$O$15*Productos!AB10),IF(AND(AC10="SI",AD10='Insumos y gastos'!$P$6),AE10+('Insumos y gastos'!$Q$15*AB10*2),IF(AND(AC10="NO",AD10='Insumos y gastos'!$P$6),Productos!AE10+('Insumos y gastos'!$Q$15*Productos!AB10),IF(AND(AC10="SI",AD10='Insumos y gastos'!$R$6),AE10+('Insumos y gastos'!$S$15*AB10*2),IF(AND(AC10="NO",AD10='Insumos y gastos'!$R$6),Productos!AE10+('Insumos y gastos'!$S$15*Productos!AB10),IF(AND(AC10="SI",AD10='Insumos y gastos'!$T$6),AE10+('Insumos y gastos'!$U$15*AB10*2),IF(AND(AC10="NO",AD10='Insumos y gastos'!$T$6),Productos!AE10+('Insumos y gastos'!$U$15*Productos!AB10),0)))))))))))) -> 0 | AH10: =IFERROR(VLOOKUP(AG10,Tabla1[[#All],[Nombre insumo]:[Pr. Unidad]],4,0),0) -> 0 | AL10: =AI10*AH10 -> 0 | AM10: =IF(AND(AJ10="SI",AK10='Insumos y gastos'!$J$6),AL10+('Insumos y gastos'!$K$15*AI10*2),IF(AND(AJ10="NO",AK10='Insumos y gastos'!$J$6),Productos!AL10+('Insumos y gastos'!$K$15*Productos!AI10),IF(AND(AJ10="SI",AK10='Insumos y gastos'!$L$6),AL10+('Insumos y gastos'!$M$15*AI10*2),IF(AND(AJ10="NO",AK10='Insumos y gastos'!$L$6),Productos!AL10+('Insumos y gastos'!$M$15*Productos!AI10),IF(AND(AJ10="SI",AK10='Insumos y gastos'!$N$6),AL10+('Insumos y gastos'!$O$15*AI10*2),IF(AND(AJ10="NO",AK10='Insumos y gastos'!$N$6),Productos!AL10+('Insumos y gastos'!$O$15*Productos!AI10),IF(AND(AJ10="SI",AK10='Insumos y gastos'!$P$6),AL10+('Insumos y gastos'!$Q$15*AI10*2),IF(AND(AJ10="NO",AK10='Insumos y gastos'!$P$6),Productos!AL10+('Insumos y gastos'!$Q$15*Productos!AI10),IF(AND(AJ10="SI",AK10='Insumos y gastos'!$R$6),AL10+('Insumos y gastos'!$S$15*AI10*2),IF(AND(AJ10="NO",AK10='Insumos y gastos'!$R$6),Productos!AL10+('Insumos y gastos'!$S$15*Productos!AI10),IF(AND(AJ10="SI",AK10='Insumos y gastos'!$T$6),AL10+('Insumos y gastos'!$U$15*AI10*2),IF(AND(AJ10="NO",AK10='Insumos y gastos'!$T$6),Productos!AL10+('Insumos y gastos'!$U$15*Productos!AI10),0)))))))))))) -> 0 | AO10: =IFERROR(VLOOKUP(AN10,Tabla1[[#All],[Nombre insumo]:[Pr. Unidad]],4,0),0) -> 0 | AQ10: =IF(Tabla3[[#This Row],[Costo insumo 1]]>0,Tabla3[[#This Row],[Cantidad insumo 1]]*Tabla3[[#This Row],[Costo insumo 1]],0) -> 0 | AS10: =IFERROR(VLOOKUP(AR10,Tabla1[[#All],[Nombre insumo]:[Pr. Unidad]],4,0),0) -> 0 | AU10: =IF(Tabla3[[#This Row],[Costo insumo 2]]>0,Tabla3[[#This Row],[Cantidad insumo 2]]*Tabla3[[#This Row],[Costo insumo 2]],0) -> 0 | AW10: =IFERROR(VLOOKUP(AV10,Tabla1[[#All],[Nombre insumo]:[Pr. Unidad]],4,0),0) -> 0 | AY10: =IF(Tabla3[[#This Row],[Costo insumo 3]]>0,Tabla3[[#This Row],[Cantidad insumo 3]]*Tabla3[[#This Row],[Costo insumo 3]],0) -> 0 | BA10: =IFERROR(VLOOKUP(AZ10,Tabla1[[#All],[Nombre insumo]:[Pr. Unidad]],4,0),0) -> 0 | BC10: =IF(Tabla3[[#This Row],[Costo insumo 4]]>0,Tabla3[[#This Row],[Cantidad insumo 4]]*Tabla3[[#This Row],[Costo insumo 4]],0) -> 0 | BE10: =IFERROR(VLOOKUP(BD10,Tabla1[[#All],[Nombre insumo]:[Pr. Unidad]],4,0),0) -> 0 | BG10: =IF(Tabla3[[#This Row],[Costo insumo 5]]>0,Tabla3[[#This Row],[Cantidad insumo 5]]*Tabla3[[#This Row],[Costo insumo 5]],0) -> 0 | BH10: =Tabla3[[#This Row],[Subtotal impresión 1]]+Tabla3[[#This Row],[Subtotal impresión 2]]+Tabla3[[#This Row],[Subtotal impresión 3]]+Tabla3[[#This Row],[Subtotal impresión 4]]+Tabla3[[#This Row],[Subtotal impresión 5]]+Tabla3[[#This Row],[Subtotal insumos 1]]+Tabla3[[#This Row],[Subtotal insumos 2]]+Tabla3[[#This Row],[Subtotal insumos 3]]+Tabla3[[#This Row],[Subtotal insumos 4]]+Tabla3[[#This Row],[Subtotal insumos 5]] -> 0 | BJ10: =BI10*'Insumos y gastos'!$M$50 -> 0 | BK10: =BI10*'Insumos y gastos'!$Q$24 -> 0 | BL10: =Tabla3[[#This Row],[Costo sin servicios]]+Tabla3[[#This Row],[Costo servicios]]+Tabla3[[#This Row],[Costo mano de obra]] -> 0
A11: 10009 | F11: =IFERROR(VLOOKUP(E11,Tabla1[[#All],[Nombre insumo]:[Pr. Unidad]],4,0),0) -> 0 | J11: =G11*F11 -> 0 | K11: =IF(AND(H11="SI",I11='Insumos y gastos'!$J$6),J11+('Insumos y gastos'!$K$15*G11*2),IF(AND(H11="NO",I11='Insumos y gastos'!$J$6),Productos!J11+('Insumos y gastos'!$K$15*Productos!G11),IF(AND(H11="SI",I11='Insumos y gastos'!$L$6),J11+('Insumos y gastos'!$M$15*G11*2),IF(AND(H11="NO",I11='Insumos y gastos'!$L$6),Productos!J11+('Insumos y gastos'!$M$15*Productos!G11),IF(AND(H11="SI",I11='Insumos y gastos'!$N$6),J11+('Insumos y gastos'!$O$15*G11*2),IF(AND(H11="NO",I11='Insumos y gastos'!$N$6),Productos!J11+('Insumos y gastos'!$O$15*Productos!G11),IF(AND(H11="SI",I11='Insumos y gastos'!$P$6),J11+('Insumos y gastos'!$Q$15*G11*2),IF(AND(H11="NO",I11='Insumos y gastos'!$P$6),Productos!J11+('Insumos y gastos'!$Q$15*Productos!G11),IF(AND(H11="SI",I11='Insumos y gastos'!$R$6),J11+('Insumos y gastos'!$S$15*G11*2),IF(AND(H11="NO",I11='Insumos y gastos'!$R$6),Productos!J11+('Insumos y gastos'!$S$15*Productos!G11),IF(AND(H11="SI",I11='Insumos y gastos'!$T$6),J11+('Insumos y gastos'!$U$15*G11*2),IF(AND(H11="NO",I11='Insumos y gastos'!$T$6),Productos!J11+('Insumos y gastos'!$U$15*Productos!G11),0)))))))))))) -> 0 | M11: =IFERROR(VLOOKUP(L11,Tabla1[[#All],[Nombre insumo]:[Pr. Unidad]],4,0),0) -> 0 | Q11: =N11*M11 -> 0 | R11: =IF(AND(O11="SI",P11='Insumos y gastos'!$J$6),Q11+('Insumos y gastos'!$K$15*N11*2),IF(AND(O11="NO",P11='Insumos y gastos'!$J$6),Productos!Q11+('Insumos y gastos'!$K$15*Productos!N11),IF(AND(O11="SI",P11='Insumos y gastos'!$L$6),Q11+('Insumos y gastos'!$M$15*N11*2),IF(AND(O11="NO",P11='Insumos y gastos'!$L$6),Productos!Q11+('Insumos y gastos'!$M$15*Productos!N11),IF(AND(O11="SI",P11='Insumos y gastos'!$N$6),Q11+('Insumos y gastos'!$O$15*N11*2),IF(AND(O11="NO",P11='Insumos y gastos'!$N$6),Productos!Q11+('Insumos y gastos'!$O$15*Productos!N11),IF(AND(O11="SI",P11='Insumos y gastos'!$P$6),Q11+('Insumos y gastos'!$Q$15*N11*2),IF(AND(O11="NO",P11='Insumos y gastos'!$P$6),Productos!Q11+('Insumos y gastos'!$Q$15*Productos!N11),IF(AND(O11="SI",P11='Insumos y gastos'!$R$6),Q11+('Insumos y gastos'!$S$15*N11*2),IF(AND(O11="NO",P11='Insumos y gastos'!$R$6),Productos!Q11+('Insumos y gastos'!$S$15*Productos!N11),IF(AND(O11="SI",P11='Insumos y gastos'!$T$6),Q11+('Insumos y gastos'!$U$15*N11*2),IF(AND(O11="NO",P11='Insumos y gastos'!$T$6),Productos!Q11+('Insumos y gastos'!$U$15*Productos!N11),0)))))))))))) -> 0 | T11: =IFERROR(VLOOKUP(S11,Tabla1[[#All],[Nombre insumo]:[Pr. Unidad]],4,0),0) -> 0 | X11: =U11*T11 -> 0 | Y11: =IF(AND(V11="SI",W11='Insumos y gastos'!$J$6),X11+('Insumos y gastos'!$K$15*U11*2),IF(AND(V11="NO",W11='Insumos y gastos'!$J$6),Productos!X11+('Insumos y gastos'!$K$15*Productos!U11),IF(AND(V11="SI",W11='Insumos y gastos'!$L$6),X11+('Insumos y gastos'!$M$15*U11*2),IF(AND(V11="NO",W11='Insumos y gastos'!$L$6),Productos!X11+('Insumos y gastos'!$M$15*Productos!U11),IF(AND(V11="SI",W11='Insumos y gastos'!$N$6),X11+('Insumos y gastos'!$O$15*U11*2),IF(AND(V11="NO",W11='Insumos y gastos'!$N$6),Productos!X11+('Insumos y gastos'!$O$15*Productos!U11),IF(AND(V11="SI",W11='Insumos y gastos'!$P$6),X11+('Insumos y gastos'!$Q$15*U11*2),IF(AND(V11="NO",W11='Insumos y gastos'!$P$6),Productos!X11+('Insumos y gastos'!$Q$15*Productos!U11),IF(AND(V11="SI",W11='Insumos y gastos'!$R$6),X11+('Insumos y gastos'!$S$15*U11*2),IF(AND(V11="NO",W11='Insumos y gastos'!$R$6),Productos!X11+('Insumos y gastos'!$S$15*Productos!U11),IF(AND(V11="SI",W11='Insumos y gastos'!$T$6),X11+('Insumos y gastos'!$U$15*U11*2),IF(AND(V11="NO",W11='Insumos y gastos'!$T$6),Productos!X11+('Insumos y gastos'!$U$15*Productos!U11),0)))))))))))) -> 0 | AA11: =IFERROR(VLOOKUP(Z11,Tabla1[[#All],[Nombre insumo]:[Pr. Unidad]],4,0),0) -> 0 | AE11: =AB11*AA11 -> 0 | AF11: =IF(AND(AC11="SI",AD11='Insumos y gastos'!$J$6),AE11+('Insumos y gastos'!$K$15*AB11*2),IF(AND(AC11="NO",AD11='Insumos y gastos'!$J$6),Productos!AE11+('Insumos y gastos'!$K$15*Productos!AB11),IF(AND(AC11="SI",AD11='Insumos y gastos'!$L$6),AE11+('Insumos y gastos'!$M$15*AB11*2),IF(AND(AC11="NO",AD11='Insumos y gastos'!$L$6),Productos!AE11+('Insumos y gastos'!$M$15*Productos!AB11),IF(AND(AC11="SI",AD11='Insumos y gastos'!$N$6),AE11+('Insumos y gastos'!$O$15*AB11*2),IF(AND(AC11="NO",AD11='Insumos y gastos'!$N$6),Productos!AE11+('Insumos y gastos'!$O$15*Productos!AB11),IF(AND(AC11="SI",AD11='Insumos y gastos'!$P$6),AE11+('Insumos y gastos'!$Q$15*AB11*2),IF(AND(AC11="NO",AD11='Insumos y gastos'!$P$6),Productos!AE11+('Insumos y gastos'!$Q$15*Productos!AB11),IF(AND(AC11="SI",AD11='Insumos y gastos'!$R$6),AE11+('Insumos y gastos'!$S$15*AB11*2),IF(AND(AC11="NO",AD11='Insumos y gastos'!$R$6),Productos!AE11+('Insumos y gastos'!$S$15*Productos!AB11),IF(AND(AC11="SI",AD11='Insumos y gastos'!$T$6),AE11+('Insumos y gastos'!$U$15*AB11*2),IF(AND(AC11="NO",AD11='Insumos y gastos'!$T$6),Productos!AE11+('Insumos y gastos'!$U$15*Productos!AB11),0)))))))))))) -> 0 | AH11: =IFERROR(VLOOKUP(AG11,Tabla1[[#All],[Nombre insumo]:[Pr. Unidad]],4,0),0) -> 0 | AL11: =AI11*AH11 -> 0 | AM11: =IF(AND(AJ11="SI",AK11='Insumos y gastos'!$J$6),AL11+('Insumos y gastos'!$K$15*AI11*2),IF(AND(AJ11="NO",AK11='Insumos y gastos'!$J$6),Productos!AL11+('Insumos y gastos'!$K$15*Productos!AI11),IF(AND(AJ11="SI",AK11='Insumos y gastos'!$L$6),AL11+('Insumos y gastos'!$M$15*AI11*2),IF(AND(AJ11="NO",AK11='Insumos y gastos'!$L$6),Productos!AL11+('Insumos y gastos'!$M$15*Productos!AI11),IF(AND(AJ11="SI",AK11='Insumos y gastos'!$N$6),AL11+('Insumos y gastos'!$O$15*AI11*2),IF(AND(AJ11="NO",AK11='Insumos y gastos'!$N$6),Productos!AL11+('Insumos y gastos'!$O$15*Productos!AI11),IF(AND(AJ11="SI",AK11='Insumos y gastos'!$P$6),AL11+('Insumos y gastos'!$Q$15*AI11*2),IF(AND(AJ11="NO",AK11='Insumos y gastos'!$P$6),Productos!AL11+('Insumos y gastos'!$Q$15*Productos!AI11),IF(AND(AJ11="SI",AK11='Insumos y gastos'!$R$6),AL11+('Insumos y gastos'!$S$15*AI11*2),IF(AND(AJ11="NO",AK11='Insumos y gastos'!$R$6),Productos!AL11+('Insumos y gastos'!$S$15*Productos!AI11),IF(AND(AJ11="SI",AK11='Insumos y gastos'!$T$6),AL11+('Insumos y gastos'!$U$15*AI11*2),IF(AND(AJ11="NO",AK11='Insumos y gastos'!$T$6),Productos!AL11+('Insumos y gastos'!$U$15*Productos!AI11),0)))))))))))) -> 0 | AO11: =IFERROR(VLOOKUP(AN11,Tabla1[[#All],[Nombre insumo]:[Pr. Unidad]],4,0),0) -> 0 | AQ11: =IF(Tabla3[[#This Row],[Costo insumo 1]]>0,Tabla3[[#This Row],[Cantidad insumo 1]]*Tabla3[[#This Row],[Costo insumo 1]],0) -> 0 | AS11: =IFERROR(VLOOKUP(AR11,Tabla1[[#All],[Nombre insumo]:[Pr. Unidad]],4,0),0) -> 0 | AU11: =IF(Tabla3[[#This Row],[Costo insumo 2]]>0,Tabla3[[#This Row],[Cantidad insumo 2]]*Tabla3[[#This Row],[Costo insumo 2]],0) -> 0 | AW11: =IFERROR(VLOOKUP(AV11,Tabla1[[#All],[Nombre insumo]:[Pr. Unidad]],4,0),0) -> 0 | AY11: =IF(Tabla3[[#This Row],[Costo insumo 3]]>0,Tabla3[[#This Row],[Cantidad insumo 3]]*Tabla3[[#This Row],[Costo insumo 3]],0) -> 0 | BA11: =IFERROR(VLOOKUP(AZ11,Tabla1[[#All],[Nombre insumo]:[Pr. Unidad]],4,0),0) -> 0 | BC11: =IF(Tabla3[[#This Row],[Costo insumo 4]]>0,Tabla3[[#This Row],[Cantidad insumo 4]]*Tabla3[[#This Row],[Costo insumo 4]],0) -> 0 | BE11: =IFERROR(VLOOKUP(BD11,Tabla1[[#All],[Nombre insumo]:[Pr. Unidad]],4,0),0) -> 0 | BG11: =IF(Tabla3[[#This Row],[Costo insumo 5]]>0,Tabla3[[#This Row],[Cantidad insumo 5]]*Tabla3[[#This Row],[Costo insumo 5]],0) -> 0 | BH11: =Tabla3[[#This Row],[Subtotal impresión 1]]+Tabla3[[#This Row],[Subtotal impresión 2]]+Tabla3[[#This Row],[Subtotal impresión 3]]+Tabla3[[#This Row],[Subtotal impresión 4]]+Tabla3[[#This Row],[Subtotal impresión 5]]+Tabla3[[#This Row],[Subtotal insumos 1]]+Tabla3[[#This Row],[Subtotal insumos 2]]+Tabla3[[#This Row],[Subtotal insumos 3]]+Tabla3[[#This Row],[Subtotal insumos 4]]+Tabla3[[#This Row],[Subtotal insumos 5]] -> 0 | BJ11: =BI11*'Insumos y gastos'!$M$50 -> 0 | BK11: =BI11*'Insumos y gastos'!$Q$24 -> 0 | BL11: =Tabla3[[#This Row],[Costo sin servicios]]+Tabla3[[#This Row],[Costo servicios]]+Tabla3[[#This Row],[Costo mano de obra]] -> 0
A12: 10010 | F12: =IFERROR(VLOOKUP(E12,Tabla1[[#All],[Nombre insumo]:[Pr. Unidad]],4,0),0) -> 0 | J12: =G12*F12 -> 0 | K12: =IF(AND(H12="SI",I12='Insumos y gastos'!$J$6),J12+('Insumos y gastos'!$K$15*G12*2),IF(AND(H12="NO",I12='Insumos y gastos'!$J$6),Productos!J12+('Insumos y gastos'!$K$15*Productos!G12),IF(AND(H12="SI",I12='Insumos y gastos'!$L$6),J12+('Insumos y gastos'!$M$15*G12*2),IF(AND(H12="NO",I12='Insumos y gastos'!$L$6),Productos!J12+('Insumos y gastos'!$M$15*Productos!G12),IF(AND(H12="SI",I12='Insumos y gastos'!$N$6),J12+('Insumos y gastos'!$O$15*G12*2),IF(AND(H12="NO",I12='Insumos y gastos'!$N$6),Productos!J12+('Insumos y gastos'!$O$15*Productos!G12),IF(AND(H12="SI",I12='Insumos y gastos'!$P$6),J12+('Insumos y gastos'!$Q$15*G12*2),IF(AND(H12="NO",I12='Insumos y gastos'!$P$6),Productos!J12+('Insumos y gastos'!$Q$15*Productos!G12),IF(AND(H12="SI",I12='Insumos y gastos'!$R$6),J12+('Insumos y gastos'!$S$15*G12*2),IF(AND(H12="NO",I12='Insumos y gastos'!$R$6),Productos!J12+('Insumos y gastos'!$S$15*Productos!G12),IF(AND(H12="SI",I12='Insumos y gastos'!$T$6),J12+('Insumos y gastos'!$U$15*G12*2),IF(AND(H12="NO",I12='Insumos y gastos'!$T$6),Productos!J12+('Insumos y gastos'!$U$15*Productos!G12),0)))))))))))) -> 0 | M12: =IFERROR(VLOOKUP(L12,Tabla1[[#All],[Nombre insumo]:[Pr. Unidad]],4,0),0) -> 0 | Q12: =N12*M12 -> 0 | R12: =IF(AND(O12="SI",P12='Insumos y gastos'!$J$6),Q12+('Insumos y gastos'!$K$15*N12*2),IF(AND(O12="NO",P12='Insumos y gastos'!$J$6),Productos!Q12+('Insumos y gastos'!$K$15*Productos!N12),IF(AND(O12="SI",P12='Insumos y gastos'!$L$6),Q12+('Insumos y gastos'!$M$15*N12*2),IF(AND(O12="NO",P12='Insumos y gastos'!$L$6),Productos!Q12+('Insumos y gastos'!$M$15*Productos!N12),IF(AND(O12="SI",P12='Insumos y gastos'!$N$6),Q12+('Insumos y gastos'!$O$15*N12*2),IF(AND(O12="NO",P12='Insumos y gastos'!$N$6),Productos!Q12+('Insumos y gastos'!$O$15*Productos!N12),IF(AND(O12="SI",P12='Insumos y gastos'!$P$6),Q12+('Insumos y gastos'!$Q$15*N12*2),IF(AND(O12="NO",P12='Insumos y gastos'!$P$6),Productos!Q12+('Insumos y gastos'!$Q$15*Productos!N12),IF(AND(O12="SI",P12='Insumos y gastos'!$R$6),Q12+('Insumos y gastos'!$S$15*N12*2),IF(AND(O12="NO",P12='Insumos y gastos'!$R$6),Productos!Q12+('Insumos y gastos'!$S$15*Productos!N12),IF(AND(O12="SI",P12='Insumos y gastos'!$T$6),Q12+('Insumos y gastos'!$U$15*N12*2),IF(AND(O12="NO",P12='Insumos y gastos'!$T$6),Productos!Q12+('Insumos y gastos'!$U$15*Productos!N12),0)))))))))))) -> 0 | T12: =IFERROR(VLOOKUP(S12,Tabla1[[#All],[Nombre insumo]:[Pr. Unidad]],4,0),0) -> 0 | X12: =U12*T12 -> 0 | Y12: =IF(AND(V12="SI",W12='Insumos y gastos'!$J$6),X12+('Insumos y gastos'!$K$15*U12*2),IF(AND(V12="NO",W12='Insumos y gastos'!$J$6),Productos!X12+('Insumos y gastos'!$K$15*Productos!U12),IF(AND(V12="SI",W12='Insumos y gastos'!$L$6),X12+('Insumos y gastos'!$M$15*U12*2),IF(AND(V12="NO",W12='Insumos y gastos'!$L$6),Productos!X12+('Insumos y gastos'!$M$15*Productos!U12),IF(AND(V12="SI",W12='Insumos y gastos'!$N$6),X12+('Insumos y gastos'!$O$15*U12*2),IF(AND(V12="NO",W12='Insumos y gastos'!$N$6),Productos!X12+('Insumos y gastos'!$O$15*Productos!U12),IF(AND(V12="SI",W12='Insumos y gastos'!$P$6),X12+('Insumos y gastos'!$Q$15*U12*2),IF(AND(V12="NO",W12='Insumos y gastos'!$P$6),Productos!X12+('Insumos y gastos'!$Q$15*Productos!U12),IF(AND(V12="SI",W12='Insumos y gastos'!$R$6),X12+('Insumos y gastos'!$S$15*U12*2),IF(AND(V12="NO",W12='Insumos y gastos'!$R$6),Productos!X12+('Insumos y gastos'!$S$15*Productos!U12),IF(AND(V12="SI",W12='Insumos y gastos'!$T$6),X12+('Insumos y gastos'!$U$15*U12*2),IF(AND(V12="NO",W12='Insumos y gastos'!$T$6),Productos!X12+('Insumos y gastos'!$U$15*Productos!U12),0)))))))))))) -> 0 | AA12: =IFERROR(VLOOKUP(Z12,Tabla1[[#All],[Nombre insumo]:[Pr. Unidad]],4,0),0) -> 0 | AE12: =AB12*AA12 -> 0 | AF12: =IF(AND(AC12="SI",AD12='Insumos y gastos'!$J$6),AE12+('Insumos y gastos'!$K$15*AB12*2),IF(AND(AC12="NO",AD12='Insumos y gastos'!$J$6),Productos!AE12+('Insumos y gastos'!$K$15*Productos!AB12),IF(AND(AC12="SI",AD12='Insumos y gastos'!$L$6),AE12+('Insumos y gastos'!$M$15*AB12*2),IF(AND(AC12="NO",AD12='Insumos y gastos'!$L$6),Productos!AE12+('Insumos y gastos'!$M$15*Productos!AB12),IF(AND(AC12="SI",AD12='Insumos y gastos'!$N$6),AE12+('Insumos y gastos'!$O$15*AB12*2),IF(AND(AC12="NO",AD12='Insumos y gastos'!$N$6),Productos!AE12+('Insumos y gastos'!$O$15*Productos!AB12),IF(AND(AC12="SI",AD12='Insumos y gastos'!$P$6),AE12+('Insumos y gastos'!$Q$15*AB12*2),IF(AND(AC12="NO",AD12='Insumos y gastos'!$P$6),Productos!AE12+('Insumos y gastos'!$Q$15*Productos!AB12),IF(AND(AC12="SI",AD12='Insumos y gastos'!$R$6),AE12+('Insumos y gastos'!$S$15*AB12*2),IF(AND(AC12="NO",AD12='Insumos y gastos'!$R$6),Productos!AE12+('Insumos y gastos'!$S$15*Productos!AB12),IF(AND(AC12="SI",AD12='Insumos y gastos'!$T$6),AE12+('Insumos y gastos'!$U$15*AB12*2),IF(AND(AC12="NO",AD12='Insumos y gastos'!$T$6),Productos!AE12+('Insumos y gastos'!$U$15*Productos!AB12),0)))))))))))) -> 0 | AH12: =IFERROR(VLOOKUP(AG12,Tabla1[[#All],[Nombre insumo]:[Pr. Unidad]],4,0),0) -> 0 | AL12: =AI12*AH12 -> 0 | AM12: =IF(AND(AJ12="SI",AK12='Insumos y gastos'!$J$6),AL12+('Insumos y gastos'!$K$15*AI12*2),IF(AND(AJ12="NO",AK12='Insumos y gastos'!$J$6),Productos!AL12+('Insumos y gastos'!$K$15*Productos!AI12),IF(AND(AJ12="SI",AK12='Insumos y gastos'!$L$6),AL12+('Insumos y gastos'!$M$15*AI12*2),IF(AND(AJ12="NO",AK12='Insumos y gastos'!$L$6),Productos!AL12+('Insumos y gastos'!$M$15*Productos!AI12),IF(AND(AJ12="SI",AK12='Insumos y gastos'!$N$6),AL12+('Insumos y gastos'!$O$15*AI12*2),IF(AND(AJ12="NO",AK12='Insumos y gastos'!$N$6),Productos!AL12+('Insumos y gastos'!$O$15*Productos!AI12),IF(AND(AJ12="SI",AK12='Insumos y gastos'!$P$6),AL12+('Insumos y gastos'!$Q$15*AI12*2),IF(AND(AJ12="NO",AK12='Insumos y gastos'!$P$6),Productos!AL12+('Insumos y gastos'!$Q$15*Productos!AI12),IF(AND(AJ12="SI",AK12='Insumos y gastos'!$R$6),AL12+('Insumos y gastos'!$S$15*AI12*2),IF(AND(AJ12="NO",AK12='Insumos y gastos'!$R$6),Productos!AL12+('Insumos y gastos'!$S$15*Productos!AI12),IF(AND(AJ12="SI",AK12='Insumos y gastos'!$T$6),AL12+('Insumos y gastos'!$U$15*AI12*2),IF(AND(AJ12="NO",AK12='Insumos y gastos'!$T$6),Productos!AL12+('Insumos y gastos'!$U$15*Productos!AI12),0)))))))))))) -> 0 | AO12: =IFERROR(VLOOKUP(AN12,Tabla1[[#All],[Nombre insumo]:[Pr. Unidad]],4,0),0) -> 0 | AQ12: =IF(Tabla3[[#This Row],[Costo insumo 1]]>0,Tabla3[[#This Row],[Cantidad insumo 1]]*Tabla3[[#This Row],[Costo insumo 1]],0) -> 0 | AS12: =IFERROR(VLOOKUP(AR12,Tabla1[[#All],[Nombre insumo]:[Pr. Unidad]],4,0),0) -> 0 | AU12: =IF(Tabla3[[#This Row],[Costo insumo 2]]>0,Tabla3[[#This Row],[Cantidad insumo 2]]*Tabla3[[#This Row],[Costo insumo 2]],0) -> 0 | AW12: =IFERROR(VLOOKUP(AV12,Tabla1[[#All],[Nombre insumo]:[Pr. Unidad]],4,0),0) -> 0 | AY12: =IF(Tabla3[[#This Row],[Costo insumo 3]]>0,Tabla3[[#This Row],[Cantidad insumo 3]]*Tabla3[[#This Row],[Costo insumo 3]],0) -> 0 | BA12: =IFERROR(VLOOKUP(AZ12,Tabla1[[#All],[Nombre insumo]:[Pr. Unidad]],4,0),0) -> 0 | BC12: =IF(Tabla3[[#This Row],[Costo insumo 4]]>0,Tabla3[[#This Row],[Cantidad insumo 4]]*Tabla3[[#This Row],[Costo insumo 4]],0) -> 0 | BE12: =IFERROR(VLOOKUP(BD12,Tabla1[[#All],[Nombre insumo]:[Pr. Unidad]],4,0),0) -> 0 | BG12: =IF(Tabla3[[#This Row],[Costo insumo 5]]>0,Tabla3[[#This Row],[Cantidad insumo 5]]*Tabla3[[#This Row],[Costo insumo 5]],0) -> 0 | BH12: =Tabla3[[#This Row],[Subtotal impresión 1]]+Tabla3[[#This Row],[Subtotal impresión 2]]+Tabla3[[#This Row],[Subtotal impresión 3]]+Tabla3[[#This Row],[Subtotal impresión 4]]+Tabla3[[#This Row],[Subtotal impresión 5]]+Tabla3[[#This Row],[Subtotal insumos 1]]+Tabla3[[#This Row],[Subtotal insumos 2]]+Tabla3[[#This Row],[Subtotal insumos 3]]+Tabla3[[#This Row],[Subtotal insumos 4]]+Tabla3[[#This Row],[Subtotal insumos 5]] -> 0 | BJ12: =BI12*'Insumos y gastos'!$M$50 -> 0 | BK12: =BI12*'Insumos y gastos'!$Q$24 -> 0 | BL12: =Tabla3[[#This Row],[Costo sin servicios]]+Tabla3[[#This Row],[Costo servicios]]+Tabla3[[#This Row],[Costo mano de obra]] -> 0
A13: 10011 | F13: =IFERROR(VLOOKUP(E13,Tabla1[[#All],[Nombre insumo]:[Pr. Unidad]],4,0),0) -> 0 | J13: =G13*F13 -> 0 | K13: =IF(AND(H13="SI",I13='Insumos y gastos'!$J$6),J13+('Insumos y gastos'!$K$15*G13*2),IF(AND(H13="NO",I13='Insumos y gastos'!$J$6),Productos!J13+('Insumos y gastos'!$K$15*Productos!G13),IF(AND(H13="SI",I13='Insumos y gastos'!$L$6),J13+('Insumos y gastos'!$M$15*G13*2),IF(AND(H13="NO",I13='Insumos y gastos'!$L$6),Productos!J13+('Insumos y gastos'!$M$15*Productos!G13),IF(AND(H13="SI",I13='Insumos y gastos'!$N$6),J13+('Insumos y gastos'!$O$15*G13*2),IF(AND(H13="NO",I13='Insumos y gastos'!$N$6),Productos!J13+('Insumos y gastos'!$O$15*Productos!G13),IF(AND(H13="SI",I13='Insumos y gastos'!$P$6),J13+('Insumos y gastos'!$Q$15*G13*2),IF(AND(H13="NO",I13='Insumos y gastos'!$P$6),Productos!J13+('Insumos y gastos'!$Q$15*Productos!G13),IF(AND(H13="SI",I13='Insumos y gastos'!$R$6),J13+('Insumos y gastos'!$S$15*G13*2),IF(AND(H13="NO",I13='Insumos y gastos'!$R$6),Productos!J13+('Insumos y gastos'!$S$15*Productos!G13),IF(AND(H13="SI",I13='Insumos y gastos'!$T$6),J13+('Insumos y gastos'!$U$15*G13*2),IF(AND(H13="NO",I13='Insumos y gastos'!$T$6),Productos!J13+('Insumos y gastos'!$U$15*Productos!G13),0)))))))))))) -> 0 | M13: =IFERROR(VLOOKUP(L13,Tabla1[[#All],[Nombre insumo]:[Pr. Unidad]],4,0),0) -> 0 | Q13: =N13*M13 -> 0 | R13: =IF(AND(O13="SI",P13='Insumos y gastos'!$J$6),Q13+('Insumos y gastos'!$K$15*N13*2),IF(AND(O13="NO",P13='Insumos y gastos'!$J$6),Productos!Q13+('Insumos y gastos'!$K$15*Productos!N13),IF(AND(O13="SI",P13='Insumos y gastos'!$L$6),Q13+('Insumos y gastos'!$M$15*N13*2),IF(AND(O13="NO",P13='Insumos y gastos'!$L$6),Productos!Q13+('Insumos y gastos'!$M$15*Productos!N13),IF(AND(O13="SI",P13='Insumos y gastos'!$N$6),Q13+('Insumos y gastos'!$O$15*N13*2),IF(AND(O13="NO",P13='Insumos y gastos'!$N$6),Productos!Q13+('Insumos y gastos'!$O$15*Productos!N13),IF(AND(O13="SI",P13='Insumos y gastos'!$P$6),Q13+('Insumos y gastos'!$Q$15*N13*2),IF(AND(O13="NO",P13='Insumos y gastos'!$P$6),Productos!Q13+('Insumos y gastos'!$Q$15*Productos!N13),IF(AND(O13="SI",P13='Insumos y gastos'!$R$6),Q13+('Insumos y gastos'!$S$15*N13*2),IF(AND(O13="NO",P13='Insumos y gastos'!$R$6),Productos!Q13+('Insumos y gastos'!$S$15*Productos!N13),IF(AND(O13="SI",P13='Insumos y gastos'!$T$6),Q13+('Insumos y gastos'!$U$15*N13*2),IF(AND(O13="NO",P13='Insumos y gastos'!$T$6),Productos!Q13+('Insumos y gastos'!$U$15*Productos!N13),0)))))))))))) -> 0 | T13: =IFERROR(VLOOKUP(S13,Tabla1[[#All],[Nombre insumo]:[Pr. Unidad]],4,0),0) -> 0 | X13: =U13*T13 -> 0 | Y13: =IF(AND(V13="SI",W13='Insumos y gastos'!$J$6),X13+('Insumos y gastos'!$K$15*U13*2),IF(AND(V13="NO",W13='Insumos y gastos'!$J$6),Productos!X13+('Insumos y gastos'!$K$15*Productos!U13),IF(AND(V13="SI",W13='Insumos y gastos'!$L$6),X13+('Insumos y gastos'!$M$15*U13*2),IF(AND(V13="NO",W13='Insumos y gastos'!$L$6),Productos!X13+('Insumos y gastos'!$M$15*Productos!U13),IF(AND(V13="SI",W13='Insumos y gastos'!$N$6),X13+('Insumos y gastos'!$O$15*U13*2),IF(AND(V13="NO",W13='Insumos y gastos'!$N$6),Productos!X13+('Insumos y gastos'!$O$15*Productos!U13),IF(AND(V13="SI",W13='Insumos y gastos'!$P$6),X13+('Insumos y gastos'!$Q$15*U13*2),IF(AND(V13="NO",W13='Insumos y gastos'!$P$6),Productos!X13+('Insumos y gastos'!$Q$15*Productos!U13),IF(AND(V13="SI",W13='Insumos y gastos'!$R$6),X13+('Insumos y gastos'!$S$15*U13*2),IF(AND(V13="NO",W13='Insumos y gastos'!$R$6),Productos!X13+('Insumos y gastos'!$S$15*Productos!U13),IF(AND(V13="SI",W13='Insumos y gastos'!$T$6),X13+('Insumos y gastos'!$U$15*U13*2),IF(AND(V13="NO",W13='Insumos y gastos'!$T$6),Productos!X13+('Insumos y gastos'!$U$15*Productos!U13),0)))))))))))) -> 0 | AA13: =IFERROR(VLOOKUP(Z13,Tabla1[[#All],[Nombre insumo]:[Pr. Unidad]],4,0),0) -> 0 | AE13: =AB13*AA13 -> 0 | AF13: =IF(AND(AC13="SI",AD13='Insumos y gastos'!$J$6),AE13+('Insumos y gastos'!$K$15*AB13*2),IF(AND(AC13="NO",AD13='Insumos y gastos'!$J$6),Productos!AE13+('Insumos y gastos'!$K$15*Productos!AB13),IF(AND(AC13="SI",AD13='Insumos y gastos'!$L$6),AE13+('Insumos y gastos'!$M$15*AB13*2),IF(AND(AC13="NO",AD13='Insumos y gastos'!$L$6),Productos!AE13+('Insumos y gastos'!$M$15*Productos!AB13),IF(AND(AC13="SI",AD13='Insumos y gastos'!$N$6),AE13+('Insumos y gastos'!$O$15*AB13*2),IF(AND(AC13="NO",AD13='Insumos y gastos'!$N$6),Productos!AE13+('Insumos y gastos'!$O$15*Productos!AB13),IF(AND(AC13="SI",AD13='Insumos y gastos'!$P$6),AE13+('Insumos y gastos'!$Q$15*AB13*2),IF(AND(AC13="NO",AD13='Insumos y gastos'!$P$6),Productos!AE13+('Insumos y gastos'!$Q$15*Productos!AB13),IF(AND(AC13="SI",AD13='Insumos y gastos'!$R$6),AE13+('Insumos y gastos'!$S$15*AB13*2),IF(AND(AC13="NO",AD13='Insumos y gastos'!$R$6),Productos!AE13+('Insumos y gastos'!$S$15*Productos!AB13),IF(AND(AC13="SI",AD13='Insumos y gastos'!$T$6),AE13+('Insumos y gastos'!$U$15*AB13*2),IF(AND(AC13="NO",AD13='Insumos y gastos'!$T$6),Productos!AE13+('Insumos y gastos'!$U$15*Productos!AB13),0)))))))))))) -> 0 | AH13: =IFERROR(VLOOKUP(AG13,Tabla1[[#All],[Nombre insumo]:[Pr. Unidad]],4,0),0) -> 0 | AL13: =AI13*AH13 -> 0 | AM13: =IF(AND(AJ13="SI",AK13='Insumos y gastos'!$J$6),AL13+('Insumos y gastos'!$K$15*AI13*2),IF(AND(AJ13="NO",AK13='Insumos y gastos'!$J$6),Productos!AL13+('Insumos y gastos'!$K$15*Productos!AI13),IF(AND(AJ13="SI",AK13='Insumos y gastos'!$L$6),AL13+('Insumos y gastos'!$M$15*AI13*2),IF(AND(AJ13="NO",AK13='Insumos y gastos'!$L$6),Productos!AL13+('Insumos y gastos'!$M$15*Productos!AI13),IF(AND(AJ13="SI",AK13='Insumos y gastos'!$N$6),AL13+('Insumos y gastos'!$O$15*AI13*2),IF(AND(AJ13="NO",AK13='Insumos y gastos'!$N$6),Productos!AL13+('Insumos y gastos'!$O$15*Productos!AI13),IF(AND(AJ13="SI",AK13='Insumos y gastos'!$P$6),AL13+('Insumos y gastos'!$Q$15*AI13*2),IF(AND(AJ13="NO",AK13='Insumos y gastos'!$P$6),Productos!AL13+('Insumos y gastos'!$Q$15*Productos!AI13),IF(AND(AJ13="SI",AK13='Insumos y gastos'!$R$6),AL13+('Insumos y gastos'!$S$15*AI13*2),IF(AND(AJ13="NO",AK13='Insumos y gastos'!$R$6),Productos!AL13+('Insumos y gastos'!$S$15*Productos!AI13),IF(AND(AJ13="SI",AK13='Insumos y gastos'!$T$6),AL13+('Insumos y gastos'!$U$15*AI13*2),IF(AND(AJ13="NO",AK13='Insumos y gastos'!$T$6),Productos!AL13+('Insumos y gastos'!$U$15*Productos!AI13),0)))))))))))) -> 0 | AO13: =IFERROR(VLOOKUP(AN13,Tabla1[[#All],[Nombre insumo]:[Pr. Unidad]],4,0),0) -> 0 | AQ13: =IF(Tabla3[[#This Row],[Costo insumo 1]]>0,Tabla3[[#This Row],[Cantidad insumo 1]]*Tabla3[[#This Row],[Costo insumo 1]],0) -> 0 | AS13: =IFERROR(VLOOKUP(AR13,Tabla1[[#All],[Nombre insumo]:[Pr. Unidad]],4,0),0) -> 0 | AU13: =IF(Tabla3[[#This Row],[Costo insumo 2]]>0,Tabla3[[#This Row],[Cantidad insumo 2]]*Tabla3[[#This Row],[Costo insumo 2]],0) -> 0 | AW13: =IFERROR(VLOOKUP(AV13,Tabla1[[#All],[Nombre insumo]:[Pr. Unidad]],4,0),0) -> 0 | AY13: =IF(Tabla3[[#This Row],[Costo insumo 3]]>0,Tabla3[[#This Row],[Cantidad insumo 3]]*Tabla3[[#This Row],[Costo insumo 3]],0) -> 0 | BA13: =IFERROR(VLOOKUP(AZ13,Tabla1[[#All],[Nombre insumo]:[Pr. Unidad]],4,0),0) -> 0 | BC13: =IF(Tabla3[[#This Row],[Costo insumo 4]]>0,Tabla3[[#This Row],[Cantidad insumo 4]]*Tabla3[[#This Row],[Costo insumo 4]],0) -> 0 | BE13: =IFERROR(VLOOKUP(BD13,Tabla1[[#All],[Nombre insumo]:[Pr. Unidad]],4,0),0) -> 0 | BG13: =IF(Tabla3[[#This Row],[Costo insumo 5]]>0,Tabla3[[#This Row],[Cantidad insumo 5]]*Tabla3[[#This Row],[Costo insumo 5]],0) -> 0 | BH13: =Tabla3[[#This Row],[Subtotal impresión 1]]+Tabla3[[#This Row],[Subtotal impresión 2]]+Tabla3[[#This Row],[Subtotal impresión 3]]+Tabla3[[#This Row],[Subtotal impresión 4]]+Tabla3[[#This Row],[Subtotal impresión 5]]+Tabla3[[#This Row],[Subtotal insumos 1]]+Tabla3[[#This Row],[Subtotal insumos 2]]+Tabla3[[#This Row],[Subtotal insumos 3]]+Tabla3[[#This Row],[Subtotal insumos 4]]+Tabla3[[#This Row],[Subtotal insumos 5]] -> 0 | BJ13: =BI13*'Insumos y gastos'!$M$50 -> 0 | BK13: =BI13*'Insumos y gastos'!$Q$24 -> 0 | BL13: =Tabla3[[#This Row],[Costo sin servicios]]+Tabla3[[#This Row],[Costo servicios]]+Tabla3[[#This Row],[Costo mano de obra]] -> 0
A14: 10012 | F14: =IFERROR(VLOOKUP(E14,Tabla1[[#All],[Nombre insumo]:[Pr. Unidad]],4,0),0) -> 0 | J14: =G14*F14 -> 0 | K14: =IF(AND(H14="SI",I14='Insumos y gastos'!$J$6),J14+('Insumos y gastos'!$K$15*G14*2),IF(AND(H14="NO",I14='Insumos y gastos'!$J$6),Productos!J14+('Insumos y gastos'!$K$15*Productos!G14),IF(AND(H14="SI",I14='Insumos y gastos'!$L$6),J14+('Insumos y gastos'!$M$15*G14*2),IF(AND(H14="NO",I14='Insumos y gastos'!$L$6),Productos!J14+('Insumos y gastos'!$M$15*Productos!G14),IF(AND(H14="SI",I14='Insumos y gastos'!$N$6),J14+('Insumos y gastos'!$O$15*G14*2),IF(AND(H14="NO",I14='Insumos y gastos'!$N$6),Productos!J14+('Insumos y gastos'!$O$15*Productos!G14),IF(AND(H14="SI",I14='Insumos y gastos'!$P$6),J14+('Insumos y gastos'!$Q$15*G14*2),IF(AND(H14="NO",I14='Insumos y gastos'!$P$6),Productos!J14+('Insumos y gastos'!$Q$15*Productos!G14),IF(AND(H14="SI",I14='Insumos y gastos'!$R$6),J14+('Insumos y gastos'!$S$15*G14*2),IF(AND(H14="NO",I14='Insumos y gastos'!$R$6),Productos!J14+('Insumos y gastos'!$S$15*Productos!G14),IF(AND(H14="SI",I14='Insumos y gastos'!$T$6),J14+('Insumos y gastos'!$U$15*G14*2),IF(AND(H14="NO",I14='Insumos y gastos'!$T$6),Productos!J14+('Insumos y gastos'!$U$15*Productos!G14),0)))))))))))) -> 0 | M14: =IFERROR(VLOOKUP(L14,Tabla1[[#All],[Nombre insumo]:[Pr. Unidad]],4,0),0) -> 0 | Q14: =N14*M14 -> 0 | R14: =IF(AND(O14="SI",P14='Insumos y gastos'!$J$6),Q14+('Insumos y gastos'!$K$15*N14*2),IF(AND(O14="NO",P14='Insumos y gastos'!$J$6),Productos!Q14+('Insumos y gastos'!$K$15*Productos!N14),IF(AND(O14="SI",P14='Insumos y gastos'!$L$6),Q14+('Insumos y gastos'!$M$15*N14*2),IF(AND(O14="NO",P14='Insumos y gastos'!$L$6),Productos!Q14+('Insumos y gastos'!$M$15*Productos!N14),IF(AND(O14="SI",P14='Insumos y gastos'!$N$6),Q14+('Insumos y gastos'!$O$15*N14*2),IF(AND(O14="NO",P14='Insumos y gastos'!$N$6),Productos!Q14+('Insumos y gastos'!$O$15*Productos!N14),IF(AND(O14="SI",P14='Insumos y gastos'!$P$6),Q14+('Insumos y gastos'!$Q$15*N14*2),IF(AND(O14="NO",P14='Insumos y gastos'!$P$6),Productos!Q14+('Insumos y gastos'!$Q$15*Productos!N14),IF(AND(O14="SI",P14='Insumos y gastos'!$R$6),Q14+('Insumos y gastos'!$S$15*N14*2),IF(AND(O14="NO",P14='Insumos y gastos'!$R$6),Productos!Q14+('Insumos y gastos'!$S$15*Productos!N14),IF(AND(O14="SI",P14='Insumos y gastos'!$T$6),Q14+('Insumos y gastos'!$U$15*N14*2),IF(AND(O14="NO",P14='Insumos y gastos'!$T$6),Productos!Q14+('Insumos y gastos'!$U$15*Productos!N14),0)))))))))))) -> 0 | T14: =IFERROR(VLOOKUP(S14,Tabla1[[#All],[Nombre insumo]:[Pr. Unidad]],4,0),0) -> 0 | X14: =U14*T14 -> 0 | Y14: =IF(AND(V14="SI",W14='Insumos y gastos'!$J$6),X14+('Insumos y gastos'!$K$15*U14*2),IF(AND(V14="NO",W14='Insumos y gastos'!$J$6),Productos!X14+('Insumos y gastos'!$K$15*Productos!U14),IF(AND(V14="SI",W14='Insumos y gastos'!$L$6),X14+('Insumos y gastos'!$M$15*U14*2),IF(AND(V14="NO",W14='Insumos y gastos'!$L$6),Productos!X14+('Insumos y gastos'!$M$15*Productos!U14),IF(AND(V14="SI",W14='Insumos y gastos'!$N$6),X14+('Insumos y gastos'!$O$15*U14*2),IF(AND(V14="NO",W14='Insumos y gastos'!$N$6),Productos!X14+('Insumos y gastos'!$O$15*Productos!U14),IF(AND(V14="SI",W14='Insumos y gastos'!$P$6),X14+('Insumos y gastos'!$Q$15*U14*2),IF(AND(V14="NO",W14='Insumos y gastos'!$P$6),Productos!X14+('Insumos y gastos'!$Q$15*Productos!U14),IF(AND(V14="SI",W14='Insumos y gastos'!$R$6),X14+('Insumos y gastos'!$S$15*U14*2),IF(AND(V14="NO",W14='Insumos y gastos'!$R$6),Productos!X14+('Insumos y gastos'!$S$15*Productos!U14),IF(AND(V14="SI",W14='Insumos y gastos'!$T$6),X14+('Insumos y gastos'!$U$15*U14*2),IF(AND(V14="NO",W14='Insumos y gastos'!$T$6),Productos!X14+('Insumos y gastos'!$U$15*Productos!U14),0)))))))))))) -> 0 | AA14: =IFERROR(VLOOKUP(Z14,Tabla1[[#All],[Nombre insumo]:[Pr. Unidad]],4,0),0) -> 0 | AE14: =AB14*AA14 -> 0 | AF14: =IF(AND(AC14="SI",AD14='Insumos y gastos'!$J$6),AE14+('Insumos y gastos'!$K$15*AB14*2),IF(AND(AC14="NO",AD14='Insumos y gastos'!$J$6),Productos!AE14+('Insumos y gastos'!$K$15*Productos!AB14),IF(AND(AC14="SI",AD14='Insumos y gastos'!$L$6),AE14+('Insumos y gastos'!$M$15*AB14*2),IF(AND(AC14="NO",AD14='Insumos y gastos'!$L$6),Productos!AE14+('Insumos y gastos'!$M$15*Productos!AB14),IF(AND(AC14="SI",AD14='Insumos y gastos'!$N$6),AE14+('Insumos y gastos'!$O$15*AB14*2),IF(AND(AC14="NO",AD14='Insumos y gastos'!$N$6),Productos!AE14+('Insumos y gastos'!$O$15*Productos!AB14),IF(AND(AC14="SI",AD14='Insumos y gastos'!$P$6),AE14+('Insumos y gastos'!$Q$15*AB14*2),IF(AND(AC14="NO",AD14='Insumos y gastos'!$P$6),Productos!AE14+('Insumos y gastos'!$Q$15*Productos!AB14),IF(AND(AC14="SI",AD14='Insumos y gastos'!$R$6),AE14+('Insumos y gastos'!$S$15*AB14*2),IF(AND(AC14="NO",AD14='Insumos y gastos'!$R$6),Productos!AE14+('Insumos y gastos'!$S$15*Productos!AB14),IF(AND(AC14="SI",AD14='Insumos y gastos'!$T$6),AE14+('Insumos y gastos'!$U$15*AB14*2),IF(AND(AC14="NO",AD14='Insumos y gastos'!$T$6),Productos!AE14+('Insumos y gastos'!$U$15*Productos!AB14),0)))))))))))) -> 0 | AH14: =IFERROR(VLOOKUP(AG14,Tabla1[[#All],[Nombre insumo]:[Pr. Unidad]],4,0),0) -> 0 | AL14: =AI14*AH14 -> 0 | AM14: =IF(AND(AJ14="SI",AK14='Insumos y gastos'!$J$6),AL14+('Insumos y gastos'!$K$15*AI14*2),IF(AND(AJ14="NO",AK14='Insumos y gastos'!$J$6),Productos!AL14+('Insumos y gastos'!$K$15*Productos!AI14),IF(AND(AJ14="SI",AK14='Insumos y gastos'!$L$6),AL14+('Insumos y gastos'!$M$15*AI14*2),IF(AND(AJ14="NO",AK14='Insumos y gastos'!$L$6),Productos!AL14+('Insumos y gastos'!$M$15*Productos!AI14),IF(AND(AJ14="SI",AK14='Insumos y gastos'!$N$6),AL14+('Insumos y gastos'!$O$15*AI14*2),IF(AND(AJ14="NO",AK14='Insumos y gastos'!$N$6),Productos!AL14+('Insumos y gastos'!$O$15*Productos!AI14),IF(AND(AJ14="SI",AK14='Insumos y gastos'!$P$6),AL14+('Insumos y gastos'!$Q$15*AI14*2),IF(AND(AJ14="NO",AK14='Insumos y gastos'!$P$6),Productos!AL14+('Insumos y gastos'!$Q$15*Productos!AI14),IF(AND(AJ14="SI",AK14='Insumos y gastos'!$R$6),AL14+('Insumos y gastos'!$S$15*AI14*2),IF(AND(AJ14="NO",AK14='Insumos y gastos'!$R$6),Productos!AL14+('Insumos y gastos'!$S$15*Productos!AI14),IF(AND(AJ14="SI",AK14='Insumos y gastos'!$T$6),AL14+('Insumos y gastos'!$U$15*AI14*2),IF(AND(AJ14="NO",AK14='Insumos y gastos'!$T$6),Productos!AL14+('Insumos y gastos'!$U$15*Productos!AI14),0)))))))))))) -> 0 | AO14: =IFERROR(VLOOKUP(AN14,Tabla1[[#All],[Nombre insumo]:[Pr. Unidad]],4,0),0) -> 0 | AQ14: =IF(Tabla3[[#This Row],[Costo insumo 1]]>0,Tabla3[[#This Row],[Cantidad insumo 1]]*Tabla3[[#This Row],[Costo insumo 1]],0) -> 0 | AS14: =IFERROR(VLOOKUP(AR14,Tabla1[[#All],[Nombre insumo]:[Pr. Unidad]],4,0),0) -> 0 | AU14: =IF(Tabla3[[#This Row],[Costo insumo 2]]>0,Tabla3[[#This Row],[Cantidad insumo 2]]*Tabla3[[#This Row],[Costo insumo 2]],0) -> 0 | AW14: =IFERROR(VLOOKUP(AV14,Tabla1[[#All],[Nombre insumo]:[Pr. Unidad]],4,0),0) -> 0 | AY14: =IF(Tabla3[[#This Row],[Costo insumo 3]]>0,Tabla3[[#This Row],[Cantidad insumo 3]]*Tabla3[[#This Row],[Costo insumo 3]],0) -> 0 | BA14: =IFERROR(VLOOKUP(AZ14,Tabla1[[#All],[Nombre insumo]:[Pr. Unidad]],4,0),0) -> 0 | BC14: =IF(Tabla3[[#This Row],[Costo insumo 4]]>0,Tabla3[[#This Row],[Cantidad insumo 4]]*Tabla3[[#This Row],[Costo insumo 4]],0) -> 0 | BE14: =IFERROR(VLOOKUP(BD14,Tabla1[[#All],[Nombre insumo]:[Pr. Unidad]],4,0),0) -> 0 | BG14: =IF(Tabla3[[#This Row],[Costo insumo 5]]>0,Tabla3[[#This Row],[Cantidad insumo 5]]*Tabla3[[#This Row],[Costo insumo 5]],0) -> 0 | BH14: =Tabla3[[#This Row],[Subtotal impresión 1]]+Tabla3[[#This Row],[Subtotal impresión 2]]+Tabla3[[#This Row],[Subtotal impresión 3]]+Tabla3[[#This Row],[Subtotal impresión 4]]+Tabla3[[#This Row],[Subtotal impresión 5]]+Tabla3[[#This Row],[Subtotal insumos 1]]+Tabla3[[#This Row],[Subtotal insumos 2]]+Tabla3[[#This Row],[Subtotal insumos 3]]+Tabla3[[#This Row],[Subtotal insumos 4]]+Tabla3[[#This Row],[Subtotal insumos 5]] -> 0 | BJ14: =BI14*'Insumos y gastos'!$M$50 -> 0 | BK14: =BI14*'Insumos y gastos'!$Q$24 -> 0 | BL14: =Tabla3[[#This Row],[Costo sin servicios]]+Tabla3[[#This Row],[Costo servicios]]+Tabla3[[#This Row],[Costo mano de obra]] -> 0
... A26: 10024 | F26: =IFERROR(VLOOKUP(E26,Tabla1[[#All],[Nombre insumo]:[Pr. Unidad]],4,0),0) -> 0 | J26: =G26*F26 -> 0 | K26: =IF(AND(H26="SI",I26='Insumos y gastos'!$J$6),J26+('Insumos y gastos'!$K$15*G26*2),IF(AND(H26="NO",I26='Insumos y gastos'!$J$6),Productos!J26+('Insumos y gastos'!$K$15*Productos!G26),IF(AND(H26="SI",I26='Insumos y gastos'!$L$6),J26+('Insumos y gastos'!$M$15*G26*2),IF(AND(H26="NO",I26='Insumos y gastos'!$L$6),Productos!J26+('Insumos y gastos'!$M$15*Productos!G26),IF(AND(H26="SI",I26='Insumos y gastos'!$N$6),J26+('Insumos y gastos'!$O$15*G26*2),IF(AND(H26="NO",I26='Insumos y gastos'!$N$6),Productos!J26+('Insumos y gastos'!$O$15*Productos!G26),IF(AND(H26="SI",I26='Insumos y gastos'!$P$6),J26+('Insumos y gastos'!$Q$15*G26*2),IF(AND(H26="NO",I26='Insumos y gastos'!$P$6),Productos!J26+('Insumos y gastos'!$Q$15*Productos!G26),IF(AND(H26="SI",I26='Insumos y gastos'!$R$6),J26+('Insumos y gastos'!$S$15*G26*2),IF(AND(H26="NO",I26='Insumos y gastos'!$R$6),Productos!J26+('Insumos y gastos'!$S$15*Productos!G26),IF(AND(H26="SI",I26='Insumos y gastos'!$T$6),J26+('Insumos y gastos'!$U$15*G26*2),IF(AND(H26="NO",I26='Insumos y gastos'!$T$6),Productos!J26+('Insumos y gastos'!$U$15*Productos!G26),0)))))))))))) -> 0 | M26: =IFERROR(VLOOKUP(L26,Tabla1[[#All],[Nombre insumo]:[Pr. Unidad]],4,0),0) -> 0 | Q26: =N26*M26 -> 0 | R26: =IF(AND(O26="SI",P26='Insumos y gastos'!$J$6),Q26+('Insumos y gastos'!$K$15*N26*2),IF(AND(O26="NO",P26='Insumos y gastos'!$J$6),Productos!Q26+('Insumos y gastos'!$K$15*Productos!N26),IF(AND(O26="SI",P26='Insumos y gastos'!$L$6),Q26+('Insumos y gastos'!$M$15*N26*2),IF(AND(O26="NO",P26='Insumos y gastos'!$L$6),Productos!Q26+('Insumos y gastos'!$M$15*Productos!N26),IF(AND(O26="SI",P26='Insumos y gastos'!$N$6),Q26+('Insumos y gastos'!$O$15*N26*2),IF(AND(O26="NO",P26='Insumos y gastos'!$N$6),Productos!Q26+('Insumos y gastos'!$O$15*Productos!N26),IF(AND(O26="SI",P26='Insumos y gastos'!$P$6),Q26+('Insumos y gastos'!$Q$15*N26*2),IF(AND(O26="NO",P26='Insumos y gastos'!$P$6),Productos!Q26+('Insumos y gastos'!$Q$15*Productos!N26),IF(AND(O26="SI",P26='Insumos y gastos'!$R$6),Q26+('Insumos y gastos'!$S$15*N26*2),IF(AND(O26="NO",P26='Insumos y gastos'!$R$6),Productos!Q26+('Insumos y gastos'!$S$15*Productos!N26),IF(AND(O26="SI",P26='Insumos y gastos'!$T$6),Q26+('Insumos y gastos'!$U$15*N26*2),IF(AND(O26="NO",P26='Insumos y gastos'!$T$6),Productos!Q26+('Insumos y gastos'!$U$15*Productos!N26),0)))))))))))) -> 0 | T26: =IFERROR(VLOOKUP(S26,Tabla1[[#All],[Nombre insumo]:[Pr. Unidad]],4,0),0) -> 0 | X26: =U26*T26 -> 0 | Y26: =IF(AND(V26="SI",W26='Insumos y gastos'!$J$6),X26+('Insumos y gastos'!$K$15*U26*2),IF(AND(V26="NO",W26='Insumos y gastos'!$J$6),Productos!X26+('Insumos y gastos'!$K$15*Productos!U26),IF(AND(V26="SI",W26='Insumos y gastos'!$L$6),X26+('Insumos y gastos'!$M$15*U26*2),IF(AND(V26="NO",W26='Insumos y gastos'!$L$6),Productos!X26+('Insumos y gastos'!$M$15*Productos!U26),IF(AND(V26="SI",W26='Insumos y gastos'!$N$6),X26+('Insumos y gastos'!$O$15*U26*2),IF(AND(V26="NO",W26='Insumos y gastos'!$N$6),Productos!X26+('Insumos y gastos'!$O$15*Productos!U26),IF(AND(V26="SI",W26='Insumos y gastos'!$P$6),X26+('Insumos y gastos'!$Q$15*U26*2),IF(AND(V26="NO",W26='Insumos y gastos'!$P$6),Productos!X26+('Insumos y gastos'!$Q$15*Productos!U26),IF(AND(V26="SI",W26='Insumos y gastos'!$R$6),X26+('Insumos y gastos'!$S$15*U26*2),IF(AND(V26="NO",W26='Insumos y gastos'!$R$6),Productos!X26+('Insumos y gastos'!$S$15*Productos!U26),IF(AND(V26="SI",W26='Insumos y gastos'!$T$6),X26+('Insumos y gastos'!$U$15*U26*2),IF(AND(V26="NO",W26='Insumos y gastos'!$T$6),Productos!X26+('Insumos y gastos'!$U$15*Productos!U26),0)))))))))))) -> 0 | AA26: =IFERROR(VLOOKUP(Z26,Tabla1[[#All],[Nombre insumo]:[Pr. Unidad]],4,0),0) -> 0 | AE26: =AB26*AA26 -> 0 | AF26: =IF(AND(AC26="SI",AD26='Insumos y gastos'!$J$6),AE26+('Insumos y gastos'!$K$15*AB26*2),IF(AND(AC26="NO",AD26='Insumos y gastos'!$J$6),Productos!AE26+('Insumos y gastos'!$K$15*Productos!AB26),IF(AND(AC26="SI",AD26='Insumos y gastos'!$L$6),AE26+('Insumos y gastos'!$M$15*AB26*2),IF(AND(AC26="NO",AD26='Insumos y gastos'!$L$6),Productos!AE26+('Insumos y gastos'!$M$15*Productos!AB26),IF(AND(AC26="SI",AD26='Insumos y gastos'!$N$6),AE26+('Insumos y gastos'!$O$15*AB26*2),IF(AND(AC26="NO",AD26='Insumos y gastos'!$N$6),Productos!AE26+('Insumos y gastos'!$O$15*Productos!AB26),IF(AND(AC26="SI",AD26='Insumos y gastos'!$P$6),AE26+('Insumos y gastos'!$Q$15*AB26*2),IF(AND(AC26="NO",AD26='Insumos y gastos'!$P$6),Productos!AE26+('Insumos y gastos'!$Q$15*Productos!AB26),IF(AND(AC26="SI",AD26='Insumos y gastos'!$R$6),AE26+('Insumos y gastos'!$S$15*AB26*2),IF(AND(AC26="NO",AD26='Insumos y gastos'!$R$6),Productos!AE26+('Insumos y gastos'!$S$15*Productos!AB26),IF(AND(AC26="SI",AD26='Insumos y gastos'!$T$6),AE26+('Insumos y gastos'!$U$15*AB26*2),IF(AND(AC26="NO",AD26='Insumos y gastos'!$T$6),Productos!AE26+('Insumos y gastos'!$U$15*Productos!AB26),0)))))))))))) -> 0 | AH26: =IFERROR(VLOOKUP(AG26,Tabla1[[#All],[Nombre insumo]:[Pr. Unidad]],4,0),0) -> 0 | AL26: =AI26*AH26 -> 0 | AM26: =IF(AND(AJ26="SI",AK26='Insumos y gastos'!$J$6),AL26+('Insumos y gastos'!$K$15*AI26*2),IF(AND(AJ26="NO",AK26='Insumos y gastos'!$J$6),Productos!AL26+('Insumos y gastos'!$K$15*Productos!AI26),IF(AND(AJ26="SI",AK26='Insumos y gastos'!$L$6),AL26+('Insumos y gastos'!$M$15*AI26*2),IF(AND(AJ26="NO",AK26='Insumos y gastos'!$L$6),Productos!AL26+('Insumos y gastos'!$M$15*Productos!AI26),IF(AND(AJ26="SI",AK26='Insumos y gastos'!$N$6),AL26+('Insumos y gastos'!$O$15*AI26*2),IF(AND(AJ26="NO",AK26='Insumos y gastos'!$N$6),Productos!AL26+('Insumos y gastos'!$O$15*Productos!AI26),IF(AND(AJ26="SI",AK26='Insumos y gastos'!$P$6),AL26+('Insumos y gastos'!$Q$15*AI26*2),IF(AND(AJ26="NO",AK26='Insumos y gastos'!$P$6),Productos!AL26+('Insumos y gastos'!$Q$15*Productos!AI26),IF(AND(AJ26="SI",AK26='Insumos y gastos'!$R$6),AL26+('Insumos y gastos'!$S$15*AI26*2),IF(AND(AJ26="NO",AK26='Insumos y gastos'!$R$6),Productos!AL26+('Insumos y gastos'!$S$15*Productos!AI26),IF(AND(AJ26="SI",AK26='Insumos y gastos'!$T$6),AL26+('Insumos y gastos'!$U$15*AI26*2),IF(AND(AJ26="NO",AK26='Insumos y gastos'!$T$6),Productos!AL26+('Insumos y gastos'!$U$15*Productos!AI26),0)))))))))))) -> 0 | AO26: =IFERROR(VLOOKUP(AN26,Tabla1[[#All],[Nombre insumo]:[Pr. Unidad]],4,0),0) -> 0 | AQ26: =IF(Tabla3[[#This Row],[Costo insumo 1]]>0,Tabla3[[#This Row],[Cantidad insumo 1]]*Tabla3[[#This Row],[Costo insumo 1]],0) -> 0 | AS26: =IFERROR(VLOOKUP(AR26,Tabla1[[#All],[Nombre insumo]:[Pr. Unidad]],4,0),0) -> 0 | AU26: =IF(Tabla3[[#This Row],[Costo insumo 2]]>0,Tabla3[[#This Row],[Cantidad insumo 2]]*Tabla3[[#This Row],[Costo insumo 2]],0) -> 0 | AW26: =IFERROR(VLOOKUP(AV26,Tabla1[[#All],[Nombre insumo]:[Pr. Unidad]],4,0),0) -> 0 | AY26: =IF(Tabla3[[#This Row],[Costo insumo 3]]>0,Tabla3[[#This Row],[Cantidad insumo 3]]*Tabla3[[#This Row],[Costo insumo 3]],0) -> 0 | BA26: =IFERROR(VLOOKUP(AZ26,Tabla1[[#All],[Nombre insumo]:[Pr. Unidad]],4,0),0) -> 0 | BC26: =IF(Tabla3[[#This Row],[Costo insumo 4]]>0,Tabla3[[#This Row],[Cantidad insumo 4]]*Tabla3[[#This Row],[Costo insumo 4]],0) -> 0 | BE26: =IFERROR(VLOOKUP(BD26,Tabla1[[#All],[Nombre insumo]:[Pr. Unidad]],4,0),0) -> 0 | BG26: =IF(Tabla3[[#This Row],[Costo insumo 5]]>0,Tabla3[[#This Row],[Cantidad insumo 5]]*Tabla3[[#This Row],[Costo insumo 5]],0) -> 0 | BH26: =Tabla3[[#This Row],[Subtotal impresión 1]]+Tabla3[[#This Row],[Subtotal impresión 2]]+Tabla3[[#This Row],[Subtotal impresión 3]]+Tabla3[[#This Row],[Subtotal impresión 4]]+Tabla3[[#This Row],[Subtotal impresión 5]]+Tabla3[[#This Row],[Subtotal insumos 1]]+Tabla3[[#This Row],[Subtotal insumos 2]]+Tabla3[[#This Row],[Subtotal insumos 3]]+Tabla3[[#This Row],[Subtotal insumos 4]]+Tabla3[[#This Row],[Subtotal insumos 5]] -> 0 | BJ26: =BI26*'Insumos y gastos'!$M$50 -> 0 | BK26: =BI26*'Insumos y gastos'!$Q$24 -> 0 | BL26: =Tabla3[[#This Row],[Costo sin servicios]]+Tabla3[[#This Row],[Costo servicios]]+Tabla3[[#This Row],[Costo mano de obra]] -> 0

Sheet Lista de precios
B7: Tabla de costos y precios
B10: Por rubro y subrubro ❤
B11: SKU | C11: Nombre producto | D11: RUBRO | E11: SUBRUBRO | F11: Costo total | G11: Porcentaje | H11: Precio sugerido | I11: Precio venta | J11: Ganancia
B12: 10001 | C12: (en blanco) | D12: (en blanco) | E12: (en blanco) | F12: 0 | H12: =G12*F12 -> 0 | J12: =I12-F12 -> 0
B13: 10002 | C13: (en blanco) | D13: (en blanco) | E13: (en blanco) | F13: 0 | H13: =G13*F13 -> 0 | J13: =I13-F13 -> 0
B14: 10003 | C14: (en blanco) | D14: (en blanco) | E14: (en blanco) | F14: 0 | H14: =G14*F14 -> 0 | J14: =I14-F14 -> 0
B15: 10004 | C15: (en blanco) | D15: (en blanco) | E15: (en blanco) | F15: 0 | H15: =G15*F15 -> 0 | J15: =I15-F15 -> 0
B16: 10005 | C16: (en blanco) | D16: (en blanco) | E16: (en blanco) | F16: 0 | H16: =G16*F16 -> 0 | J16: =I16-F16 -> 0
B17: 10006 | C17: (en blanco) | D17: (en blanco) | E17: (en blanco) | F17: 0 | H17: =G17*F17 -> 0 | J17: =I17-F17 -> 0
B18: 10007 | C18: (en blanco) | D18: (en blanco) | E18: (en blanco) | F18: 0 | H18: =G18*F18 -> 0 | J18: =I18-F18 -> 0
B19: 10008 | C19: (en blanco) | D19: (en blanco) | E19: (en blanco) | F19: 0 | H19: =G19*F19 -> 0 | J19: =I19-F19 -> 0
B20: 10009 | C20: (en blanco) | D20: (en blanco) | E20: (en blanco) | F20: 0 | H20: =G20*F20 -> 0 | J20: =I20-F20 -> 0
B21: 10010 | C21: (en blanco) | D21: (en blanco) | E21: (en blanco) | F21: 0 | H21: =G21*F21 -> 0 | J21: =I21-F21 -> 0
B22: 10011 | C22: (en blanco) | D22: (en blanco) | E22: (en blanco) | F22: 0 | H22: =G22*F22 -> 0 | J22: =I22-F22 -> 0
B23: 10012 | C23: (en blanco) | D23: (en blanco) | E23: (en blanco) | F23: 0 | H23: =G23*F23 -> 0 | J23: =I23-F23 -> 0
... B35: 10024 | C35: (en blanco) | D35: (en blanco) | E35: (en blanco) | F35: 0 | H35: =G35*F35 -> 0 | J35: =I35-F35 -> 0
